{
"SERV_ID":"OA_LDR_ACTION",
"SERV_QUERY_MODE":"1",
"SERV_WF_FLAG":"0",
"SERV_DELETE_FLAG":"2",
"S_PUBLIC":"1",
"SERV_PAGE_COUNT":"50",
"SERV_PID":"",
"SERV_SEARCH_FLAG":"2",
"SERV_TYPE":"1",
"SERV_CMPY":"",
"SERV_NAME":"领导活动",
"SERV_CLASS":"com.rh.oa.ldr.LeaderActServ",
"SERV_SRC_ID":"",
"S_USER":"yangjinyun",
"SERV_RED_HEAD":"",
"SERV_MOBILE_LIST":"",
"_ROWNUM_":"0",
"SERV_SQL_WHERE":"",
"SERV_NAV_ITEMS":"",
"TABLE_ACTION":"OA_LDR_ACTION",
"SERV_DATA_SOURCE":"",
"SERV_CARD_STYLE":"2",
"SY_SERV_ACT":
[
{
"SERV_ID":"OA_LDR_ACTION",
"ACT_WS_RESULT":"",
"S_FLAG":"1",
"ACT_LOG_FLAG":"2",
"ACT_ID":"2OuO0TwfZ9NVhGJSYMW1xD",
"ACT_HOT_KEY":"",
"S_MTIME":"2013-01-30 15:13:21:761",
"_ROWNUM_":"0",
"ACT_TYPE":"3",
"ACT_TIP":"",
"_PK_":"2OuO0TwfZ9NVhGJSYMW1xD",
"ACT_WS_FLAG":"2",
"ACT_GROUP":"2",
"ACT_NAME":" 查 看 ",
"ACT_CSS":"byid",
"ACT_EXPRESSION":"",
"ACT_MEMO":"",
"SY_SERV_ACT_PARAM":
[
],
"ACT_ORDER":"10",
"ACT_MOBILE_FLAG":"",
"LIST_DIS_GROUP":"",
"ACT_CODE":"byid",
"ACT_EXPRESSION_FLAG":"0"
},
{
"SERV_ID":"OA_LDR_ACTION",
"ACT_WS_RESULT":"",
"S_FLAG":"1",
"ACT_LOG_FLAG":"2",
"ACT_ID":"1w_RGtdlN5W9naf_NdDUjV",
"ACT_HOT_KEY":"",
"S_MTIME":"2016-02-22 18:26:00:077",
"_ROWNUM_":"1",
"ACT_TYPE":"1",
"ACT_TIP":"",
"_PK_":"1w_RGtdlN5W9naf_NdDUjV",
"ACT_WS_FLAG":"2",
"ACT_GROUP":"1",
"ACT_NAME":" 新 建",
"ACT_CSS":"add",
"ACT_EXPRESSION":"",
"ACT_MEMO":"",
"SY_SERV_ACT_PARAM":
[
],
"ACT_ORDER":"20",
"ACT_MOBILE_FLAG":"",
"LIST_DIS_GROUP":"",
"ACT_CODE":"add",
"ACT_EXPRESSION_FLAG":"0"
},
{
"SERV_ID":"OA_LDR_ACTION",
"ACT_WS_RESULT":"",
"S_FLAG":"2",
"ACT_LOG_FLAG":"2",
"ACT_ID":"0uVa4SPRp8_WnS0Xm4FSJ-",
"ACT_HOT_KEY":"",
"S_MTIME":"2013-01-30 15:13:21:761",
"_ROWNUM_":"2",
"ACT_TYPE":"1",
"ACT_TIP":"",
"_PK_":"0uVa4SPRp8_WnS0Xm4FSJ-",
"ACT_WS_FLAG":"2",
"ACT_GROUP":"1",
"ACT_NAME":" 保 存 ",
"ACT_CSS":"batchSave",
"ACT_EXPRESSION":"",
"ACT_MEMO":"",
"SY_SERV_ACT_PARAM":
[
],
"ACT_ORDER":"30",
"ACT_MOBILE_FLAG":"",
"LIST_DIS_GROUP":"",
"ACT_CODE":"batchSave",
"ACT_EXPRESSION_FLAG":"0"
},
{
"SERV_ID":"OA_LDR_ACTION",
"ACT_WS_RESULT":"",
"S_FLAG":"1",
"ACT_LOG_FLAG":"2",
"ACT_ID":"1zGsS_fKh3uqDuqbj3bWUI",
"ACT_HOT_KEY":"",
"S_MTIME":"2013-05-06 12:17:26:328",
"_ROWNUM_":"3",
"ACT_TYPE":"2",
"ACT_TIP":"满足以下条件的数据显示保存按钮：未发布，且审核状态为：未送审、不审核、审核不通过",
"_PK_":"1zGsS_fKh3uqDuqbj3bWUI",
"ACT_WS_FLAG":"2",
"ACT_GROUP":"1",
"ACT_NAME":" 保 存 ",
"ACT_CSS":"save",
"ACT_EXPRESSION":"'#ACT_STATE#' == '2' && ('#CHK_STATE#'  == '1'  || '#CHK_STATE#' == '15'  || '#CHK_STATE#' == '20');",
"ACT_MEMO":"",
"SY_SERV_ACT_PARAM":
[
],
"ACT_ORDER":"50",
"ACT_MOBILE_FLAG":"",
"LIST_DIS_GROUP":"",
"ACT_CODE":"save",
"ACT_EXPRESSION_FLAG":"0"
},
{
"SERV_ID":"OA_LDR_ACTION",
"ACT_WS_RESULT":"",
"S_FLAG":"2",
"ACT_LOG_FLAG":"2",
"ACT_ID":"1RxqdR_jh3THy2U-yBiob_",
"ACT_HOT_KEY":"",
"S_MTIME":"2013-01-30 15:13:21:761",
"_ROWNUM_":"4",
"ACT_TYPE":"2",
"ACT_TIP":"",
"_PK_":"1RxqdR_jh3THy2U-yBiob_",
"ACT_WS_FLAG":"2",
"ACT_GROUP":"1",
"ACT_NAME":"复制并新建",
"ACT_CSS":"copy",
"ACT_EXPRESSION":"'#_ADD_#'==''",
"ACT_MEMO":"",
"SY_SERV_ACT_PARAM":
[
],
"ACT_ORDER":"60",
"ACT_MOBILE_FLAG":"",
"LIST_DIS_GROUP":"",
"ACT_CODE":"copyNew",
"ACT_EXPRESSION_FLAG":"0"
},
{
"SERV_ID":"OA_LDR_ACTION",
"ACT_WS_RESULT":"",
"S_FLAG":"2",
"ACT_LOG_FLAG":"2",
"ACT_ID":"1XiFFXI-92QFwR9JMQUbUH",
"ACT_HOT_KEY":"",
"S_MTIME":"2013-01-30 15:13:21:761",
"_ROWNUM_":"5",
"ACT_TYPE":"2",
"ACT_TIP":"",
"_PK_":"1XiFFXI-92QFwR9JMQUbUH",
"ACT_WS_FLAG":"2",
"ACT_GROUP":"2",
"ACT_NAME":"变更历史",
"ACT_CSS":"search",
"ACT_EXPRESSION":"'#_ADD_#'==''",
"ACT_MEMO":"",
"SY_SERV_ACT_PARAM":
[
],
"ACT_ORDER":"70",
"ACT_MOBILE_FLAG":"",
"LIST_DIS_GROUP":"",
"ACT_CODE":"logItem",
"ACT_EXPRESSION_FLAG":"0"
},
{
"SERV_ID":"OA_LDR_ACTION",
"ACT_WS_RESULT":"",
"S_FLAG":"1",
"ACT_LOG_FLAG":"1",
"ACT_ID":"1C-DHYVBZeq9CZ3E_AOQrB",
"ACT_HOT_KEY":"",
"S_MTIME":"2013-05-06 11:44:40:168",
"_ROWNUM_":"6",
"ACT_TYPE":"1",
"ACT_TIP":"",
"_PK_":"1C-DHYVBZeq9CZ3E_AOQrB",
"ACT_WS_FLAG":"2",
"ACT_GROUP":"1",
"ACT_NAME":" 删 除 ",
"ACT_CSS":"delete",
"ACT_EXPRESSION":"'#_QUERYID_#' == '27ilzQzJl7qqmZ1OX-VNzV'",
"ACT_MEMO":"",
"SY_SERV_ACT_PARAM":
[
],
"ACT_ORDER":"100",
"ACT_MOBILE_FLAG":"",
"LIST_DIS_GROUP":"",
"ACT_CODE":"delete",
"ACT_EXPRESSION_FLAG":"0"
},
{
"SERV_ID":"OA_LDR_ACTION",
"ACT_WS_RESULT":"",
"S_FLAG":"2",
"ACT_LOG_FLAG":"2",
"ACT_ID":"2OfMJQoBd1LpnbPUz3zjid",
"ACT_HOT_KEY":"",
"S_MTIME":"2013-01-30 15:13:21:761",
"_ROWNUM_":"7",
"ACT_TYPE":"1",
"ACT_TIP":"",
"_PK_":"2OfMJQoBd1LpnbPUz3zjid",
"ACT_WS_FLAG":"2",
"ACT_GROUP":"1",
"ACT_NAME":" 导 入 ",
"ACT_CSS":"imp",
"ACT_EXPRESSION":"",
"ACT_MEMO":"",
"SY_SERV_ACT_PARAM":
[
],
"ACT_ORDER":"110",
"ACT_MOBILE_FLAG":"",
"LIST_DIS_GROUP":"",
"ACT_CODE":"imp",
"ACT_EXPRESSION_FLAG":"0"
},
{
"SERV_ID":"OA_LDR_ACTION",
"ACT_WS_RESULT":"",
"S_FLAG":"1",
"ACT_LOG_FLAG":"2",
"ACT_ID":"0854HXM2t6yUql2s5c9OXn",
"ACT_HOT_KEY":"",
"S_MTIME":"2013-05-06 12:02:58:772",
"_ROWNUM_":"8",
"ACT_TYPE":"1",
"ACT_TIP":"",
"_PK_":"0854HXM2t6yUql2s5c9OXn",
"ACT_WS_FLAG":"2",
"ACT_GROUP":"2",
"ACT_NAME":"送审核",
"ACT_CSS":"select",
"ACT_EXPRESSION":"'#_QUERYID_#' == '27ilzQzJl7qqmZ1OX-VNzV' || '#_QUERYID_#' == '0hwWetkTdaJHOX2soBroL_';",
"ACT_MEMO":"",
"SY_SERV_ACT_PARAM":
[
],
"ACT_ORDER":"120",
"ACT_MOBILE_FLAG":"",
"LIST_DIS_GROUP":"",
"ACT_CODE":"sendToChk",
"ACT_EXPRESSION_FLAG":"0"
},
{
"SERV_ID":"OA_LDR_ACTION",
"ACT_WS_RESULT":"",
"S_FLAG":"2",
"ACT_LOG_FLAG":"2",
"ACT_ID":"2W7jss69d9uUPg1wa1s-ON",
"ACT_HOT_KEY":"",
"S_MTIME":"2013-01-30 15:13:21:761",
"_ROWNUM_":"9",
"ACT_TYPE":"1",
"ACT_TIP":"",
"_PK_":"2W7jss69d9uUPg1wa1s-ON",
"ACT_WS_FLAG":"2",
"ACT_GROUP":"2",
"ACT_NAME":" 导 出 ",
"ACT_CSS":"exp",
"ACT_EXPRESSION":"",
"ACT_MEMO":"",
"SY_SERV_ACT_PARAM":
[
],
"ACT_ORDER":"120",
"ACT_MOBILE_FLAG":"",
"LIST_DIS_GROUP":"",
"ACT_CODE":"exp",
"ACT_EXPRESSION_FLAG":"0"
},
{
"SERV_ID":"OA_LDR_ACTION",
"ACT_WS_RESULT":"",
"S_FLAG":"1",
"ACT_LOG_FLAG":"2",
"ACT_ID":"1QmsVFyoAheH84vF1EYVFtrT",
"ACT_HOT_KEY":"",
"S_MTIME":"2013-05-06 12:03:43:583",
"_ROWNUM_":"10",
"ACT_TYPE":"2",
"ACT_TIP":"",
"_PK_":"1QmsVFyoAheH84vF1EYVFtrT",
"ACT_WS_FLAG":"2",
"ACT_GROUP":"2",
"ACT_NAME":"送审核",
"ACT_CSS":"default",
"ACT_EXPRESSION":"('#CHK_STATE#' == '1'  &&  '#_ADD_#' != 'true' ) || ('#CHK_STATE#' == '15' );",
"ACT_MEMO":"",
"SY_SERV_ACT_PARAM":
[
],
"ACT_ORDER":"120",
"ACT_MOBILE_FLAG":"",
"LIST_DIS_GROUP":"",
"ACT_CODE":"sendToChkCard",
"ACT_EXPRESSION_FLAG":"0"
},
{
"SERV_ID":"OA_LDR_ACTION",
"ACT_WS_RESULT":"",
"S_FLAG":"1",
"ACT_LOG_FLAG":"2",
"ACT_ID":"2Adt0PARJ4WUV9DjTRrge9",
"ACT_HOT_KEY":"",
"S_MTIME":"2013-05-06 11:51:04:351",
"_ROWNUM_":"11",
"ACT_TYPE":"2",
"ACT_TIP":"",
"_PK_":"2Adt0PARJ4WUV9DjTRrge9",
"ACT_WS_FLAG":"2",
"ACT_GROUP":"2",
"ACT_NAME":"取消发布",
"ACT_CSS":"delete",
"ACT_EXPRESSION":"'#ACT_STATE#' == 1;",
"ACT_MEMO":"",
"SY_SERV_ACT_PARAM":
[
],
"ACT_ORDER":"130",
"ACT_MOBILE_FLAG":"",
"LIST_DIS_GROUP":"",
"ACT_CODE":"cancelPublish",
"ACT_EXPRESSION_FLAG":"0"
},
{
"SERV_ID":"OA_LDR_ACTION",
"ACT_WS_RESULT":"",
"S_FLAG":"1",
"ACT_LOG_FLAG":"2",
"ACT_ID":"0zITgylaF6oW6bD4LkAFFf",
"ACT_HOT_KEY":"",
"S_MTIME":"2013-05-06 12:25:44:186",
"_ROWNUM_":"12",
"ACT_TYPE":"2",
"ACT_TIP":"启用条件：未发布，且已审核或不审核",
"_PK_":"0zITgylaF6oW6bD4LkAFFf",
"ACT_WS_FLAG":"2",
"ACT_GROUP":"2",
"ACT_NAME":"发布",
"ACT_CSS":"sync",
"ACT_EXPRESSION":"'#ACT_STATE#' == '2' && ( '#CHK_STATE#'  == '10' ||  '#CHK_STATE#' == '20');",
"ACT_MEMO":"",
"SY_SERV_ACT_PARAM":
[
],
"ACT_ORDER":"130",
"ACT_MOBILE_FLAG":"",
"LIST_DIS_GROUP":"",
"ACT_CODE":"publish",
"ACT_EXPRESSION_FLAG":"0"
}
],
"SERV_CARD_TMPL":"",
"SERV_KEYS":"ACT_ID",
"SERV_LIST_STYLE":"",
"S_MTIME":"2015-08-25 15:55:05:787",
"SERV_MEMO":"领导活动_需要审核",
"SERV_DATA_TITLE":"",
"SERV_AUTH_FLAG":"1",
"SERV_JS":"<style>\n#OA_LDR_ACTION-winTabs {height:700px !important;}\n<\/style>",
"SERV_CARD_LOAD":"1",
"SERV_NO_COUNT":"2",
"SERV_LOCK_FLAG":"2",
"SERV_SQL_ORDER":"BEGIN_TIME desc",
"SERV_MOBILE_JS":"",
"SERV_RELATE_CONFIG":"",
"SERV_RELATE_FLAG":"0",
"SERV_FILE_PATH":"",
"SY_SERV_LINK":
[
],
"S_FLAG":"1",
"SAFE_FLAG":"1",
"TABLE_VIEW":"OA_LDR_ACTION",
"SY_SERV_QUERY":
[
{
"SERV_ID":"OA_LDR_ACTION",
"S_FLAG":"1",
"S_MTIME":"2013-01-30 15:13:21:931",
"_ROWNUM_":"0",
"QUERY_ORDER":"20",
"_PK_":"27ilzQzJl7qqmZ1OX-VNzV",
"QUERY_NAME":"未送审",
"QUERY_DEFAULT":"2",
"QUERY_SQL":"and CHK_STATE < 5",
"LIST_ID":"",
"QUERY_ID":"27ilzQzJl7qqmZ1OX-VNzV",
"S_USER":"yangjinyun",
"QUERY_TYPE":"1"
},
{
"SERV_ID":"OA_LDR_ACTION",
"S_FLAG":"1",
"S_MTIME":"2013-01-30 15:13:21:931",
"_ROWNUM_":"1",
"QUERY_ORDER":"30",
"_PK_":"1JPttW58hbDab28xbY9HlX",
"QUERY_NAME":"已送审",
"QUERY_DEFAULT":"2",
"QUERY_SQL":"and CHK_STATE = 5",
"LIST_ID":"",
"QUERY_ID":"1JPttW58hbDab28xbY9HlX",
"S_USER":"yangjinyun",
"QUERY_TYPE":"1"
},
{
"SERV_ID":"OA_LDR_ACTION",
"S_FLAG":"1",
"S_MTIME":"2013-05-06 12:01:51:951",
"_ROWNUM_":"2",
"QUERY_ORDER":"33",
"_PK_":"1oLsNedqt9J96J169oFsOk",
"QUERY_NAME":"审核通过",
"QUERY_DEFAULT":"2",
"QUERY_SQL":"and CHK_STATE  = 10",
"LIST_ID":"",
"QUERY_ID":"1oLsNedqt9J96J169oFsOk",
"S_USER":"1Xvd5e5X50O8J0Ir-0zlwd",
"QUERY_TYPE":"1"
},
{
"SERV_ID":"OA_LDR_ACTION",
"S_FLAG":"1",
"S_MTIME":"2013-05-06 12:02:06:179",
"_ROWNUM_":"3",
"QUERY_ORDER":"35",
"_PK_":"0hwWetkTdaJHOX2soBroL_",
"QUERY_NAME":"审核不通过",
"QUERY_DEFAULT":"2",
"QUERY_SQL":"and CHK_STATE = 15",
"LIST_ID":"",
"QUERY_ID":"0hwWetkTdaJHOX2soBroL_",
"S_USER":"yangjinyun",
"QUERY_TYPE":"1"
},
{
"SERV_ID":"OA_LDR_ACTION",
"S_FLAG":"1",
"S_MTIME":"2013-01-30 15:13:21:931",
"_ROWNUM_":"4",
"QUERY_ORDER":"40",
"_PK_":"36s86EME532anOeEhpXRxb",
"QUERY_NAME":"已发布",
"QUERY_DEFAULT":"2",
"QUERY_SQL":"and ACT_STATE = 1",
"LIST_ID":"",
"QUERY_ID":"36s86EME532anOeEhpXRxb",
"S_USER":"yangjinyun",
"QUERY_TYPE":"1"
}
],
"SY_SERV_ITEM":
[
{
"SERV_ID":"OA_LDR_ACTION",
"ITEM_CARD_WIDTH":"0",
"ITEM_LOG_FLAG":"2",
"ITEM_TIP":"",
"ITEM_ORDER_CODES":"",
"ITEM_CARD_FORMAT":"",
"ITEM_LIST_STYLE":"",
"ITEM_VALIDATE":"",
"ITEM_MEMO":"ID",
"ITEM_VALIDATE_HINT":"",
"ITEM_NOTNULL":"1",
"ITEM_LIST_ORDER":"0",
"ITEM_FIELD_TYPE":"STR",
"ITEM_SEARCH_FLAG":"2",
"ITEM_INPUT_MODE":"1",
"ITEM_USER_FLAG":"0",
"_ROWNUM_":"0",
"ITEM_LIST_WIDTH":"0",
"ITEM_EXPTENDS":"",
"ITEM_NAME":"ID",
"ITEM_NOTNULL_SCRIPT":"",
"ITEM_CARD_ORDER":"0",
"ITEM_CARD_COLS":"1",
"ITEM_SUM_FLAG":"0",
"ITEM_TYPE":"1",
"S_MTIME":"2013-01-30 15:13:21:756",
"ITEM_LIST_FORMAT":"",
"ITEM_ID":"39rrrL0Cha_bphsDvAFlis",
"ITEM_LIST_FLAG":"2",
"ITEM_CARD_DISABLE":"2",
"ITEM_CARD_ROWS":"1",
"ITEM_READONLY":"2",
"ITEM_HIDDEN_SCRIPT":"",
"ITEM_LIST_EDIT":"2",
"DICT_ID":"",
"ITEM_READONLY_SCRIPT":"",
"ITEM_FIELD_LENGTH":"40",
"S_FLAG":"1",
"ITEM_CARD_LINK":"",
"ITEM_HIDDEN":"1",
"ITEM_CARD_STYLE":"",
"ITEM_UNIQUE_GROUP":"0",
"_PK_":"39rrrL0Cha_bphsDvAFlis",
"ITEM_LIST_ALIGN":"1",
"ITEM_INPUT_TYPE":"1",
"ITEM_LIST_LINK":"",
"ITEM_INPUT_FLAG":"2",
"ITEM_CODE":"ACT_ID",
"ITEM_MOBILE_TYPE":"3",
"ITEM_LABEL_HIDDEN":"0",
"ITEM_INPUT_DEFAULT":"",
"ITEM_INPUT_CONFIG":""
},
{
"SERV_ID":"OA_LDR_ACTION",
"ITEM_CARD_WIDTH":"0",
"ITEM_LOG_FLAG":"2",
"ITEM_TIP":"",
"ITEM_ORDER_CODES":"",
"ITEM_CARD_FORMAT":"",
"ITEM_LIST_STYLE":"",
"ITEM_VALIDATE":"",
"ITEM_MEMO":"公司编码",
"ITEM_VALIDATE_HINT":"",
"ITEM_NOTNULL":"2",
"ITEM_LIST_ORDER":"10",
"ITEM_FIELD_TYPE":"STR",
"ITEM_SEARCH_FLAG":"2",
"ITEM_INPUT_MODE":"1",
"ITEM_USER_FLAG":"0",
"_ROWNUM_":"1",
"ITEM_LIST_WIDTH":"0",
"ITEM_EXPTENDS":"",
"ITEM_NAME":"公司编码",
"ITEM_NOTNULL_SCRIPT":"",
"ITEM_CARD_ORDER":"10",
"ITEM_CARD_COLS":"1",
"ITEM_SUM_FLAG":"0",
"ITEM_TYPE":"1",
"S_MTIME":"2013-01-30 15:13:21:756",
"ITEM_LIST_FORMAT":"",
"ITEM_ID":"3J24xH4EZcoHRg99G3YYAD",
"ITEM_LIST_FLAG":"2",
"ITEM_CARD_DISABLE":"2",
"ITEM_CARD_ROWS":"1",
"ITEM_READONLY":"2",
"ITEM_HIDDEN_SCRIPT":"",
"ITEM_LIST_EDIT":"2",
"DICT_ID":"",
"ITEM_READONLY_SCRIPT":"",
"ITEM_FIELD_LENGTH":"40",
"S_FLAG":"1",
"ITEM_CARD_LINK":"",
"ITEM_HIDDEN":"1",
"ITEM_CARD_STYLE":"",
"ITEM_UNIQUE_GROUP":"0",
"_PK_":"3J24xH4EZcoHRg99G3YYAD",
"ITEM_LIST_ALIGN":"1",
"ITEM_INPUT_TYPE":"1",
"ITEM_LIST_LINK":"",
"ITEM_INPUT_FLAG":"2",
"ITEM_CODE":"CMPY_CODE",
"ITEM_MOBILE_TYPE":"3",
"ITEM_LABEL_HIDDEN":"0",
"ITEM_INPUT_DEFAULT":"",
"ITEM_INPUT_CONFIG":""
},
{
"SERV_ID":"OA_LDR_ACTION",
"ITEM_CARD_WIDTH":"0",
"ITEM_LOG_FLAG":"2",
"ITEM_TIP":"",
"ITEM_ORDER_CODES":"",
"ITEM_CARD_FORMAT":"",
"ITEM_LIST_STYLE":"",
"ITEM_VALIDATE":"",
"ITEM_MEMO":"标题",
"ITEM_VALIDATE_HINT":"",
"ITEM_NOTNULL":"1",
"ITEM_LIST_ORDER":"10",
"ITEM_FIELD_TYPE":"STR",
"ITEM_SEARCH_FLAG":"1",
"ITEM_INPUT_MODE":"1",
"ITEM_USER_FLAG":"0",
"_ROWNUM_":"2",
"ITEM_LIST_WIDTH":"0",
"ITEM_EXPTENDS":"",
"ITEM_NAME":"标题",
"ITEM_NOTNULL_SCRIPT":"",
"ITEM_CARD_ORDER":"70",
"ITEM_CARD_COLS":"2",
"ITEM_SUM_FLAG":"0",
"ITEM_TYPE":"1",
"S_MTIME":"2013-05-24 14:23:47:419",
"ITEM_LIST_FORMAT":"",
"ITEM_ID":"2pYsw1cvZaEXZz9jzMF1s9",
"ITEM_LIST_FLAG":"1",
"ITEM_CARD_DISABLE":"2",
"ITEM_CARD_ROWS":"1",
"ITEM_READONLY":"2",
"ITEM_HIDDEN_SCRIPT":"",
"ITEM_LIST_EDIT":"2",
"DICT_ID":"",
"ITEM_READONLY_SCRIPT":"",
"ITEM_FIELD_LENGTH":"400",
"S_FLAG":"1",
"ITEM_CARD_LINK":"",
"ITEM_HIDDEN":"2",
"ITEM_CARD_STYLE":"",
"ITEM_UNIQUE_GROUP":"0",
"_PK_":"2pYsw1cvZaEXZz9jzMF1s9",
"ITEM_LIST_ALIGN":"1",
"ITEM_INPUT_TYPE":"1",
"ITEM_LIST_LINK":"Tools.openCard(this)",
"ITEM_INPUT_FLAG":"2",
"ITEM_CODE":"TITLE",
"ITEM_MOBILE_TYPE":"3",
"ITEM_LABEL_HIDDEN":"0",
"ITEM_INPUT_DEFAULT":"",
"ITEM_INPUT_CONFIG":""
},
{
"SERV_ID":"OA_LDR_ACTION",
"ITEM_CARD_WIDTH":"0",
"ITEM_LOG_FLAG":"2",
"ITEM_TIP":"",
"ITEM_ORDER_CODES":"",
"ITEM_CARD_FORMAT":"",
"ITEM_LIST_STYLE":"",
"ITEM_VALIDATE":"",
"ITEM_MEMO":"领导ID",
"ITEM_VALIDATE_HINT":"",
"ITEM_NOTNULL":"1",
"ITEM_LIST_ORDER":"30",
"ITEM_FIELD_TYPE":"STR",
"ITEM_SEARCH_FLAG":"1",
"ITEM_INPUT_MODE":"1",
"ITEM_USER_FLAG":"0",
"_ROWNUM_":"3",
"ITEM_LIST_WIDTH":"0",
"ITEM_EXPTENDS":"",
"ITEM_NAME":"领导姓名",
"ITEM_NOTNULL_SCRIPT":"",
"ITEM_CARD_ORDER":"30",
"ITEM_CARD_COLS":"2",
"ITEM_SUM_FLAG":"0",
"ITEM_TYPE":"1",
"S_MTIME":"2015-07-29 18:10:30:046",
"ITEM_LIST_FORMAT":"",
"ITEM_ID":"1rO3aeIPhflWbJYE3R4c5c",
"ITEM_LIST_FLAG":"1",
"ITEM_CARD_DISABLE":"2",
"ITEM_CARD_ROWS":"1",
"ITEM_READONLY":"2",
"ITEM_HIDDEN_SCRIPT":"",
"ITEM_LIST_EDIT":"2",
"DICT_ID":"OA_LDR_SECRETARY",
"ITEM_READONLY_SCRIPT":"",
"ITEM_FIELD_LENGTH":"300",
"S_FLAG":"1",
"ITEM_CARD_LINK":"",
"ITEM_HIDDEN":"2",
"ITEM_CARD_STYLE":"",
"ITEM_UNIQUE_GROUP":"0",
"_PK_":"1rO3aeIPhflWbJYE3R4c5c",
"ITEM_LIST_ALIGN":"3",
"ITEM_INPUT_TYPE":"4",
"ITEM_LIST_LINK":"",
"ITEM_INPUT_FLAG":"2",
"ITEM_CODE":"LDR_ID",
"ITEM_MOBILE_TYPE":"3",
"ITEM_LABEL_HIDDEN":"0",
"ITEM_INPUT_DEFAULT":"",
"ITEM_INPUT_CONFIG":"OA_LDR_SECRETARY"
},
{
"SERV_ID":"OA_LDR_ACTION",
"ITEM_CARD_WIDTH":"0",
"ITEM_LOG_FLAG":"2",
"ITEM_TIP":"",
"ITEM_ORDER_CODES":"",
"ITEM_CARD_FORMAT":"",
"ITEM_LIST_STYLE":"",
"ITEM_VALIDATE":"",
"ITEM_MEMO":"活动类型",
"ITEM_VALIDATE_HINT":"",
"ITEM_NOTNULL":"1",
"ITEM_LIST_ORDER":"35",
"ITEM_FIELD_TYPE":"STR",
"ITEM_SEARCH_FLAG":"1",
"ITEM_INPUT_MODE":"1",
"ITEM_USER_FLAG":"0",
"_ROWNUM_":"4",
"ITEM_LIST_WIDTH":"0",
"ITEM_EXPTENDS":"",
"ITEM_NAME":"活动类型",
"ITEM_NOTNULL_SCRIPT":"",
"ITEM_CARD_ORDER":"100",
"ITEM_CARD_COLS":"2",
"ITEM_SUM_FLAG":"0",
"ITEM_TYPE":"1",
"S_MTIME":"2013-05-28 10:08:04:285",
"ITEM_LIST_FORMAT":"",
"ITEM_ID":"28v-kzmMpatp6Jn9z01T9O",
"ITEM_LIST_FLAG":"1",
"ITEM_CARD_DISABLE":"2",
"ITEM_CARD_ROWS":"1",
"ITEM_READONLY":"2",
"ITEM_HIDDEN_SCRIPT":"",
"ITEM_LIST_EDIT":"2",
"DICT_ID":"OA_LDR_ACT_TYPE",
"ITEM_READONLY_SCRIPT":"",
"ITEM_FIELD_LENGTH":"50",
"S_FLAG":"1",
"ITEM_CARD_LINK":"",
"ITEM_HIDDEN":"2",
"ITEM_CARD_STYLE":"",
"ITEM_UNIQUE_GROUP":"0",
"_PK_":"28v-kzmMpatp6Jn9z01T9O",
"ITEM_LIST_ALIGN":"3",
"ITEM_INPUT_TYPE":"2",
"ITEM_LIST_LINK":"",
"ITEM_INPUT_FLAG":"2",
"ITEM_CODE":"ACT_TYPE",
"ITEM_MOBILE_TYPE":"3",
"ITEM_LABEL_HIDDEN":"0",
"ITEM_INPUT_DEFAULT":"",
"ITEM_INPUT_CONFIG":"OA_LDR_ACT_TYPE"
},
{
"SERV_ID":"OA_LDR_ACTION",
"ITEM_CARD_WIDTH":"0",
"ITEM_LOG_FLAG":"2",
"ITEM_TIP":"",
"ITEM_ORDER_CODES":"",
"ITEM_CARD_FORMAT":"",
"ITEM_LIST_STYLE":"",
"ITEM_VALIDATE":"",
"ITEM_MEMO":"开始时间",
"ITEM_VALIDATE_HINT":"",
"ITEM_NOTNULL":"1",
"ITEM_LIST_ORDER":"40",
"ITEM_FIELD_TYPE":"STR",
"ITEM_SEARCH_FLAG":"1",
"ITEM_INPUT_MODE":"4",
"ITEM_USER_FLAG":"0",
"_ROWNUM_":"5",
"ITEM_LIST_WIDTH":"0",
"ITEM_EXPTENDS":"",
"ITEM_NAME":"开始时间",
"ITEM_NOTNULL_SCRIPT":"",
"ITEM_CARD_ORDER":"40",
"ITEM_CARD_COLS":"1",
"ITEM_SUM_FLAG":"0",
"ITEM_TYPE":"1",
"S_MTIME":"2013-05-28 10:08:04:388",
"ITEM_LIST_FORMAT":"",
"ITEM_ID":"03ZroWI7haUW1egVDD0lyI",
"ITEM_LIST_FLAG":"1",
"ITEM_CARD_DISABLE":"2",
"ITEM_CARD_ROWS":"1",
"ITEM_READONLY":"2",
"ITEM_HIDDEN_SCRIPT":"",
"ITEM_LIST_EDIT":"2",
"DICT_ID":"",
"ITEM_READONLY_SCRIPT":"",
"ITEM_FIELD_LENGTH":"20",
"S_FLAG":"1",
"ITEM_CARD_LINK":"",
"ITEM_HIDDEN":"2",
"ITEM_CARD_STYLE":"",
"ITEM_UNIQUE_GROUP":"0",
"_PK_":"03ZroWI7haUW1egVDD0lyI",
"ITEM_LIST_ALIGN":"3",
"ITEM_INPUT_TYPE":"1",
"ITEM_LIST_LINK":"",
"ITEM_INPUT_FLAG":"2",
"ITEM_CODE":"BEGIN_TIME",
"ITEM_MOBILE_TYPE":"3",
"ITEM_LABEL_HIDDEN":"0",
"ITEM_INPUT_DEFAULT":"",
"ITEM_INPUT_CONFIG":"DATETIME"
},
{
"SERV_ID":"OA_LDR_ACTION",
"ITEM_CARD_WIDTH":"0",
"ITEM_LOG_FLAG":"2",
"ITEM_TIP":"",
"ITEM_ORDER_CODES":"",
"ITEM_CARD_FORMAT":"",
"ITEM_LIST_STYLE":"",
"ITEM_VALIDATE":"",
"ITEM_MEMO":"结束时间",
"ITEM_VALIDATE_HINT":"",
"ITEM_NOTNULL":"1",
"ITEM_LIST_ORDER":"50",
"ITEM_FIELD_TYPE":"STR",
"ITEM_SEARCH_FLAG":"1",
"ITEM_INPUT_MODE":"4",
"ITEM_USER_FLAG":"0",
"_ROWNUM_":"6",
"ITEM_LIST_WIDTH":"0",
"ITEM_EXPTENDS":"",
"ITEM_NAME":"结束时间",
"ITEM_NOTNULL_SCRIPT":"",
"ITEM_CARD_ORDER":"50",
"ITEM_CARD_COLS":"1",
"ITEM_SUM_FLAG":"0",
"ITEM_TYPE":"1",
"S_MTIME":"2013-05-28 10:08:04:467",
"ITEM_LIST_FORMAT":"",
"ITEM_ID":"3VGygCfQFbKUvfR6kpsMkT",
"ITEM_LIST_FLAG":"1",
"ITEM_CARD_DISABLE":"2",
"ITEM_CARD_ROWS":"1",
"ITEM_READONLY":"2",
"ITEM_HIDDEN_SCRIPT":"",
"ITEM_LIST_EDIT":"2",
"DICT_ID":"",
"ITEM_READONLY_SCRIPT":"",
"ITEM_FIELD_LENGTH":"20",
"S_FLAG":"1",
"ITEM_CARD_LINK":"",
"ITEM_HIDDEN":"2",
"ITEM_CARD_STYLE":"",
"ITEM_UNIQUE_GROUP":"0",
"_PK_":"3VGygCfQFbKUvfR6kpsMkT",
"ITEM_LIST_ALIGN":"3",
"ITEM_INPUT_TYPE":"1",
"ITEM_LIST_LINK":"",
"ITEM_INPUT_FLAG":"2",
"ITEM_CODE":"END_TIME",
"ITEM_MOBILE_TYPE":"3",
"ITEM_LABEL_HIDDEN":"0",
"ITEM_INPUT_DEFAULT":"",
"ITEM_INPUT_CONFIG":"DATETIME"
},
{
"SERV_ID":"OA_LDR_ACTION",
"ITEM_CARD_WIDTH":"0",
"ITEM_LOG_FLAG":"2",
"ITEM_TIP":"",
"ITEM_ORDER_CODES":"",
"ITEM_CARD_FORMAT":"",
"ITEM_LIST_STYLE":"",
"ITEM_VALIDATE":"",
"ITEM_MEMO":"活动地点",
"ITEM_VALIDATE_HINT":"",
"ITEM_NOTNULL":"2",
"ITEM_LIST_ORDER":"60",
"ITEM_FIELD_TYPE":"STR",
"ITEM_SEARCH_FLAG":"2",
"ITEM_INPUT_MODE":"1",
"ITEM_USER_FLAG":"0",
"_ROWNUM_":"7",
"ITEM_LIST_WIDTH":"0",
"ITEM_EXPTENDS":"",
"ITEM_NAME":"活动地点",
"ITEM_NOTNULL_SCRIPT":"",
"ITEM_CARD_ORDER":"60",
"ITEM_CARD_COLS":"2",
"ITEM_SUM_FLAG":"0",
"ITEM_TYPE":"1",
"S_MTIME":"2013-01-30 15:13:21:756",
"ITEM_LIST_FORMAT":"",
"ITEM_ID":"2tlyd2PQR4FEWHt5MEwgd5",
"ITEM_LIST_FLAG":"2",
"ITEM_CARD_DISABLE":"2",
"ITEM_CARD_ROWS":"1",
"ITEM_READONLY":"2",
"ITEM_HIDDEN_SCRIPT":"",
"ITEM_LIST_EDIT":"2",
"DICT_ID":"",
"ITEM_READONLY_SCRIPT":"",
"ITEM_FIELD_LENGTH":"200",
"S_FLAG":"1",
"ITEM_CARD_LINK":"",
"ITEM_HIDDEN":"2",
"ITEM_CARD_STYLE":"",
"ITEM_UNIQUE_GROUP":"0",
"_PK_":"2tlyd2PQR4FEWHt5MEwgd5",
"ITEM_LIST_ALIGN":"1",
"ITEM_INPUT_TYPE":"1",
"ITEM_LIST_LINK":"",
"ITEM_INPUT_FLAG":"2",
"ITEM_CODE":"ADDRESS",
"ITEM_MOBILE_TYPE":"3",
"ITEM_LABEL_HIDDEN":"0",
"ITEM_INPUT_DEFAULT":"",
"ITEM_INPUT_CONFIG":""
},
{
"SERV_ID":"OA_LDR_ACTION",
"ITEM_CARD_WIDTH":"0",
"ITEM_LOG_FLAG":"2",
"ITEM_TIP":"",
"ITEM_ORDER_CODES":"",
"ITEM_CARD_FORMAT":"",
"ITEM_LIST_STYLE":"",
"ITEM_VALIDATE":"",
"ITEM_MEMO":"",
"ITEM_VALIDATE_HINT":"",
"ITEM_NOTNULL":"2",
"ITEM_LIST_ORDER":"85",
"ITEM_FIELD_TYPE":"STR",
"ITEM_SEARCH_FLAG":"2",
"ITEM_INPUT_MODE":"3",
"ITEM_USER_FLAG":"0",
"_ROWNUM_":"8",
"ITEM_LIST_WIDTH":"0",
"ITEM_EXPTENDS":"",
"ITEM_NAME":"参与人员",
"ITEM_NOTNULL_SCRIPT":"",
"ITEM_CARD_ORDER":"180",
"ITEM_CARD_COLS":"1",
"ITEM_SUM_FLAG":"0",
"ITEM_TYPE":"1",
"S_MTIME":"2015-10-14 20:29:38:273",
"ITEM_LIST_FORMAT":"",
"ITEM_ID":"10DSky91taQ9yUobgGaOp8",
"ITEM_LIST_FLAG":"2",
"ITEM_CARD_DISABLE":"2",
"ITEM_CARD_ROWS":"1",
"ITEM_READONLY":"2",
"ITEM_HIDDEN_SCRIPT":"",
"ITEM_LIST_EDIT":"2",
"DICT_ID":"SY_ORG_USER",
"ITEM_READONLY_SCRIPT":"",
"ITEM_FIELD_LENGTH":"4000",
"S_FLAG":"1",
"ITEM_CARD_LINK":"",
"ITEM_HIDDEN":"2",
"ITEM_CARD_STYLE":"",
"ITEM_UNIQUE_GROUP":"0",
"_PK_":"10DSky91taQ9yUobgGaOp8",
"ITEM_LIST_ALIGN":"1",
"ITEM_INPUT_TYPE":"1",
"ITEM_LIST_LINK":"",
"ITEM_INPUT_FLAG":"2",
"ITEM_CODE":"OTHER_USER_CODE",
"ITEM_MOBILE_TYPE":"3",
"ITEM_LABEL_HIDDEN":"0",
"ITEM_INPUT_DEFAULT":"",
"ITEM_INPUT_CONFIG":"SY_ORG_USER"
},
{
"SERV_ID":"OA_LDR_ACTION",
"ITEM_CARD_WIDTH":"0",
"ITEM_LOG_FLAG":"2",
"ITEM_TIP":"SY_ORG_USER,{\"SOURCE\":\"USER_NAME~USER_CODE\",\"TARGET\":\"OTHER_USER~OTHER_USER_CODE\",\"TYPE\":\"single\"}",
"ITEM_ORDER_CODES":"",
"ITEM_CARD_FORMAT":"",
"ITEM_LIST_STYLE":"",
"ITEM_VALIDATE":"",
"ITEM_MEMO":"其它陪同人员",
"ITEM_VALIDATE_HINT":"",
"ITEM_NOTNULL":"2",
"ITEM_LIST_ORDER":"85",
"ITEM_FIELD_TYPE":"STR",
"ITEM_SEARCH_FLAG":"2",
"ITEM_INPUT_MODE":"3",
"ITEM_USER_FLAG":"0",
"_ROWNUM_":"9",
"ITEM_LIST_WIDTH":"0",
"ITEM_EXPTENDS":"",
"ITEM_NAME":"参与人员",
"ITEM_NOTNULL_SCRIPT":"",
"ITEM_CARD_ORDER":"140",
"ITEM_CARD_COLS":"2",
"ITEM_SUM_FLAG":"0",
"ITEM_TYPE":"1",
"S_MTIME":"2015-10-14 20:29:24:199",
"ITEM_LIST_FORMAT":"",
"ITEM_ID":"1PJneZ-Ax8ra7ccuTCWupU",
"ITEM_LIST_FLAG":"2",
"ITEM_CARD_DISABLE":"2",
"ITEM_CARD_ROWS":"1",
"ITEM_READONLY":"2",
"ITEM_HIDDEN_SCRIPT":"",
"ITEM_LIST_EDIT":"2",
"DICT_ID":"SY_ORG_USER",
"ITEM_READONLY_SCRIPT":"",
"ITEM_FIELD_LENGTH":"4000",
"S_FLAG":"2",
"ITEM_CARD_LINK":"",
"ITEM_HIDDEN":"1",
"ITEM_CARD_STYLE":"",
"ITEM_UNIQUE_GROUP":"0",
"_PK_":"1PJneZ-Ax8ra7ccuTCWupU",
"ITEM_LIST_ALIGN":"1",
"ITEM_INPUT_TYPE":"1",
"ITEM_LIST_LINK":"",
"ITEM_INPUT_FLAG":"2",
"ITEM_CODE":"OTHER_USER",
"ITEM_MOBILE_TYPE":"3",
"ITEM_LABEL_HIDDEN":"0",
"ITEM_INPUT_DEFAULT":"",
"ITEM_INPUT_CONFIG":"SY_ORG_USER"
},
{
"SERV_ID":"OA_LDR_ACTION",
"ITEM_CARD_WIDTH":"0",
"ITEM_LOG_FLAG":"2",
"ITEM_TIP":"",
"ITEM_ORDER_CODES":"",
"ITEM_CARD_FORMAT":"",
"ITEM_LIST_STYLE":"",
"ITEM_VALIDATE":"",
"ITEM_MEMO":"内容",
"ITEM_VALIDATE_HINT":"",
"ITEM_NOTNULL":"2",
"ITEM_LIST_ORDER":"88",
"ITEM_FIELD_TYPE":"STR",
"ITEM_SEARCH_FLAG":"2",
"ITEM_INPUT_MODE":"1",
"ITEM_USER_FLAG":"0",
"_ROWNUM_":"10",
"ITEM_LIST_WIDTH":"0",
"ITEM_EXPTENDS":"",
"ITEM_NAME":"具体安排",
"ITEM_NOTNULL_SCRIPT":"",
"ITEM_CARD_ORDER":"80",
"ITEM_CARD_COLS":"2",
"ITEM_SUM_FLAG":"0",
"ITEM_TYPE":"1",
"S_MTIME":"2015-07-29 18:08:32:628",
"ITEM_LIST_FORMAT":"",
"ITEM_ID":"2uPzPJ4fFbToAlkpZLu0yD",
"ITEM_LIST_FLAG":"2",
"ITEM_CARD_DISABLE":"2",
"ITEM_CARD_ROWS":"1",
"ITEM_READONLY":"2",
"ITEM_HIDDEN_SCRIPT":"",
"ITEM_LIST_EDIT":"2",
"DICT_ID":"",
"ITEM_READONLY_SCRIPT":"",
"ITEM_FIELD_LENGTH":"2000",
"S_FLAG":"1",
"ITEM_CARD_LINK":"",
"ITEM_HIDDEN":"2",
"ITEM_CARD_STYLE":"",
"ITEM_UNIQUE_GROUP":"0",
"_PK_":"2uPzPJ4fFbToAlkpZLu0yD",
"ITEM_LIST_ALIGN":"1",
"ITEM_INPUT_TYPE":"5",
"ITEM_LIST_LINK":"",
"ITEM_INPUT_FLAG":"2",
"ITEM_CODE":"CONTENT",
"ITEM_MOBILE_TYPE":"3",
"ITEM_LABEL_HIDDEN":"0",
"ITEM_INPUT_DEFAULT":"",
"ITEM_INPUT_CONFIG":""
},
{
"SERV_ID":"OA_LDR_ACTION",
"ITEM_CARD_WIDTH":"0",
"ITEM_LOG_FLAG":"2",
"ITEM_TIP":"",
"ITEM_ORDER_CODES":"",
"ITEM_CARD_FORMAT":"",
"ITEM_LIST_STYLE":"",
"ITEM_VALIDATE":"",
"ITEM_MEMO":"状态。1 送汇总；5送领导；10已汇总；15未汇总",
"ITEM_VALIDATE_HINT":"",
"ITEM_NOTNULL":"2",
"ITEM_LIST_ORDER":"90",
"ITEM_FIELD_TYPE":"NUM",
"ITEM_SEARCH_FLAG":"1",
"ITEM_INPUT_MODE":"1",
"ITEM_USER_FLAG":"0",
"_ROWNUM_":"11",
"ITEM_LIST_WIDTH":"0",
"ITEM_EXPTENDS":"",
"ITEM_NAME":"发布状态",
"ITEM_NOTNULL_SCRIPT":"",
"ITEM_CARD_ORDER":"90",
"ITEM_CARD_COLS":"1",
"ITEM_SUM_FLAG":"0",
"ITEM_TYPE":"1",
"S_MTIME":"2013-05-28 13:53:41:181",
"ITEM_LIST_FORMAT":"",
"ITEM_ID":"2koCT_qNl0d9wTh3umV9Ao",
"ITEM_LIST_FLAG":"1",
"ITEM_CARD_DISABLE":"2",
"ITEM_CARD_ROWS":"1",
"ITEM_READONLY":"1",
"ITEM_HIDDEN_SCRIPT":"",
"ITEM_LIST_EDIT":"2",
"DICT_ID":"OA_LDR_ACT_STATE",
"ITEM_READONLY_SCRIPT":"",
"ITEM_FIELD_LENGTH":"2",
"S_FLAG":"1",
"ITEM_CARD_LINK":"",
"ITEM_HIDDEN":"2",
"ITEM_CARD_STYLE":"",
"ITEM_UNIQUE_GROUP":"0",
"_PK_":"2koCT_qNl0d9wTh3umV9Ao",
"ITEM_LIST_ALIGN":"3",
"ITEM_INPUT_TYPE":"2",
"ITEM_LIST_LINK":"",
"ITEM_INPUT_FLAG":"2",
"ITEM_CODE":"ACT_STATE",
"ITEM_MOBILE_TYPE":"3",
"ITEM_LABEL_HIDDEN":"0",
"ITEM_INPUT_DEFAULT":"2",
"ITEM_INPUT_CONFIG":"OA_LDR_ACT_STATE"
},
{
"SERV_ID":"OA_LDR_ACTION",
"ITEM_CARD_WIDTH":"0",
"ITEM_LOG_FLAG":"2",
"ITEM_TIP":"",
"ITEM_ORDER_CODES":"",
"ITEM_CARD_FORMAT":"",
"ITEM_LIST_STYLE":"",
"ITEM_VALIDATE":"",
"ITEM_MEMO":"审核人",
"ITEM_VALIDATE_HINT":"",
"ITEM_NOTNULL":"2",
"ITEM_LIST_ORDER":"110",
"ITEM_FIELD_TYPE":"STR",
"ITEM_SEARCH_FLAG":"2",
"ITEM_INPUT_MODE":"1",
"ITEM_USER_FLAG":"0",
"_ROWNUM_":"12",
"ITEM_LIST_WIDTH":"0",
"ITEM_EXPTENDS":"",
"ITEM_NAME":"审核人",
"ITEM_NOTNULL_SCRIPT":"",
"ITEM_CARD_ORDER":"110",
"ITEM_CARD_COLS":"1",
"ITEM_SUM_FLAG":"0",
"ITEM_TYPE":"1",
"S_MTIME":"2013-01-30 15:13:21:756",
"ITEM_LIST_FORMAT":"",
"ITEM_ID":"32ntdeZW56bEDIlS4QTO_x",
"ITEM_LIST_FLAG":"2",
"ITEM_CARD_DISABLE":"2",
"ITEM_CARD_ROWS":"1",
"ITEM_READONLY":"2",
"ITEM_HIDDEN_SCRIPT":"",
"ITEM_LIST_EDIT":"2",
"DICT_ID":"",
"ITEM_READONLY_SCRIPT":"",
"ITEM_FIELD_LENGTH":"40",
"S_FLAG":"1",
"ITEM_CARD_LINK":"",
"ITEM_HIDDEN":"1",
"ITEM_CARD_STYLE":"",
"ITEM_UNIQUE_GROUP":"0",
"_PK_":"32ntdeZW56bEDIlS4QTO_x",
"ITEM_LIST_ALIGN":"1",
"ITEM_INPUT_TYPE":"1",
"ITEM_LIST_LINK":"",
"ITEM_INPUT_FLAG":"2",
"ITEM_CODE":"CHK_USER",
"ITEM_MOBILE_TYPE":"3",
"ITEM_LABEL_HIDDEN":"0",
"ITEM_INPUT_DEFAULT":"",
"ITEM_INPUT_CONFIG":""
},
{
"SERV_ID":"OA_LDR_ACTION",
"ITEM_CARD_WIDTH":"0",
"ITEM_LOG_FLAG":"2",
"ITEM_TIP":"",
"ITEM_ORDER_CODES":"",
"ITEM_CARD_FORMAT":"",
"ITEM_LIST_STYLE":"",
"ITEM_VALIDATE":"",
"ITEM_MEMO":"审核状态：1已送审，5审核通过，10审核未通过",
"ITEM_VALIDATE_HINT":"",
"ITEM_NOTNULL":"2",
"ITEM_LIST_ORDER":"120",
"ITEM_FIELD_TYPE":"NUM",
"ITEM_SEARCH_FLAG":"2",
"ITEM_INPUT_MODE":"1",
"ITEM_USER_FLAG":"0",
"_ROWNUM_":"13",
"ITEM_LIST_WIDTH":"0",
"ITEM_EXPTENDS":"",
"ITEM_NAME":"审核状态",
"ITEM_NOTNULL_SCRIPT":"",
"ITEM_CARD_ORDER":"120",
"ITEM_CARD_COLS":"1",
"ITEM_SUM_FLAG":"0",
"ITEM_TYPE":"1",
"S_MTIME":"2016-12-18 16:52:18:254",
"ITEM_LIST_FORMAT":"",
"ITEM_ID":"2e5YFi52N4OHvXf25qwifY",
"ITEM_LIST_FLAG":"2",
"ITEM_CARD_DISABLE":"2",
"ITEM_CARD_ROWS":"1",
"ITEM_READONLY":"1",
"ITEM_HIDDEN_SCRIPT":"",
"ITEM_LIST_EDIT":"2",
"DICT_ID":"OA_LDR_ACT_CHK_STATE",
"ITEM_READONLY_SCRIPT":"",
"ITEM_FIELD_LENGTH":"2",
"S_FLAG":"1",
"ITEM_CARD_LINK":"",
"ITEM_HIDDEN":"1",
"ITEM_CARD_STYLE":"",
"ITEM_UNIQUE_GROUP":"0",
"_PK_":"2e5YFi52N4OHvXf25qwifY",
"ITEM_LIST_ALIGN":"3",
"ITEM_INPUT_TYPE":"2",
"ITEM_LIST_LINK":"",
"ITEM_INPUT_FLAG":"2",
"ITEM_CODE":"CHK_STATE",
"ITEM_MOBILE_TYPE":"3",
"ITEM_LABEL_HIDDEN":"0",
"ITEM_INPUT_DEFAULT":"1",
"ITEM_INPUT_CONFIG":"OA_LDR_ACT_CHK_STATE"
},
{
"SERV_ID":"OA_LDR_ACTION",
"ITEM_CARD_WIDTH":"0",
"ITEM_LOG_FLAG":"2",
"ITEM_TIP":"",
"ITEM_ORDER_CODES":"",
"ITEM_CARD_FORMAT":"",
"ITEM_LIST_STYLE":"",
"ITEM_VALIDATE":"",
"ITEM_MEMO":"删除状态",
"ITEM_VALIDATE_HINT":"",
"ITEM_NOTNULL":"2",
"ITEM_LIST_ORDER":"130",
"ITEM_FIELD_TYPE":"NUM",
"ITEM_SEARCH_FLAG":"2",
"ITEM_INPUT_MODE":"1",
"ITEM_USER_FLAG":"0",
"_ROWNUM_":"14",
"ITEM_LIST_WIDTH":"0",
"ITEM_EXPTENDS":"",
"ITEM_NAME":"删除状态",
"ITEM_NOTNULL_SCRIPT":"",
"ITEM_CARD_ORDER":"130",
"ITEM_CARD_COLS":"1",
"ITEM_SUM_FLAG":"0",
"ITEM_TYPE":"1",
"S_MTIME":"2013-01-30 15:13:21:756",
"ITEM_LIST_FORMAT":"",
"ITEM_ID":"2tO_Kofdl0xEVwubArgUJA",
"ITEM_LIST_FLAG":"2",
"ITEM_CARD_DISABLE":"2",
"ITEM_CARD_ROWS":"1",
"ITEM_READONLY":"2",
"ITEM_HIDDEN_SCRIPT":"",
"ITEM_LIST_EDIT":"2",
"DICT_ID":"",
"ITEM_READONLY_SCRIPT":"",
"ITEM_FIELD_LENGTH":"1",
"S_FLAG":"1",
"ITEM_CARD_LINK":"",
"ITEM_HIDDEN":"1",
"ITEM_CARD_STYLE":"",
"ITEM_UNIQUE_GROUP":"0",
"_PK_":"2tO_Kofdl0xEVwubArgUJA",
"ITEM_LIST_ALIGN":"1",
"ITEM_INPUT_TYPE":"1",
"ITEM_LIST_LINK":"",
"ITEM_INPUT_FLAG":"2",
"ITEM_CODE":"S_FLAG",
"ITEM_MOBILE_TYPE":"3",
"ITEM_LABEL_HIDDEN":"0",
"ITEM_INPUT_DEFAULT":"1",
"ITEM_INPUT_CONFIG":""
},
{
"SERV_ID":"OA_LDR_ACTION",
"ITEM_CARD_WIDTH":"0",
"ITEM_LOG_FLAG":"2",
"ITEM_TIP":"",
"ITEM_ORDER_CODES":"",
"ITEM_CARD_FORMAT":"",
"ITEM_LIST_STYLE":"",
"ITEM_VALIDATE":"",
"ITEM_MEMO":"所属机构",
"ITEM_VALIDATE_HINT":"",
"ITEM_NOTNULL":"2",
"ITEM_LIST_ORDER":"150",
"ITEM_FIELD_TYPE":"STR",
"ITEM_SEARCH_FLAG":"2",
"ITEM_INPUT_MODE":"1",
"ITEM_USER_FLAG":"0",
"_ROWNUM_":"15",
"ITEM_LIST_WIDTH":"0",
"ITEM_EXPTENDS":"",
"ITEM_NAME":"所属机构",
"ITEM_NOTNULL_SCRIPT":"",
"ITEM_CARD_ORDER":"150",
"ITEM_CARD_COLS":"1",
"ITEM_SUM_FLAG":"0",
"ITEM_TYPE":"1",
"S_MTIME":"2013-01-30 15:13:21:756",
"ITEM_LIST_FORMAT":"",
"ITEM_ID":"0Rg8VZkepaybypjr22xulr",
"ITEM_LIST_FLAG":"2",
"ITEM_CARD_DISABLE":"2",
"ITEM_CARD_ROWS":"1",
"ITEM_READONLY":"2",
"ITEM_HIDDEN_SCRIPT":"",
"ITEM_LIST_EDIT":"2",
"DICT_ID":"",
"ITEM_READONLY_SCRIPT":"",
"ITEM_FIELD_LENGTH":"40",
"S_FLAG":"1",
"ITEM_CARD_LINK":"",
"ITEM_HIDDEN":"1",
"ITEM_CARD_STYLE":"",
"ITEM_UNIQUE_GROUP":"0",
"_PK_":"0Rg8VZkepaybypjr22xulr",
"ITEM_LIST_ALIGN":"1",
"ITEM_INPUT_TYPE":"1",
"ITEM_LIST_LINK":"",
"ITEM_INPUT_FLAG":"2",
"ITEM_CODE":"S_ODEPT",
"ITEM_MOBILE_TYPE":"3",
"ITEM_LABEL_HIDDEN":"0",
"ITEM_INPUT_DEFAULT":"@ODEPT_CODE@",
"ITEM_INPUT_CONFIG":""
},
{
"SERV_ID":"OA_LDR_ACTION",
"ITEM_CARD_WIDTH":"0",
"ITEM_LOG_FLAG":"2",
"ITEM_TIP":"",
"ITEM_ORDER_CODES":"",
"ITEM_CARD_FORMAT":"",
"ITEM_LIST_STYLE":"",
"ITEM_VALIDATE":"",
"ITEM_MEMO":"修改时间",
"ITEM_VALIDATE_HINT":"",
"ITEM_NOTNULL":"2",
"ITEM_LIST_ORDER":"160",
"ITEM_FIELD_TYPE":"STR",
"ITEM_SEARCH_FLAG":"2",
"ITEM_INPUT_MODE":"1",
"ITEM_USER_FLAG":"0",
"_ROWNUM_":"16",
"ITEM_LIST_WIDTH":"0",
"ITEM_EXPTENDS":"",
"ITEM_NAME":"修改时间",
"ITEM_NOTNULL_SCRIPT":"",
"ITEM_CARD_ORDER":"160",
"ITEM_CARD_COLS":"1",
"ITEM_SUM_FLAG":"0",
"ITEM_TYPE":"1",
"S_MTIME":"2016-12-18 16:51:57:769",
"ITEM_LIST_FORMAT":"",
"ITEM_ID":"2RJDjKMkt3NpHZanuC4Mch",
"ITEM_LIST_FLAG":"2",
"ITEM_CARD_DISABLE":"2",
"ITEM_CARD_ROWS":"1",
"ITEM_READONLY":"1",
"ITEM_HIDDEN_SCRIPT":"",
"ITEM_LIST_EDIT":"2",
"DICT_ID":"",
"ITEM_READONLY_SCRIPT":"",
"ITEM_FIELD_LENGTH":"25",
"S_FLAG":"1",
"ITEM_CARD_LINK":"",
"ITEM_HIDDEN":"1",
"ITEM_CARD_STYLE":"",
"ITEM_UNIQUE_GROUP":"0",
"_PK_":"2RJDjKMkt3NpHZanuC4Mch",
"ITEM_LIST_ALIGN":"1",
"ITEM_INPUT_TYPE":"1",
"ITEM_LIST_LINK":"",
"ITEM_INPUT_FLAG":"2",
"ITEM_CODE":"S_MTIME",
"ITEM_MOBILE_TYPE":"3",
"ITEM_LABEL_HIDDEN":"0",
"ITEM_INPUT_DEFAULT":"@DATETIME_TS@",
"ITEM_INPUT_CONFIG":""
},
{
"SERV_ID":"OA_LDR_ACTION",
"ITEM_CARD_WIDTH":"0",
"ITEM_LOG_FLAG":"2",
"ITEM_TIP":"",
"ITEM_ORDER_CODES":"",
"ITEM_CARD_FORMAT":"",
"ITEM_LIST_STYLE":"",
"ITEM_VALIDATE":"",
"ITEM_MEMO":"添加时间",
"ITEM_VALIDATE_HINT":"",
"ITEM_NOTNULL":"2",
"ITEM_LIST_ORDER":"170",
"ITEM_FIELD_TYPE":"STR",
"ITEM_SEARCH_FLAG":"2",
"ITEM_INPUT_MODE":"1",
"ITEM_USER_FLAG":"0",
"_ROWNUM_":"17",
"ITEM_LIST_WIDTH":"0",
"ITEM_EXPTENDS":"",
"ITEM_NAME":"添加时间",
"ITEM_NOTNULL_SCRIPT":"",
"ITEM_CARD_ORDER":"170",
"ITEM_CARD_COLS":"1",
"ITEM_SUM_FLAG":"0",
"ITEM_TYPE":"1",
"S_MTIME":"2013-01-30 15:13:21:756",
"ITEM_LIST_FORMAT":"",
"ITEM_ID":"0FL5Z3ayl1JUmBo79Q_Hnk",
"ITEM_LIST_FLAG":"2",
"ITEM_CARD_DISABLE":"2",
"ITEM_CARD_ROWS":"1",
"ITEM_READONLY":"2",
"ITEM_HIDDEN_SCRIPT":"",
"ITEM_LIST_EDIT":"2",
"DICT_ID":"",
"ITEM_READONLY_SCRIPT":"",
"ITEM_FIELD_LENGTH":"20",
"S_FLAG":"1",
"ITEM_CARD_LINK":"",
"ITEM_HIDDEN":"1",
"ITEM_CARD_STYLE":"",
"ITEM_UNIQUE_GROUP":"0",
"_PK_":"0FL5Z3ayl1JUmBo79Q_Hnk",
"ITEM_LIST_ALIGN":"1",
"ITEM_INPUT_TYPE":"1",
"ITEM_LIST_LINK":"",
"ITEM_INPUT_FLAG":"2",
"ITEM_CODE":"S_ATIME",
"ITEM_MOBILE_TYPE":"3",
"ITEM_LABEL_HIDDEN":"0",
"ITEM_INPUT_DEFAULT":"@DATETIME_TS@",
"ITEM_INPUT_CONFIG":""
},
{
"SERV_ID":"OA_LDR_ACTION",
"ITEM_CARD_WIDTH":"0",
"ITEM_LOG_FLAG":"2",
"ITEM_TIP":"",
"ITEM_ORDER_CODES":"",
"ITEM_CARD_FORMAT":"",
"ITEM_LIST_STYLE":"",
"ITEM_VALIDATE":"",
"ITEM_MEMO":"添加人",
"ITEM_VALIDATE_HINT":"",
"ITEM_NOTNULL":"2",
"ITEM_LIST_ORDER":"200",
"ITEM_FIELD_TYPE":"STR",
"ITEM_SEARCH_FLAG":"1",
"ITEM_INPUT_MODE":"3",
"ITEM_USER_FLAG":"0",
"_ROWNUM_":"18",
"ITEM_LIST_WIDTH":"0",
"ITEM_EXPTENDS":"",
"ITEM_NAME":"添加人",
"ITEM_NOTNULL_SCRIPT":"",
"ITEM_CARD_ORDER":"20",
"ITEM_CARD_COLS":"1",
"ITEM_SUM_FLAG":"0",
"ITEM_TYPE":"1",
"S_MTIME":"2013-05-28 10:08:04:773",
"ITEM_LIST_FORMAT":"",
"ITEM_ID":"0pQd-wXtZ5d9d-d4lrcJok",
"ITEM_LIST_FLAG":"1",
"ITEM_CARD_DISABLE":"2",
"ITEM_CARD_ROWS":"1",
"ITEM_READONLY":"1",
"ITEM_HIDDEN_SCRIPT":"",
"ITEM_LIST_EDIT":"2",
"DICT_ID":"SY_ORG_DEPT_USER",
"ITEM_READONLY_SCRIPT":"",
"ITEM_FIELD_LENGTH":"40",
"S_FLAG":"1",
"ITEM_CARD_LINK":"",
"ITEM_HIDDEN":"2",
"ITEM_CARD_STYLE":"",
"ITEM_UNIQUE_GROUP":"0",
"_PK_":"0pQd-wXtZ5d9d-d4lrcJok",
"ITEM_LIST_ALIGN":"3",
"ITEM_INPUT_TYPE":"1",
"ITEM_LIST_LINK":"",
"ITEM_INPUT_FLAG":"2",
"ITEM_CODE":"S_USER",
"ITEM_MOBILE_TYPE":"3",
"ITEM_LABEL_HIDDEN":"0",
"ITEM_INPUT_DEFAULT":"@USER_CODE@",
"ITEM_INPUT_CONFIG":"SY_ORG_DEPT_USER,{}"
}
],
"SERV_CACHE_FLAG":"3",
"_PK_":"OA_LDR_ACTION",
"SERV_LIST_LOAD":"1",
"S_CMPY":"ruaho",
"SERV_DATA_CODE":"",
"SERV_DICT_CACHE":"",
"SERV_CARD_TMPL_CODES":"",
"SY_SERV_WHERE":
[
{
"SERV_ID":"OA_LDR_ACTION",
"S_FLAG":"1",
"WHERE_ORDER":"20",
"_PK_":"2kYgniKEF0DqIGl1sH0MPz",
"WHERE_SERV_TYPE":"",
"S_MTIME":"2015-09-14 15:31:24:544",
"WHERE_NAME":"秘书看对应的领导",
"WHERE_ID":"2kYgniKEF0DqIGl1sH0MPz",
"_ROWNUM_":"0",
"WHERE_FLOW_FLAG":"9",
"WHERE_SCRIPT":"1==1",
"WHERE_CONTENT":"and ACT_ID IN (SELECT ACT_ID FROM OA_LDR_ACT_USERS b WHERE B.USER_CODE IN  (SELECT USER_CODE FROM SY_ORG_USER_RELATION_V WHERE RELATION_TYPE = 3 AND ORIGIN_USER_CODE = '@USER_CODE@'))"
}
]
}