{
"SERV_ID":"OA_ZH_ASSAF_AS",
"SERV_QUERY_MODE":"2",
"SERV_WF_FLAG":"1",
"SERV_DELETE_FLAG":"1",
"S_PUBLIC":"1",
"SERV_PAGE_COUNT":"50",
"SERV_PID":"",
"SERV_SEARCH_FLAG":"1",
"SERV_TYPE":"1",
"SERV_CMPY":"S_CMPY",
"SERV_NAME":"应用系统服务申请单",
"SERV_CLASS":"com.rh.oa.zh.serv.LetterServ",
"SERV_SRC_ID":"",
"S_USER":"1Xvd5e5X50O8J0Ir-0zlwd",
"SERV_RED_HEAD":"{\"title\":\"应用系统服务申请单\"}",
"SERV_MOBILE_LIST":"",
"_ROWNUM_":"0",
"SERV_SQL_WHERE":"AND TMPL_TYPE_CODE ='OA_ZH_ASSAF_AS' and S_FLAG = 1",
"SERV_NAV_ITEMS":"",
"TABLE_ACTION":"OA_ZH_ASSAF_AS",
"SERV_DATA_SOURCE":"",
"SERV_CARD_STYLE":"2",
"SY_SERV_ACT":
[
{
"SERV_ID":"OA_ZH_ASSAF_AS",
"ACT_WS_RESULT":"",
"S_FLAG":"1",
"ACT_LOG_FLAG":"2",
"ACT_ID":"1m2yqL-vRbwGS_sggFNDwH",
"ACT_HOT_KEY":"",
"S_MTIME":"2016-02-22 18:20:05:280",
"_ROWNUM_":"0",
"ACT_TYPE":"1",
"ACT_TIP":"",
"_PK_":"1m2yqL-vRbwGS_sggFNDwH",
"ACT_WS_FLAG":"2",
"ACT_GROUP":"1",
"ACT_NAME":" 新 建",
"ACT_CSS":"add",
"ACT_EXPRESSION":"",
"ACT_MEMO":"",
"SY_SERV_ACT_PARAM":
[
],
"ACT_ORDER":"1",
"ACT_MOBILE_FLAG":"",
"LIST_DIS_GROUP":"",
"ACT_CODE":"add",
"ACT_EXPRESSION_FLAG":"0"
},
{
"SERV_ID":"OA_ZH_ASSAF_AS",
"ACT_WS_RESULT":"",
"S_FLAG":"1",
"ACT_LOG_FLAG":"1",
"ACT_ID":"1RV98_IAB12r-EycpHS_oP",
"ACT_HOT_KEY":"",
"S_MTIME":"2014-01-09 22:26:53:895",
"_ROWNUM_":"1",
"ACT_TYPE":"3",
"ACT_TIP":"",
"_PK_":"1RV98_IAB12r-EycpHS_oP",
"ACT_WS_FLAG":"2",
"ACT_GROUP":"1",
"ACT_NAME":"删除",
"ACT_CSS":"delete",
"ACT_EXPRESSION":"",
"ACT_MEMO":"",
"SY_SERV_ACT_PARAM":
[
],
"ACT_ORDER":"2",
"ACT_MOBILE_FLAG":"",
"LIST_DIS_GROUP":"",
"ACT_CODE":"delete",
"ACT_EXPRESSION_FLAG":"0"
},
{
"SERV_ID":"OA_ZH_ASSAF_AS",
"ACT_WS_RESULT":"",
"S_FLAG":"1",
"ACT_LOG_FLAG":"2",
"ACT_ID":"0lq0tYxw1ega0ePBqYrJvb",
"ACT_HOT_KEY":"",
"S_MTIME":"2013-04-18 15:12:54:599",
"_ROWNUM_":"2",
"ACT_TYPE":"2",
"ACT_TIP":"",
"_PK_":"0lq0tYxw1ega0ePBqYrJvb",
"ACT_WS_FLAG":"2",
"ACT_GROUP":"1",
"ACT_NAME":"保存",
"ACT_CSS":"save",
"ACT_EXPRESSION":"",
"ACT_MEMO":"",
"SY_SERV_ACT_PARAM":
[
],
"ACT_ORDER":"3",
"ACT_MOBILE_FLAG":"",
"LIST_DIS_GROUP":"",
"ACT_CODE":"save",
"ACT_EXPRESSION_FLAG":"0"
},
{
"SERV_ID":"OA_ZH_ASSAF_AS",
"ACT_WS_RESULT":"",
"S_FLAG":"1",
"ACT_LOG_FLAG":"2",
"ACT_ID":"0gYDFKGJBfgFSQDjFTVvY2",
"ACT_HOT_KEY":"",
"S_MTIME":"2013-04-18 15:12:57:188",
"_ROWNUM_":"3",
"ACT_TYPE":"3",
"ACT_TIP":"",
"_PK_":"0gYDFKGJBfgFSQDjFTVvY2",
"ACT_WS_FLAG":"2",
"ACT_GROUP":"2",
"ACT_NAME":"查看",
"ACT_CSS":"view",
"ACT_EXPRESSION":"",
"ACT_MEMO":"",
"SY_SERV_ACT_PARAM":
[
],
"ACT_ORDER":"4",
"ACT_MOBILE_FLAG":"",
"LIST_DIS_GROUP":"",
"ACT_CODE":"byid",
"ACT_EXPRESSION_FLAG":"0"
},
{
"SERV_ID":"OA_ZH_ASSAF_AS",
"ACT_WS_RESULT":"",
"S_FLAG":"2",
"ACT_LOG_FLAG":"2",
"ACT_ID":"04Szb6Pg50coIaDmNEZXB7",
"ACT_HOT_KEY":"",
"S_MTIME":"2013-10-14 14:45:59:576",
"_ROWNUM_":"4",
"ACT_TYPE":"1",
"ACT_TIP":"",
"_PK_":"04Szb6Pg50coIaDmNEZXB7",
"ACT_WS_FLAG":"2",
"ACT_GROUP":"1",
"ACT_NAME":" 保 存 ",
"ACT_CSS":"batchSave",
"ACT_EXPRESSION":"",
"ACT_MEMO":"",
"SY_SERV_ACT_PARAM":
[
],
"ACT_ORDER":"30",
"ACT_MOBILE_FLAG":"1",
"LIST_DIS_GROUP":"",
"ACT_CODE":"batchSave",
"ACT_EXPRESSION_FLAG":"0"
},
{
"SERV_ID":"OA_ZH_ASSAF_AS",
"ACT_WS_RESULT":"",
"S_FLAG":"2",
"ACT_LOG_FLAG":"2",
"ACT_ID":"3VT40espBbsXKYsvLoeNOzW",
"ACT_HOT_KEY":"",
"S_MTIME":"2013-10-14 14:45:59:808",
"_ROWNUM_":"5",
"ACT_TYPE":"2",
"ACT_TIP":"",
"_PK_":"3VT40espBbsXKYsvLoeNOzW",
"ACT_WS_FLAG":"2",
"ACT_GROUP":"1",
"ACT_NAME":"复制并新建",
"ACT_CSS":"copy",
"ACT_EXPRESSION":"'#_ADD_#'==''",
"ACT_MEMO":"",
"SY_SERV_ACT_PARAM":
[
],
"ACT_ORDER":"60",
"ACT_MOBILE_FLAG":"1",
"LIST_DIS_GROUP":"",
"ACT_CODE":"copyNew",
"ACT_EXPRESSION_FLAG":"0"
},
{
"SERV_ID":"OA_ZH_ASSAF_AS",
"ACT_WS_RESULT":"",
"S_FLAG":"1",
"ACT_LOG_FLAG":"2",
"ACT_ID":"0KdEFMMOopR89pnqBjmukEge",
"ACT_HOT_KEY":"",
"S_MTIME":"2013-10-14 14:46:15:801",
"_ROWNUM_":"6",
"ACT_TYPE":"3",
"ACT_TIP":"",
"_PK_":"0KdEFMMOopR89pnqBjmukEge",
"ACT_WS_FLAG":"2",
"ACT_GROUP":"2",
"ACT_NAME":"变更历史",
"ACT_CSS":"search",
"ACT_EXPRESSION":"'#_ADD_#'==''",
"ACT_MEMO":"",
"SY_SERV_ACT_PARAM":
[
],
"ACT_ORDER":"70",
"ACT_MOBILE_FLAG":"1",
"LIST_DIS_GROUP":"",
"ACT_CODE":"logItem",
"ACT_EXPRESSION_FLAG":"0"
},
{
"SERV_ID":"OA_ZH_ASSAF_AS",
"ACT_WS_RESULT":"",
"S_FLAG":"2",
"ACT_LOG_FLAG":"2",
"ACT_ID":"3MCtPViEl2Nbt5W64FS7ugk",
"ACT_HOT_KEY":"",
"S_MTIME":"2013-10-14 14:45:59:751",
"_ROWNUM_":"7",
"ACT_TYPE":"1",
"ACT_TIP":"",
"_PK_":"3MCtPViEl2Nbt5W64FS7ugk",
"ACT_WS_FLAG":"2",
"ACT_GROUP":"1",
"ACT_NAME":" 导 入 ",
"ACT_CSS":"imp",
"ACT_EXPRESSION":"",
"ACT_MEMO":"",
"SY_SERV_ACT_PARAM":
[
],
"ACT_ORDER":"110",
"ACT_MOBILE_FLAG":"1",
"LIST_DIS_GROUP":"",
"ACT_CODE":"imp",
"ACT_EXPRESSION_FLAG":"0"
},
{
"SERV_ID":"OA_ZH_ASSAF_AS",
"ACT_WS_RESULT":"",
"S_FLAG":"1",
"ACT_LOG_FLAG":"2",
"ACT_ID":"1WicQJVHtb6G8TNQumARBNi",
"ACT_HOT_KEY":"",
"S_MTIME":"2013-12-30 11:54:51:646",
"_ROWNUM_":"8",
"ACT_TYPE":"1",
"ACT_TIP":"",
"_PK_":"1WicQJVHtb6G8TNQumARBNi",
"ACT_WS_FLAG":"2",
"ACT_GROUP":"2",
"ACT_NAME":" 导 出Excel",
"ACT_CSS":"exp",
"ACT_EXPRESSION":"",
"ACT_MEMO":"",
"SY_SERV_ACT_PARAM":
[
],
"ACT_ORDER":"120",
"ACT_MOBILE_FLAG":"2",
"LIST_DIS_GROUP":"",
"ACT_CODE":"exp",
"ACT_EXPRESSION_FLAG":"0"
},
{
"SERV_ID":"OA_ZH_ASSAF_AS",
"ACT_WS_RESULT":"",
"S_FLAG":"2",
"ACT_LOG_FLAG":"2",
"ACT_ID":"1nz0pATm9dEFYO3JyhVTtq",
"ACT_HOT_KEY":"",
"S_MTIME":"2013-10-14 14:45:59:930",
"_ROWNUM_":"9",
"ACT_TYPE":"2",
"ACT_TIP":"",
"_PK_":"1nz0pATm9dEFYO3JyhVTtq",
"ACT_WS_FLAG":"2",
"ACT_GROUP":"2",
"ACT_NAME":" 接 收 ",
"ACT_CSS":"exp",
"ACT_EXPRESSION":"",
"ACT_MEMO":"this.receive();",
"SY_SERV_ACT_PARAM":
[
],
"ACT_ORDER":"130",
"ACT_MOBILE_FLAG":"1",
"LIST_DIS_GROUP":"",
"ACT_CODE":"receive",
"ACT_EXPRESSION_FLAG":"0"
},
{
"SERV_ID":"OA_ZH_ASSAF_AS",
"ACT_WS_RESULT":"",
"S_FLAG":"2",
"ACT_LOG_FLAG":"2",
"ACT_ID":"2AP1Yuusxfl97c2Xy5L0j5I",
"ACT_HOT_KEY":"",
"S_MTIME":"2013-10-14 14:45:59:973",
"_ROWNUM_":"10",
"ACT_TYPE":"1",
"ACT_TIP":"zip文件导入",
"_PK_":"2AP1Yuusxfl97c2Xy5L0j5I",
"ACT_WS_FLAG":"2",
"ACT_GROUP":"1",
"ACT_NAME":"批量导入",
"ACT_CSS":"imp",
"ACT_EXPRESSION":"",
"ACT_MEMO":"",
"SY_SERV_ACT_PARAM":
[
],
"ACT_ORDER":"140",
"ACT_MOBILE_FLAG":"1",
"LIST_DIS_GROUP":"",
"ACT_CODE":"impZip",
"ACT_EXPRESSION_FLAG":"0"
},
{
"SERV_ID":"OA_ZH_ASSAF_AS",
"ACT_WS_RESULT":"",
"S_FLAG":"2",
"ACT_LOG_FLAG":"2",
"ACT_ID":"0XHb5QRGRf7qkEwGMDbHcOy",
"ACT_HOT_KEY":"",
"S_MTIME":"2013-10-14 14:46:00:018",
"_ROWNUM_":"11",
"ACT_TYPE":"1",
"ACT_TIP":"zip文件导出",
"_PK_":"0XHb5QRGRf7qkEwGMDbHcOy",
"ACT_WS_FLAG":"2",
"ACT_GROUP":"2",
"ACT_NAME":"批量导出",
"ACT_CSS":"imp",
"ACT_EXPRESSION":"",
"ACT_MEMO":"",
"SY_SERV_ACT_PARAM":
[
],
"ACT_ORDER":"150",
"ACT_MOBILE_FLAG":"1",
"LIST_DIS_GROUP":"",
"ACT_CODE":"expZip",
"ACT_EXPRESSION_FLAG":"0"
}
],
"SERV_CARD_TMPL":"2",
"SERV_KEYS":"AS_ID",
"SERV_LIST_STYLE":"",
"S_MTIME":"2014-10-21 09:51:32:051",
"SERV_MEMO":"",
"SERV_DATA_TITLE":"#AS_TITLE#",
"SERV_AUTH_FLAG":"1",
"SERV_JS":"<script type=\"text\/javascript\" src=\"\/oa\/zh\/afterListViewLoad.js\"><\/script>",
"SERV_CARD_LOAD":"1",
"SERV_NO_COUNT":"2",
"SERV_LOCK_FLAG":"2",
"SERV_SQL_ORDER":"S_MTIME DESC",
"SERV_MOBILE_JS":"",
"SERV_RELATE_CONFIG":"",
"SERV_RELATE_FLAG":"0",
"SERV_FILE_PATH":"",
"SY_SERV_LINK":
[
{
"SERV_ID":"OA_ZH_ASSAF_AS",
"S_FLAG":"1",
"LINK_SERV_QUERY":"2",
"LINK_EXPRESSION":"",
"S_MTIME":"2013-10-16 14:56:16:261",
"_ROWNUM_":"0",
"LINK_REFRESH":"1",
"LINK_UPDATE_FLAG":"2",
"LINK_READONLY":"1",
"LINK_DELETE_FLAG":"2",
"LINK_MAIN_LIST":"2",
"LINK_QUERY_FLAG":"2",
"LINK_SHOW_POSITION":"3",
"SY_SERV_LINK_ITEM":
[
{
"LINK_WHERE_FLAG":"1",
"_PK_":"2y8vBvAg92BrWNXRCVYUTDb",
"LITEM_ID":"2y8vBvAg92BrWNXRCVYUTDb",
"_ROWNUM_":"0",
"LINK_ID":"1XpUpZPrVfX9mrhEyKRMhx",
"LINK_ITEM_CODE":"DATA_ID",
"ITEM_CODE":"AS_ID",
"LINK_VALUE_FLAG":"1"
},
{
"LINK_WHERE_FLAG":"2",
"_PK_":"0K5DWovoJfFp6gMXc9IIzj",
"LITEM_ID":"0K5DWovoJfFp6gMXc9IIzj",
"_ROWNUM_":"1",
"LINK_ID":"1XpUpZPrVfX9mrhEyKRMhx",
"LINK_ITEM_CODE":"readOnly",
"ITEM_CODE":"false",
"LINK_VALUE_FLAG":"2"
}
],
"_PK_":"1XpUpZPrVfX9mrhEyKRMhx",
"LINK_WHERE":"and SEND_STATUS > 1",
"LINK_SERV_ID":"OA_COMM_SEND_DETAIL",
"LINK_PAGE_COUNT":"50",
"LINK_ID":"1XpUpZPrVfX9mrhEyKRMhx",
"LINK_NAME":"传阅列表",
"LINK_SHOW_MOBILE":"0",
"LINK_ORDER":"3",
"LINK_SHOW_TYPE":"1"
},
{
"SERV_ID":"OA_ZH_ASSAF_AS",
"S_FLAG":"1",
"LINK_SERV_QUERY":"2",
"LINK_EXPRESSION":"",
"S_MTIME":"2013-09-24 18:01:16:375",
"_ROWNUM_":"1",
"LINK_REFRESH":"2",
"LINK_UPDATE_FLAG":"2",
"LINK_READONLY":"1",
"LINK_DELETE_FLAG":"2",
"LINK_MAIN_LIST":"2",
"LINK_QUERY_FLAG":"2",
"LINK_SHOW_POSITION":"3",
"SY_SERV_LINK_ITEM":
[
],
"_PK_":"2kQR9uwhxbdaQM1LBlI6mm",
"LINK_WHERE":"\/sy\/comm\/comment\/displayComment.jsp?data={\"DATA_ID\":\"#AS_ID#\",\"SERV_ID\":\"OA_ZH_ASSAF_AS\"}",
"LINK_SERV_ID":"GW_COMMENT",
"LINK_PAGE_COUNT":"50",
"LINK_ID":"2kQR9uwhxbdaQM1LBlI6mm",
"LINK_NAME":"备注",
"LINK_SHOW_MOBILE":"0",
"LINK_ORDER":"5",
"LINK_SHOW_TYPE":"3"
}
],
"S_FLAG":"1",
"SAFE_FLAG":"1",
"TABLE_VIEW":"OA_ZH_ASSAF_AS",
"SY_SERV_QUERY":
[
],
"SY_SERV_ITEM":
[
{
"SERV_ID":"OA_ZH_ASSAF_AS",
"ITEM_CARD_WIDTH":"0",
"ITEM_LOG_FLAG":"2",
"ITEM_TIP":"",
"ITEM_ORDER_CODES":"",
"ITEM_CARD_FORMAT":"",
"ITEM_LIST_STYLE":"",
"ITEM_VALIDATE":"",
"ITEM_MEMO":"主键ID",
"ITEM_VALIDATE_HINT":"",
"ITEM_NOTNULL":"2",
"ITEM_LIST_ORDER":"0",
"ITEM_FIELD_TYPE":"STR",
"ITEM_SEARCH_FLAG":"2",
"ITEM_INPUT_MODE":"1",
"ITEM_USER_FLAG":"0",
"_ROWNUM_":"0",
"ITEM_LIST_WIDTH":"0",
"ITEM_EXPTENDS":"",
"ITEM_NAME":"主键ID",
"ITEM_NOTNULL_SCRIPT":"",
"ITEM_CARD_ORDER":"0",
"ITEM_CARD_COLS":"1",
"ITEM_SUM_FLAG":"0",
"ITEM_TYPE":"1",
"S_MTIME":"2013-04-18 15:08:37:732",
"ITEM_LIST_FORMAT":"",
"ITEM_ID":"3A0x78oh1etW7VAR17NYqr",
"ITEM_LIST_FLAG":"2",
"ITEM_CARD_DISABLE":"2",
"ITEM_CARD_ROWS":"1",
"ITEM_READONLY":"2",
"ITEM_HIDDEN_SCRIPT":"",
"ITEM_LIST_EDIT":"2",
"DICT_ID":"",
"ITEM_READONLY_SCRIPT":"",
"ITEM_FIELD_LENGTH":"40",
"S_FLAG":"1",
"ITEM_CARD_LINK":"",
"ITEM_HIDDEN":"1",
"ITEM_CARD_STYLE":"",
"ITEM_UNIQUE_GROUP":"0",
"_PK_":"3A0x78oh1etW7VAR17NYqr",
"ITEM_LIST_ALIGN":"1",
"ITEM_INPUT_TYPE":"1",
"ITEM_LIST_LINK":"",
"ITEM_INPUT_FLAG":"2",
"ITEM_CODE":"AS_ID",
"ITEM_MOBILE_TYPE":"3",
"ITEM_LABEL_HIDDEN":"0",
"ITEM_INPUT_DEFAULT":"",
"ITEM_INPUT_CONFIG":""
},
{
"SERV_ID":"OA_ZH_ASSAF_AS",
"ITEM_CARD_WIDTH":"125",
"ITEM_LOG_FLAG":"1",
"ITEM_TIP":"",
"ITEM_ORDER_CODES":"",
"ITEM_CARD_FORMAT":"",
"ITEM_LIST_STYLE":"",
"ITEM_VALIDATE":"",
"ITEM_MEMO":"编号",
"ITEM_VALIDATE_HINT":"",
"ITEM_NOTNULL":"2",
"ITEM_LIST_ORDER":"1",
"ITEM_FIELD_TYPE":"STR",
"ITEM_SEARCH_FLAG":"2",
"ITEM_INPUT_MODE":"1",
"ITEM_USER_FLAG":"0",
"_ROWNUM_":"1",
"ITEM_LIST_WIDTH":"0",
"ITEM_EXPTENDS":"{'COMBO':{'ITEM_CODES':'GW_YEAR,GW_YEAR_NUMBER','SUFFIX':'号','SEP':'-','WRAP':{'GW_YEAR':\n\n{'BEFORE':'〔','AFTER':'〕'}}}}",
"ITEM_NAME":"编号",
"ITEM_NOTNULL_SCRIPT":"",
"ITEM_CARD_ORDER":"0",
"ITEM_CARD_COLS":"1",
"ITEM_SUM_FLAG":"0",
"ITEM_TYPE":"1",
"S_MTIME":"2013-11-27 14:21:54:922",
"ITEM_LIST_FORMAT":"",
"ITEM_ID":"0CZLWB3Nt11Q84KEnldlsN3",
"ITEM_LIST_FLAG":"3",
"ITEM_CARD_DISABLE":"2",
"ITEM_CARD_ROWS":"1",
"ITEM_READONLY":"2",
"ITEM_HIDDEN_SCRIPT":"",
"ITEM_LIST_EDIT":"2",
"DICT_ID":"",
"ITEM_READONLY_SCRIPT":"",
"ITEM_FIELD_LENGTH":"42",
"S_FLAG":"1",
"ITEM_CARD_LINK":"",
"ITEM_HIDDEN":"2",
"ITEM_CARD_STYLE":"",
"ITEM_UNIQUE_GROUP":"0",
"_PK_":"0CZLWB3Nt11Q84KEnldlsN3",
"ITEM_LIST_ALIGN":"1",
"ITEM_INPUT_TYPE":"1",
"ITEM_LIST_LINK":"",
"ITEM_INPUT_FLAG":"2",
"ITEM_CODE":"GW_YEAR_CODE",
"ITEM_MOBILE_TYPE":"3",
"ITEM_LABEL_HIDDEN":"0",
"ITEM_INPUT_DEFAULT":"",
"ITEM_INPUT_CONFIG":""
},
{
"SERV_ID":"OA_ZH_ASSAF_AS",
"ITEM_CARD_WIDTH":"0",
"ITEM_LOG_FLAG":"2",
"ITEM_TIP":"",
"ITEM_ORDER_CODES":"",
"ITEM_CARD_FORMAT":"",
"ITEM_LIST_STYLE":"",
"ITEM_VALIDATE":"",
"ITEM_MEMO":"文件编号",
"ITEM_VALIDATE_HINT":"",
"ITEM_NOTNULL":"2",
"ITEM_LIST_ORDER":"2",
"ITEM_FIELD_TYPE":"STR",
"ITEM_SEARCH_FLAG":"1",
"ITEM_INPUT_MODE":"1",
"ITEM_USER_FLAG":"0",
"_ROWNUM_":"2",
"ITEM_LIST_WIDTH":"0",
"ITEM_EXPTENDS":"",
"ITEM_NAME":"文件编号",
"ITEM_NOTNULL_SCRIPT":"",
"ITEM_CARD_ORDER":"0",
"ITEM_CARD_COLS":"1",
"ITEM_SUM_FLAG":"0",
"ITEM_TYPE":"1",
"S_MTIME":"2013-11-27 14:21:25:295",
"ITEM_LIST_FORMAT":"",
"ITEM_ID":"1jOEDGNW5a6qhkv00pxDuVc",
"ITEM_LIST_FLAG":"1",
"ITEM_CARD_DISABLE":"2",
"ITEM_CARD_ROWS":"1",
"ITEM_READONLY":"2",
"ITEM_HIDDEN_SCRIPT":"",
"ITEM_LIST_EDIT":"2",
"DICT_ID":"",
"ITEM_READONLY_SCRIPT":"",
"ITEM_FIELD_LENGTH":"40",
"S_FLAG":"1",
"ITEM_CARD_LINK":"",
"ITEM_HIDDEN":"1",
"ITEM_CARD_STYLE":"",
"ITEM_UNIQUE_GROUP":"0",
"_PK_":"1jOEDGNW5a6qhkv00pxDuVc",
"ITEM_LIST_ALIGN":"1",
"ITEM_INPUT_TYPE":"1",
"ITEM_LIST_LINK":"",
"ITEM_INPUT_FLAG":"2",
"ITEM_CODE":"GW_CODE",
"ITEM_MOBILE_TYPE":"3",
"ITEM_LABEL_HIDDEN":"0",
"ITEM_INPUT_DEFAULT":"",
"ITEM_INPUT_CONFIG":""
},
{
"SERV_ID":"OA_ZH_ASSAF_AS",
"ITEM_CARD_WIDTH":"45",
"ITEM_LOG_FLAG":"2",
"ITEM_TIP":"",
"ITEM_ORDER_CODES":"",
"ITEM_CARD_FORMAT":"",
"ITEM_LIST_STYLE":"",
"ITEM_VALIDATE":"",
"ITEM_MEMO":"流水号",
"ITEM_VALIDATE_HINT":"",
"ITEM_NOTNULL":"2",
"ITEM_LIST_ORDER":"3",
"ITEM_FIELD_TYPE":"NUM",
"ITEM_SEARCH_FLAG":"2",
"ITEM_INPUT_MODE":"1",
"ITEM_USER_FLAG":"0",
"_ROWNUM_":"3",
"ITEM_LIST_WIDTH":"0",
"ITEM_EXPTENDS":"",
"ITEM_NAME":"流水号",
"ITEM_NOTNULL_SCRIPT":"",
"ITEM_CARD_ORDER":"0",
"ITEM_CARD_COLS":"1",
"ITEM_SUM_FLAG":"0",
"ITEM_TYPE":"1",
"S_MTIME":"2013-09-23 18:05:30:870",
"ITEM_LIST_FORMAT":"",
"ITEM_ID":"1FSz0RS7p7VqPCn7xDaK3b",
"ITEM_LIST_FLAG":"2",
"ITEM_CARD_DISABLE":"2",
"ITEM_CARD_ROWS":"1",
"ITEM_READONLY":"2",
"ITEM_HIDDEN_SCRIPT":"",
"ITEM_LIST_EDIT":"2",
"DICT_ID":"",
"ITEM_READONLY_SCRIPT":"",
"ITEM_FIELD_LENGTH":"8",
"S_FLAG":"1",
"ITEM_CARD_LINK":"",
"ITEM_HIDDEN":"2",
"ITEM_CARD_STYLE":"",
"ITEM_UNIQUE_GROUP":"0",
"_PK_":"1FSz0RS7p7VqPCn7xDaK3b",
"ITEM_LIST_ALIGN":"1",
"ITEM_INPUT_TYPE":"1",
"ITEM_LIST_LINK":"",
"ITEM_INPUT_FLAG":"2",
"ITEM_CODE":"GW_YEAR_NUMBER",
"ITEM_MOBILE_TYPE":"3",
"ITEM_LABEL_HIDDEN":"0",
"ITEM_INPUT_DEFAULT":"0",
"ITEM_INPUT_CONFIG":""
},
{
"SERV_ID":"OA_ZH_ASSAF_AS",
"ITEM_CARD_WIDTH":"45",
"ITEM_LOG_FLAG":"2",
"ITEM_TIP":"",
"ITEM_ORDER_CODES":"",
"ITEM_CARD_FORMAT":"",
"ITEM_LIST_STYLE":"",
"ITEM_VALIDATE":"",
"ITEM_MEMO":"年号",
"ITEM_VALIDATE_HINT":"",
"ITEM_NOTNULL":"2",
"ITEM_LIST_ORDER":"3",
"ITEM_FIELD_TYPE":"NUM",
"ITEM_SEARCH_FLAG":"2",
"ITEM_INPUT_MODE":"1",
"ITEM_USER_FLAG":"0",
"_ROWNUM_":"4",
"ITEM_LIST_WIDTH":"0",
"ITEM_EXPTENDS":"",
"ITEM_NAME":"年号",
"ITEM_NOTNULL_SCRIPT":"",
"ITEM_CARD_ORDER":"0",
"ITEM_CARD_COLS":"1",
"ITEM_SUM_FLAG":"0",
"ITEM_TYPE":"1",
"S_MTIME":"2013-09-24 10:45:43:456",
"ITEM_LIST_FORMAT":"",
"ITEM_ID":"12Ud9h1wxb2uX9lOblmXgG0",
"ITEM_LIST_FLAG":"2",
"ITEM_CARD_DISABLE":"2",
"ITEM_CARD_ROWS":"1",
"ITEM_READONLY":"2",
"ITEM_HIDDEN_SCRIPT":"",
"ITEM_LIST_EDIT":"2",
"DICT_ID":"",
"ITEM_READONLY_SCRIPT":"",
"ITEM_FIELD_LENGTH":"23",
"S_FLAG":"1",
"ITEM_CARD_LINK":"",
"ITEM_HIDDEN":"2",
"ITEM_CARD_STYLE":"",
"ITEM_UNIQUE_GROUP":"0",
"_PK_":"12Ud9h1wxb2uX9lOblmXgG0",
"ITEM_LIST_ALIGN":"1",
"ITEM_INPUT_TYPE":"1",
"ITEM_LIST_LINK":"",
"ITEM_INPUT_FLAG":"2",
"ITEM_CODE":"GW_YEAR",
"ITEM_MOBILE_TYPE":"3",
"ITEM_LABEL_HIDDEN":"0",
"ITEM_INPUT_DEFAULT":"@DATE_YEAR@",
"ITEM_INPUT_CONFIG":""
},
{
"SERV_ID":"OA_ZH_ASSAF_AS",
"ITEM_CARD_WIDTH":"0",
"ITEM_LOG_FLAG":"1",
"ITEM_TIP":"",
"ITEM_ORDER_CODES":"",
"ITEM_CARD_FORMAT":"",
"ITEM_LIST_STYLE":"",
"ITEM_VALIDATE":"",
"ITEM_MEMO":"标题",
"ITEM_VALIDATE_HINT":"",
"ITEM_NOTNULL":"1",
"ITEM_LIST_ORDER":"10",
"ITEM_FIELD_TYPE":"STR",
"ITEM_SEARCH_FLAG":"1",
"ITEM_INPUT_MODE":"1",
"ITEM_USER_FLAG":"0",
"_ROWNUM_":"5",
"ITEM_LIST_WIDTH":"0",
"ITEM_EXPTENDS":"",
"ITEM_NAME":"标题",
"ITEM_NOTNULL_SCRIPT":"",
"ITEM_CARD_ORDER":"0",
"ITEM_CARD_COLS":"2",
"ITEM_SUM_FLAG":"0",
"ITEM_TYPE":"1",
"S_MTIME":"2013-10-12 13:55:05:324",
"ITEM_LIST_FORMAT":"Format.limit(20)",
"ITEM_ID":"01B6MmuM12CXFiz8v-jcdO",
"ITEM_LIST_FLAG":"1",
"ITEM_CARD_DISABLE":"2",
"ITEM_CARD_ROWS":"1",
"ITEM_READONLY":"2",
"ITEM_HIDDEN_SCRIPT":"",
"ITEM_LIST_EDIT":"2",
"DICT_ID":"",
"ITEM_READONLY_SCRIPT":"",
"ITEM_FIELD_LENGTH":"200",
"S_FLAG":"1",
"ITEM_CARD_LINK":"",
"ITEM_HIDDEN":"2",
"ITEM_CARD_STYLE":"",
"ITEM_UNIQUE_GROUP":"0",
"_PK_":"01B6MmuM12CXFiz8v-jcdO",
"ITEM_LIST_ALIGN":"1",
"ITEM_INPUT_TYPE":"1",
"ITEM_LIST_LINK":"Tools.openCard(this)",
"ITEM_INPUT_FLAG":"2",
"ITEM_CODE":"AS_TITLE",
"ITEM_MOBILE_TYPE":"3",
"ITEM_LABEL_HIDDEN":"0",
"ITEM_INPUT_DEFAULT":"",
"ITEM_INPUT_CONFIG":""
},
{
"SERV_ID":"OA_ZH_ASSAF_AS",
"ITEM_CARD_WIDTH":"0",
"ITEM_LOG_FLAG":"2",
"ITEM_TIP":"",
"ITEM_ORDER_CODES":"",
"ITEM_CARD_FORMAT":"",
"ITEM_LIST_STYLE":"",
"ITEM_VALIDATE":"",
"ITEM_MEMO":"起草人",
"ITEM_VALIDATE_HINT":"",
"ITEM_NOTNULL":"2",
"ITEM_LIST_ORDER":"20",
"ITEM_FIELD_TYPE":"STR",
"ITEM_SEARCH_FLAG":"2",
"ITEM_INPUT_MODE":"3",
"ITEM_USER_FLAG":"0",
"_ROWNUM_":"6",
"ITEM_LIST_WIDTH":"0",
"ITEM_EXPTENDS":"",
"ITEM_NAME":"起草人",
"ITEM_NOTNULL_SCRIPT":"",
"ITEM_CARD_ORDER":"0",
"ITEM_CARD_COLS":"1",
"ITEM_SUM_FLAG":"0",
"ITEM_TYPE":"1",
"S_MTIME":"2013-11-27 16:25:00:341",
"ITEM_LIST_FORMAT":"",
"ITEM_ID":"0vIHsDKXFcX8Z9xAe7avvn",
"ITEM_LIST_FLAG":"2",
"ITEM_CARD_DISABLE":"2",
"ITEM_CARD_ROWS":"1",
"ITEM_READONLY":"1",
"ITEM_HIDDEN_SCRIPT":"",
"ITEM_LIST_EDIT":"2",
"DICT_ID":"SY_ORG_DEPT_USER_ALL",
"ITEM_READONLY_SCRIPT":"",
"ITEM_FIELD_LENGTH":"40",
"S_FLAG":"1",
"ITEM_CARD_LINK":"",
"ITEM_HIDDEN":"2",
"ITEM_CARD_STYLE":"",
"ITEM_UNIQUE_GROUP":"0",
"_PK_":"0vIHsDKXFcX8Z9xAe7avvn",
"ITEM_LIST_ALIGN":"3",
"ITEM_INPUT_TYPE":"1",
"ITEM_LIST_LINK":"",
"ITEM_INPUT_FLAG":"2",
"ITEM_CODE":"S_USER",
"ITEM_MOBILE_TYPE":"3",
"ITEM_LABEL_HIDDEN":"0",
"ITEM_INPUT_DEFAULT":"@USER_CODE@",
"ITEM_INPUT_CONFIG":"SY_ORG_DEPT_USER_ALL"
},
{
"SERV_ID":"OA_ZH_ASSAF_AS",
"ITEM_CARD_WIDTH":"0",
"ITEM_LOG_FLAG":"1",
"ITEM_TIP":"",
"ITEM_ORDER_CODES":"",
"ITEM_CARD_FORMAT":"",
"ITEM_LIST_STYLE":"",
"ITEM_VALIDATE":"",
"ITEM_MEMO":"更新时间",
"ITEM_VALIDATE_HINT":"",
"ITEM_NOTNULL":"1",
"ITEM_LIST_ORDER":"30",
"ITEM_FIELD_TYPE":"STR",
"ITEM_SEARCH_FLAG":"1",
"ITEM_INPUT_MODE":"4",
"ITEM_USER_FLAG":"0",
"_ROWNUM_":"7",
"ITEM_LIST_WIDTH":"0",
"ITEM_EXPTENDS":"",
"ITEM_NAME":"起草时间",
"ITEM_NOTNULL_SCRIPT":"",
"ITEM_CARD_ORDER":"0",
"ITEM_CARD_COLS":"1",
"ITEM_SUM_FLAG":"0",
"ITEM_TYPE":"1",
"S_MTIME":"2013-10-12 13:55:43:527",
"ITEM_LIST_FORMAT":"",
"ITEM_ID":"0xaMfljSRd28YBOiz09BIZ",
"ITEM_LIST_FLAG":"1",
"ITEM_CARD_DISABLE":"2",
"ITEM_CARD_ROWS":"1",
"ITEM_READONLY":"2",
"ITEM_HIDDEN_SCRIPT":"",
"ITEM_LIST_EDIT":"2",
"DICT_ID":"",
"ITEM_READONLY_SCRIPT":"",
"ITEM_FIELD_LENGTH":"23",
"S_FLAG":"1",
"ITEM_CARD_LINK":"",
"ITEM_HIDDEN":"2",
"ITEM_CARD_STYLE":"",
"ITEM_UNIQUE_GROUP":"0",
"_PK_":"0xaMfljSRd28YBOiz09BIZ",
"ITEM_LIST_ALIGN":"1",
"ITEM_INPUT_TYPE":"1",
"ITEM_LIST_LINK":"",
"ITEM_INPUT_FLAG":"2",
"ITEM_CODE":"S_ATIME",
"ITEM_MOBILE_TYPE":"3",
"ITEM_LABEL_HIDDEN":"0",
"ITEM_INPUT_DEFAULT":"@DATETIME@",
"ITEM_INPUT_CONFIG":""
},
{
"SERV_ID":"OA_ZH_ASSAF_AS",
"ITEM_CARD_WIDTH":"0",
"ITEM_LOG_FLAG":"1",
"ITEM_TIP":"",
"ITEM_ORDER_CODES":"",
"ITEM_CARD_FORMAT":"",
"ITEM_LIST_STYLE":"",
"ITEM_VALIDATE":"",
"ITEM_MEMO":"联系方式",
"ITEM_VALIDATE_HINT":"",
"ITEM_NOTNULL":"1",
"ITEM_LIST_ORDER":"40",
"ITEM_FIELD_TYPE":"STR",
"ITEM_SEARCH_FLAG":"2",
"ITEM_INPUT_MODE":"1",
"ITEM_USER_FLAG":"0",
"_ROWNUM_":"8",
"ITEM_LIST_WIDTH":"0",
"ITEM_EXPTENDS":"",
"ITEM_NAME":"联系方式",
"ITEM_NOTNULL_SCRIPT":"",
"ITEM_CARD_ORDER":"0",
"ITEM_CARD_COLS":"1",
"ITEM_SUM_FLAG":"0",
"ITEM_TYPE":"1",
"S_MTIME":"2013-10-12 13:55:59:347",
"ITEM_LIST_FORMAT":"",
"ITEM_ID":"1YS_k-QlR2nUmgKOh09M2a",
"ITEM_LIST_FLAG":"2",
"ITEM_CARD_DISABLE":"2",
"ITEM_CARD_ROWS":"1",
"ITEM_READONLY":"2",
"ITEM_HIDDEN_SCRIPT":"",
"ITEM_LIST_EDIT":"2",
"DICT_ID":"",
"ITEM_READONLY_SCRIPT":"",
"ITEM_FIELD_LENGTH":"40",
"S_FLAG":"1",
"ITEM_CARD_LINK":"",
"ITEM_HIDDEN":"2",
"ITEM_CARD_STYLE":"",
"ITEM_UNIQUE_GROUP":"0",
"_PK_":"1YS_k-QlR2nUmgKOh09M2a",
"ITEM_LIST_ALIGN":"1",
"ITEM_INPUT_TYPE":"1",
"ITEM_LIST_LINK":"",
"ITEM_INPUT_FLAG":"2",
"ITEM_CODE":"AS_LPHONE",
"ITEM_MOBILE_TYPE":"3",
"ITEM_LABEL_HIDDEN":"0",
"ITEM_INPUT_DEFAULT":"@OFFICE_PHONE@",
"ITEM_INPUT_CONFIG":""
},
{
"SERV_ID":"OA_ZH_ASSAF_AS",
"ITEM_CARD_WIDTH":"0",
"ITEM_LOG_FLAG":"2",
"ITEM_TIP":"",
"ITEM_ORDER_CODES":"",
"ITEM_CARD_FORMAT":"",
"ITEM_LIST_STYLE":"",
"ITEM_VALIDATE":"",
"ITEM_MEMO":"机构",
"ITEM_VALIDATE_HINT":"",
"ITEM_NOTNULL":"2",
"ITEM_LIST_ORDER":"50",
"ITEM_FIELD_TYPE":"STR",
"ITEM_SEARCH_FLAG":"2",
"ITEM_INPUT_MODE":"3",
"ITEM_USER_FLAG":"0",
"_ROWNUM_":"9",
"ITEM_LIST_WIDTH":"0",
"ITEM_EXPTENDS":"",
"ITEM_NAME":"机构",
"ITEM_NOTNULL_SCRIPT":"",
"ITEM_CARD_ORDER":"0",
"ITEM_CARD_COLS":"1",
"ITEM_SUM_FLAG":"0",
"ITEM_TYPE":"1",
"S_MTIME":"2013-12-04 14:44:58:385",
"ITEM_LIST_FORMAT":"",
"ITEM_ID":"1LInhdOY5e9acasodI63IU",
"ITEM_LIST_FLAG":"2",
"ITEM_CARD_DISABLE":"2",
"ITEM_CARD_ROWS":"1",
"ITEM_READONLY":"1",
"ITEM_HIDDEN_SCRIPT":"",
"ITEM_LIST_EDIT":"2",
"DICT_ID":"SY_ORG_ODEPT_ALL",
"ITEM_READONLY_SCRIPT":"",
"ITEM_FIELD_LENGTH":"40",
"S_FLAG":"1",
"ITEM_CARD_LINK":"",
"ITEM_HIDDEN":"2",
"ITEM_CARD_STYLE":"",
"ITEM_UNIQUE_GROUP":"0",
"_PK_":"1LInhdOY5e9acasodI63IU",
"ITEM_LIST_ALIGN":"1",
"ITEM_INPUT_TYPE":"1",
"ITEM_LIST_LINK":"",
"ITEM_INPUT_FLAG":"2",
"ITEM_CODE":"S_ODEPT",
"ITEM_MOBILE_TYPE":"3",
"ITEM_LABEL_HIDDEN":"0",
"ITEM_INPUT_DEFAULT":"@ODEPT_CODE@",
"ITEM_INPUT_CONFIG":"SY_ORG_ODEPT_ALL,{\"LEVEL\":\"2\"}"
},
{
"SERV_ID":"OA_ZH_ASSAF_AS",
"ITEM_CARD_WIDTH":"0",
"ITEM_LOG_FLAG":"2",
"ITEM_TIP":"",
"ITEM_ORDER_CODES":"",
"ITEM_CARD_FORMAT":"",
"ITEM_LIST_STYLE":"",
"ITEM_VALIDATE":"",
"ITEM_MEMO":"",
"ITEM_VALIDATE_HINT":"",
"ITEM_NOTNULL":"1",
"ITEM_LIST_ORDER":"55",
"ITEM_FIELD_TYPE":"STR",
"ITEM_SEARCH_FLAG":"1",
"ITEM_INPUT_MODE":"1",
"ITEM_USER_FLAG":"2",
"_ROWNUM_":"10",
"ITEM_LIST_WIDTH":"0",
"ITEM_EXPTENDS":"",
"ITEM_NAME":"服务类型",
"ITEM_NOTNULL_SCRIPT":"",
"ITEM_CARD_ORDER":"0",
"ITEM_CARD_COLS":"1",
"ITEM_SUM_FLAG":"2",
"ITEM_TYPE":"1",
"S_MTIME":"2014-10-21 09:44:48:047",
"ITEM_LIST_FORMAT":"",
"ITEM_ID":"0LMnDHII1aLG0Vh3RLLEkQz",
"ITEM_LIST_FLAG":"1",
"ITEM_CARD_DISABLE":"2",
"ITEM_CARD_ROWS":"1",
"ITEM_READONLY":"2",
"ITEM_HIDDEN_SCRIPT":"",
"ITEM_LIST_EDIT":"2",
"DICT_ID":"AS_SERV_TYPES",
"ITEM_READONLY_SCRIPT":"",
"ITEM_FIELD_LENGTH":"40",
"S_FLAG":"1",
"ITEM_CARD_LINK":"",
"ITEM_HIDDEN":"2",
"ITEM_CARD_STYLE":"",
"ITEM_UNIQUE_GROUP":"0",
"_PK_":"0LMnDHII1aLG0Vh3RLLEkQz",
"ITEM_LIST_ALIGN":"1",
"ITEM_INPUT_TYPE":"2",
"ITEM_LIST_LINK":"",
"ITEM_INPUT_FLAG":"2",
"ITEM_CODE":"AS_SERV",
"ITEM_MOBILE_TYPE":"3",
"ITEM_LABEL_HIDDEN":"2",
"ITEM_INPUT_DEFAULT":"DNO",
"ITEM_INPUT_CONFIG":"AS_SERV_TYPES"
},
{
"SERV_ID":"OA_ZH_ASSAF_AS",
"ITEM_CARD_WIDTH":"0",
"ITEM_LOG_FLAG":"1",
"ITEM_TIP":"",
"ITEM_ORDER_CODES":"",
"ITEM_CARD_FORMAT":"",
"ITEM_LIST_STYLE":"",
"ITEM_VALIDATE":"",
"ITEM_MEMO":"服务单类型",
"ITEM_VALIDATE_HINT":"",
"ITEM_NOTNULL":"1",
"ITEM_LIST_ORDER":"60",
"ITEM_FIELD_TYPE":"STR",
"ITEM_SEARCH_FLAG":"1",
"ITEM_INPUT_MODE":"1",
"ITEM_USER_FLAG":"0",
"_ROWNUM_":"11",
"ITEM_LIST_WIDTH":"0",
"ITEM_EXPTENDS":"",
"ITEM_NAME":"服务单类型",
"ITEM_NOTNULL_SCRIPT":"",
"ITEM_CARD_ORDER":"0",
"ITEM_CARD_COLS":"1",
"ITEM_SUM_FLAG":"0",
"ITEM_TYPE":"1",
"S_MTIME":"2013-12-16 12:48:40:744",
"ITEM_LIST_FORMAT":"",
"ITEM_ID":"0YHlzLWrZbY8dea-4mg1OF",
"ITEM_LIST_FLAG":"1",
"ITEM_CARD_DISABLE":"2",
"ITEM_CARD_ROWS":"1",
"ITEM_READONLY":"2",
"ITEM_HIDDEN_SCRIPT":"",
"ITEM_LIST_EDIT":"2",
"DICT_ID":"AS_SERV-DNO",
"ITEM_READONLY_SCRIPT":"",
"ITEM_FIELD_LENGTH":"200",
"S_FLAG":"1",
"ITEM_CARD_LINK":"",
"ITEM_HIDDEN":"2",
"ITEM_CARD_STYLE":"",
"ITEM_UNIQUE_GROUP":"0",
"_PK_":"0YHlzLWrZbY8dea-4mg1OF",
"ITEM_LIST_ALIGN":"3",
"ITEM_INPUT_TYPE":"2",
"ITEM_LIST_LINK":"",
"ITEM_INPUT_FLAG":"2",
"ITEM_CODE":"AS_SERV_TYPES",
"ITEM_MOBILE_TYPE":"3",
"ITEM_LABEL_HIDDEN":"0",
"ITEM_INPUT_DEFAULT":"",
"ITEM_INPUT_CONFIG":"AS_SERV-DNO"
},
{
"SERV_ID":"OA_ZH_ASSAF_AS",
"ITEM_CARD_WIDTH":"0",
"ITEM_LOG_FLAG":"2",
"ITEM_TIP":"",
"ITEM_ORDER_CODES":"",
"ITEM_CARD_FORMAT":"",
"ITEM_LIST_STYLE":"",
"ITEM_VALIDATE":"",
"ITEM_MEMO":"办理环节",
"ITEM_VALIDATE_HINT":"",
"ITEM_NOTNULL":"2",
"ITEM_LIST_ORDER":"65",
"ITEM_FIELD_TYPE":"STR",
"ITEM_SEARCH_FLAG":"2",
"ITEM_INPUT_MODE":"1",
"ITEM_USER_FLAG":"0",
"_ROWNUM_":"12",
"ITEM_LIST_WIDTH":"0",
"ITEM_EXPTENDS":"",
"ITEM_NAME":"办理环节",
"ITEM_NOTNULL_SCRIPT":"",
"ITEM_CARD_ORDER":"250",
"ITEM_CARD_COLS":"1",
"ITEM_SUM_FLAG":"0",
"ITEM_TYPE":"1",
"S_MTIME":"2013-11-27 16:26:06:559",
"ITEM_LIST_FORMAT":"",
"ITEM_ID":"2pbjJH05YdbBoAPcHxmAIFk",
"ITEM_LIST_FLAG":"1",
"ITEM_CARD_DISABLE":"2",
"ITEM_CARD_ROWS":"1",
"ITEM_READONLY":"2",
"ITEM_HIDDEN_SCRIPT":"",
"ITEM_LIST_EDIT":"2",
"DICT_ID":"",
"ITEM_READONLY_SCRIPT":"",
"ITEM_FIELD_LENGTH":"4000",
"S_FLAG":"1",
"ITEM_CARD_LINK":"",
"ITEM_HIDDEN":"1",
"ITEM_CARD_STYLE":"",
"ITEM_UNIQUE_GROUP":"0",
"_PK_":"2pbjJH05YdbBoAPcHxmAIFk",
"ITEM_LIST_ALIGN":"1",
"ITEM_INPUT_TYPE":"1",
"ITEM_LIST_LINK":"",
"ITEM_INPUT_FLAG":"2",
"ITEM_CODE":"S_WF_USER_STATE",
"ITEM_MOBILE_TYPE":"3",
"ITEM_LABEL_HIDDEN":"0",
"ITEM_INPUT_DEFAULT":"",
"ITEM_INPUT_CONFIG":""
},
{
"SERV_ID":"OA_ZH_ASSAF_AS",
"ITEM_CARD_WIDTH":"0",
"ITEM_LOG_FLAG":"1",
"ITEM_TIP":"",
"ITEM_ORDER_CODES":"",
"ITEM_CARD_FORMAT":"",
"ITEM_LIST_STYLE":"",
"ITEM_VALIDATE":"",
"ITEM_MEMO":"所属应用系统名称",
"ITEM_VALIDATE_HINT":"",
"ITEM_NOTNULL":"2",
"ITEM_LIST_ORDER":"70",
"ITEM_FIELD_TYPE":"STR",
"ITEM_SEARCH_FLAG":"2",
"ITEM_INPUT_MODE":"3",
"ITEM_USER_FLAG":"0",
"_ROWNUM_":"13",
"ITEM_LIST_WIDTH":"0",
"ITEM_EXPTENDS":"",
"ITEM_NAME":"所属应用系统名称",
"ITEM_NOTNULL_SCRIPT":"",
"ITEM_CARD_ORDER":"0",
"ITEM_CARD_COLS":"1",
"ITEM_SUM_FLAG":"0",
"ITEM_TYPE":"1",
"S_MTIME":"2013-11-27 14:21:25:218",
"ITEM_LIST_FORMAT":"",
"ITEM_ID":"0_nns8mHJa_qCAXkOb5T0Y",
"ITEM_LIST_FLAG":"2",
"ITEM_CARD_DISABLE":"2",
"ITEM_CARD_ROWS":"1",
"ITEM_READONLY":"2",
"ITEM_HIDDEN_SCRIPT":"",
"ITEM_LIST_EDIT":"2",
"DICT_ID":"AS_ASP_NAME",
"ITEM_READONLY_SCRIPT":"",
"ITEM_FIELD_LENGTH":"200",
"S_FLAG":"1",
"ITEM_CARD_LINK":"",
"ITEM_HIDDEN":"2",
"ITEM_CARD_STYLE":"{'max-width':'130px; !important'}",
"ITEM_UNIQUE_GROUP":"0",
"_PK_":"0_nns8mHJa_qCAXkOb5T0Y",
"ITEM_LIST_ALIGN":"3",
"ITEM_INPUT_TYPE":"1",
"ITEM_LIST_LINK":"",
"ITEM_INPUT_FLAG":"2",
"ITEM_CODE":"AS_ASP_NAME",
"ITEM_MOBILE_TYPE":"3",
"ITEM_LABEL_HIDDEN":"0",
"ITEM_INPUT_DEFAULT":"",
"ITEM_INPUT_CONFIG":"AS_ASP_NAME,{\"TYPE\":\"multi\"}"
},
{
"SERV_ID":"OA_ZH_ASSAF_AS",
"ITEM_CARD_WIDTH":"0",
"ITEM_LOG_FLAG":"1",
"ITEM_TIP":"",
"ITEM_ORDER_CODES":"",
"ITEM_CARD_FORMAT":"",
"ITEM_LIST_STYLE":"",
"ITEM_VALIDATE":"",
"ITEM_MEMO":"摘要信息",
"ITEM_VALIDATE_HINT":"",
"ITEM_NOTNULL":"1",
"ITEM_LIST_ORDER":"80",
"ITEM_FIELD_TYPE":"STR",
"ITEM_SEARCH_FLAG":"2",
"ITEM_INPUT_MODE":"1",
"ITEM_USER_FLAG":"0",
"_ROWNUM_":"14",
"ITEM_LIST_WIDTH":"0",
"ITEM_EXPTENDS":"",
"ITEM_NAME":"摘要信息",
"ITEM_NOTNULL_SCRIPT":"",
"ITEM_CARD_ORDER":"0",
"ITEM_CARD_COLS":"2",
"ITEM_SUM_FLAG":"0",
"ITEM_TYPE":"1",
"S_MTIME":"2013-10-12 13:57:10:023",
"ITEM_LIST_FORMAT":"",
"ITEM_ID":"36qnLuPjtaqETmoz7pTNJH",
"ITEM_LIST_FLAG":"2",
"ITEM_CARD_DISABLE":"2",
"ITEM_CARD_ROWS":"1",
"ITEM_READONLY":"2",
"ITEM_HIDDEN_SCRIPT":"",
"ITEM_LIST_EDIT":"2",
"DICT_ID":"",
"ITEM_READONLY_SCRIPT":"",
"ITEM_FIELD_LENGTH":"1000",
"S_FLAG":"1",
"ITEM_CARD_LINK":"",
"ITEM_HIDDEN":"2",
"ITEM_CARD_STYLE":"",
"ITEM_UNIQUE_GROUP":"0",
"_PK_":"36qnLuPjtaqETmoz7pTNJH",
"ITEM_LIST_ALIGN":"1",
"ITEM_INPUT_TYPE":"5",
"ITEM_LIST_LINK":"",
"ITEM_INPUT_FLAG":"2",
"ITEM_CODE":"AS_SUM_INFO",
"ITEM_MOBILE_TYPE":"3",
"ITEM_LABEL_HIDDEN":"0",
"ITEM_INPUT_DEFAULT":"",
"ITEM_INPUT_CONFIG":""
},
{
"SERV_ID":"OA_ZH_ASSAF_AS",
"ITEM_CARD_WIDTH":"0",
"ITEM_LOG_FLAG":"2",
"ITEM_TIP":"",
"ITEM_ORDER_CODES":"",
"ITEM_CARD_FORMAT":"",
"ITEM_LIST_STYLE":"",
"ITEM_VALIDATE":"",
"ITEM_MEMO":"公司",
"ITEM_VALIDATE_HINT":"",
"ITEM_NOTNULL":"2",
"ITEM_LIST_ORDER":"110",
"ITEM_FIELD_TYPE":"STR",
"ITEM_SEARCH_FLAG":"2",
"ITEM_INPUT_MODE":"1",
"ITEM_USER_FLAG":"0",
"_ROWNUM_":"15",
"ITEM_LIST_WIDTH":"0",
"ITEM_EXPTENDS":"",
"ITEM_NAME":"公司",
"ITEM_NOTNULL_SCRIPT":"",
"ITEM_CARD_ORDER":"0",
"ITEM_CARD_COLS":"1",
"ITEM_SUM_FLAG":"0",
"ITEM_TYPE":"1",
"S_MTIME":"2013-04-18 15:08:37:797",
"ITEM_LIST_FORMAT":"",
"ITEM_ID":"30OasM84h6U86P1D3zEUWb",
"ITEM_LIST_FLAG":"2",
"ITEM_CARD_DISABLE":"2",
"ITEM_CARD_ROWS":"1",
"ITEM_READONLY":"2",
"ITEM_HIDDEN_SCRIPT":"",
"ITEM_LIST_EDIT":"2",
"DICT_ID":"",
"ITEM_READONLY_SCRIPT":"",
"ITEM_FIELD_LENGTH":"40",
"S_FLAG":"1",
"ITEM_CARD_LINK":"",
"ITEM_HIDDEN":"1",
"ITEM_CARD_STYLE":"",
"ITEM_UNIQUE_GROUP":"0",
"_PK_":"30OasM84h6U86P1D3zEUWb",
"ITEM_LIST_ALIGN":"1",
"ITEM_INPUT_TYPE":"1",
"ITEM_LIST_LINK":"",
"ITEM_INPUT_FLAG":"2",
"ITEM_CODE":"S_CMPY",
"ITEM_MOBILE_TYPE":"3",
"ITEM_LABEL_HIDDEN":"0",
"ITEM_INPUT_DEFAULT":"@CMPY_CODE@",
"ITEM_INPUT_CONFIG":""
},
{
"SERV_ID":"OA_ZH_ASSAF_AS",
"ITEM_CARD_WIDTH":"0",
"ITEM_LOG_FLAG":"2",
"ITEM_TIP":"",
"ITEM_ORDER_CODES":"",
"ITEM_CARD_FORMAT":"",
"ITEM_LIST_STYLE":"",
"ITEM_VALIDATE":"",
"ITEM_MEMO":"启用标志，1：启用；2：不启用；",
"ITEM_VALIDATE_HINT":"",
"ITEM_NOTNULL":"2",
"ITEM_LIST_ORDER":"120",
"ITEM_FIELD_TYPE":"NUM",
"ITEM_SEARCH_FLAG":"2",
"ITEM_INPUT_MODE":"1",
"ITEM_USER_FLAG":"0",
"_ROWNUM_":"16",
"ITEM_LIST_WIDTH":"0",
"ITEM_EXPTENDS":"",
"ITEM_NAME":"启用标志",
"ITEM_NOTNULL_SCRIPT":"",
"ITEM_CARD_ORDER":"0",
"ITEM_CARD_COLS":"1",
"ITEM_SUM_FLAG":"0",
"ITEM_TYPE":"1",
"S_MTIME":"2013-04-18 15:08:37:825",
"ITEM_LIST_FORMAT":"",
"ITEM_ID":"0k6Jh4d9l5BXaHdgpd2aqB",
"ITEM_LIST_FLAG":"2",
"ITEM_CARD_DISABLE":"2",
"ITEM_CARD_ROWS":"1",
"ITEM_READONLY":"2",
"ITEM_HIDDEN_SCRIPT":"",
"ITEM_LIST_EDIT":"2",
"DICT_ID":"",
"ITEM_READONLY_SCRIPT":"",
"ITEM_FIELD_LENGTH":"4",
"S_FLAG":"1",
"ITEM_CARD_LINK":"",
"ITEM_HIDDEN":"1",
"ITEM_CARD_STYLE":"",
"ITEM_UNIQUE_GROUP":"0",
"_PK_":"0k6Jh4d9l5BXaHdgpd2aqB",
"ITEM_LIST_ALIGN":"1",
"ITEM_INPUT_TYPE":"1",
"ITEM_LIST_LINK":"",
"ITEM_INPUT_FLAG":"2",
"ITEM_CODE":"S_FLAG",
"ITEM_MOBILE_TYPE":"3",
"ITEM_LABEL_HIDDEN":"0",
"ITEM_INPUT_DEFAULT":"1",
"ITEM_INPUT_CONFIG":""
},
{
"SERV_ID":"OA_ZH_ASSAF_AS",
"ITEM_CARD_WIDTH":"0",
"ITEM_LOG_FLAG":"2",
"ITEM_TIP":"",
"ITEM_ORDER_CODES":"",
"ITEM_CARD_FORMAT":"",
"ITEM_LIST_STYLE":"",
"ITEM_VALIDATE":"",
"ITEM_MEMO":"流程实例编码",
"ITEM_VALIDATE_HINT":"",
"ITEM_NOTNULL":"2",
"ITEM_LIST_ORDER":"130",
"ITEM_FIELD_TYPE":"STR",
"ITEM_SEARCH_FLAG":"2",
"ITEM_INPUT_MODE":"1",
"ITEM_USER_FLAG":"0",
"_ROWNUM_":"17",
"ITEM_LIST_WIDTH":"0",
"ITEM_EXPTENDS":"",
"ITEM_NAME":"流程实例编码",
"ITEM_NOTNULL_SCRIPT":"",
"ITEM_CARD_ORDER":"0",
"ITEM_CARD_COLS":"1",
"ITEM_SUM_FLAG":"0",
"ITEM_TYPE":"1",
"S_MTIME":"2013-12-25 14:30:15:170",
"ITEM_LIST_FORMAT":"",
"ITEM_ID":"0_M_ODaw1cXH3E0lny_Nes",
"ITEM_LIST_FLAG":"3",
"ITEM_CARD_DISABLE":"2",
"ITEM_CARD_ROWS":"1",
"ITEM_READONLY":"2",
"ITEM_HIDDEN_SCRIPT":"",
"ITEM_LIST_EDIT":"2",
"DICT_ID":"",
"ITEM_READONLY_SCRIPT":"",
"ITEM_FIELD_LENGTH":"40",
"S_FLAG":"1",
"ITEM_CARD_LINK":"",
"ITEM_HIDDEN":"1",
"ITEM_CARD_STYLE":"",
"ITEM_UNIQUE_GROUP":"0",
"_PK_":"0_M_ODaw1cXH3E0lny_Nes",
"ITEM_LIST_ALIGN":"1",
"ITEM_INPUT_TYPE":"1",
"ITEM_LIST_LINK":"",
"ITEM_INPUT_FLAG":"2",
"ITEM_CODE":"S_WF_INST",
"ITEM_MOBILE_TYPE":"3",
"ITEM_LABEL_HIDDEN":"0",
"ITEM_INPUT_DEFAULT":"",
"ITEM_INPUT_CONFIG":""
},
{
"SERV_ID":"OA_ZH_ASSAF_AS",
"ITEM_CARD_WIDTH":"0",
"ITEM_LOG_FLAG":"2",
"ITEM_TIP":"",
"ITEM_ORDER_CODES":"",
"ITEM_CARD_FORMAT":"",
"ITEM_LIST_STYLE":"",
"ITEM_VALIDATE":"",
"ITEM_MEMO":"当前处理用户",
"ITEM_VALIDATE_HINT":"",
"ITEM_NOTNULL":"2",
"ITEM_LIST_ORDER":"140",
"ITEM_FIELD_TYPE":"STR",
"ITEM_SEARCH_FLAG":"2",
"ITEM_INPUT_MODE":"1",
"ITEM_USER_FLAG":"0",
"_ROWNUM_":"18",
"ITEM_LIST_WIDTH":"0",
"ITEM_EXPTENDS":"",
"ITEM_NAME":"当前处理用户",
"ITEM_NOTNULL_SCRIPT":"",
"ITEM_CARD_ORDER":"0",
"ITEM_CARD_COLS":"1",
"ITEM_SUM_FLAG":"0",
"ITEM_TYPE":"1",
"S_MTIME":"2013-12-25 14:30:07:028",
"ITEM_LIST_FORMAT":"",
"ITEM_ID":"1M-JCCcf52grZBInCD7ULl",
"ITEM_LIST_FLAG":"3",
"ITEM_CARD_DISABLE":"2",
"ITEM_CARD_ROWS":"1",
"ITEM_READONLY":"2",
"ITEM_HIDDEN_SCRIPT":"",
"ITEM_LIST_EDIT":"2",
"DICT_ID":"",
"ITEM_READONLY_SCRIPT":"",
"ITEM_FIELD_LENGTH":"40",
"S_FLAG":"1",
"ITEM_CARD_LINK":"",
"ITEM_HIDDEN":"1",
"ITEM_CARD_STYLE":"",
"ITEM_UNIQUE_GROUP":"0",
"_PK_":"1M-JCCcf52grZBInCD7ULl",
"ITEM_LIST_ALIGN":"1",
"ITEM_INPUT_TYPE":"1",
"ITEM_LIST_LINK":"",
"ITEM_INPUT_FLAG":"2",
"ITEM_CODE":"S_WF_USER",
"ITEM_MOBILE_TYPE":"3",
"ITEM_LABEL_HIDDEN":"0",
"ITEM_INPUT_DEFAULT":"",
"ITEM_INPUT_CONFIG":""
},
{
"SERV_ID":"OA_ZH_ASSAF_AS",
"ITEM_CARD_WIDTH":"0",
"ITEM_LOG_FLAG":"2",
"ITEM_TIP":"",
"ITEM_ORDER_CODES":"",
"ITEM_CARD_FORMAT":"",
"ITEM_LIST_STYLE":"",
"ITEM_VALIDATE":"",
"ITEM_MEMO":"当前处理节点",
"ITEM_VALIDATE_HINT":"",
"ITEM_NOTNULL":"2",
"ITEM_LIST_ORDER":"150",
"ITEM_FIELD_TYPE":"STR",
"ITEM_SEARCH_FLAG":"2",
"ITEM_INPUT_MODE":"1",
"ITEM_USER_FLAG":"0",
"_ROWNUM_":"19",
"ITEM_LIST_WIDTH":"0",
"ITEM_EXPTENDS":"",
"ITEM_NAME":"当前处理节点",
"ITEM_NOTNULL_SCRIPT":"",
"ITEM_CARD_ORDER":"0",
"ITEM_CARD_COLS":"1",
"ITEM_SUM_FLAG":"0",
"ITEM_TYPE":"1",
"S_MTIME":"2013-12-25 14:29:53:735",
"ITEM_LIST_FORMAT":"",
"ITEM_ID":"1B2FJl-4JbCVYRz6cGIbch",
"ITEM_LIST_FLAG":"3",
"ITEM_CARD_DISABLE":"2",
"ITEM_CARD_ROWS":"1",
"ITEM_READONLY":"2",
"ITEM_HIDDEN_SCRIPT":"",
"ITEM_LIST_EDIT":"2",
"DICT_ID":"",
"ITEM_READONLY_SCRIPT":"",
"ITEM_FIELD_LENGTH":"40",
"S_FLAG":"1",
"ITEM_CARD_LINK":"",
"ITEM_HIDDEN":"1",
"ITEM_CARD_STYLE":"",
"ITEM_UNIQUE_GROUP":"0",
"_PK_":"1B2FJl-4JbCVYRz6cGIbch",
"ITEM_LIST_ALIGN":"1",
"ITEM_INPUT_TYPE":"1",
"ITEM_LIST_LINK":"",
"ITEM_INPUT_FLAG":"2",
"ITEM_CODE":"S_WF_NODE",
"ITEM_MOBILE_TYPE":"3",
"ITEM_LABEL_HIDDEN":"0",
"ITEM_INPUT_DEFAULT":"",
"ITEM_INPUT_CONFIG":""
},
{
"SERV_ID":"OA_ZH_ASSAF_AS",
"ITEM_CARD_WIDTH":"0",
"ITEM_LOG_FLAG":"2",
"ITEM_TIP":"",
"ITEM_ORDER_CODES":"",
"ITEM_CARD_FORMAT":"",
"ITEM_LIST_STYLE":"",
"ITEM_VALIDATE":"",
"ITEM_MEMO":"当前流程状态",
"ITEM_VALIDATE_HINT":"",
"ITEM_NOTNULL":"2",
"ITEM_LIST_ORDER":"160",
"ITEM_FIELD_TYPE":"NUM",
"ITEM_SEARCH_FLAG":"1",
"ITEM_INPUT_MODE":"1",
"ITEM_USER_FLAG":"0",
"_ROWNUM_":"20",
"ITEM_LIST_WIDTH":"0",
"ITEM_EXPTENDS":"",
"ITEM_NAME":"办理状态",
"ITEM_NOTNULL_SCRIPT":"",
"ITEM_CARD_ORDER":"0",
"ITEM_CARD_COLS":"1",
"ITEM_SUM_FLAG":"0",
"ITEM_TYPE":"1",
"S_MTIME":"2013-12-23 17:34:50:581",
"ITEM_LIST_FORMAT":"",
"ITEM_ID":"2LG-Pevvp3n9EkmssX5VVD",
"ITEM_LIST_FLAG":"3",
"ITEM_CARD_DISABLE":"2",
"ITEM_CARD_ROWS":"1",
"ITEM_READONLY":"2",
"ITEM_HIDDEN_SCRIPT":"",
"ITEM_LIST_EDIT":"2",
"DICT_ID":"OA_GW_STATE",
"ITEM_READONLY_SCRIPT":"",
"ITEM_FIELD_LENGTH":"4",
"S_FLAG":"1",
"ITEM_CARD_LINK":"",
"ITEM_HIDDEN":"1",
"ITEM_CARD_STYLE":"",
"ITEM_UNIQUE_GROUP":"0",
"_PK_":"2LG-Pevvp3n9EkmssX5VVD",
"ITEM_LIST_ALIGN":"1",
"ITEM_INPUT_TYPE":"2",
"ITEM_LIST_LINK":"",
"ITEM_INPUT_FLAG":"2",
"ITEM_CODE":"S_WF_STATE",
"ITEM_MOBILE_TYPE":"3",
"ITEM_LABEL_HIDDEN":"0",
"ITEM_INPUT_DEFAULT":"0",
"ITEM_INPUT_CONFIG":"OA_GW_STATE"
},
{
"SERV_ID":"OA_ZH_ASSAF_AS",
"ITEM_CARD_WIDTH":"0",
"ITEM_LOG_FLAG":"2",
"ITEM_TIP":"",
"ITEM_ORDER_CODES":"",
"ITEM_CARD_FORMAT":"",
"ITEM_LIST_STYLE":"",
"ITEM_VALIDATE":"",
"ITEM_MEMO":"修改时间",
"ITEM_VALIDATE_HINT":"",
"ITEM_NOTNULL":"2",
"ITEM_LIST_ORDER":"170",
"ITEM_FIELD_TYPE":"STR",
"ITEM_SEARCH_FLAG":"2",
"ITEM_INPUT_MODE":"1",
"ITEM_USER_FLAG":"0",
"_ROWNUM_":"21",
"ITEM_LIST_WIDTH":"0",
"ITEM_EXPTENDS":"",
"ITEM_NAME":"修改时间",
"ITEM_NOTNULL_SCRIPT":"",
"ITEM_CARD_ORDER":"0",
"ITEM_CARD_COLS":"1",
"ITEM_SUM_FLAG":"0",
"ITEM_TYPE":"1",
"S_MTIME":"2013-04-18 15:08:37:973",
"ITEM_LIST_FORMAT":"",
"ITEM_ID":"0465GHuYRamoFBD-jQbufH",
"ITEM_LIST_FLAG":"2",
"ITEM_CARD_DISABLE":"2",
"ITEM_CARD_ROWS":"1",
"ITEM_READONLY":"2",
"ITEM_HIDDEN_SCRIPT":"",
"ITEM_LIST_EDIT":"2",
"DICT_ID":"",
"ITEM_READONLY_SCRIPT":"",
"ITEM_FIELD_LENGTH":"23",
"S_FLAG":"1",
"ITEM_CARD_LINK":"",
"ITEM_HIDDEN":"1",
"ITEM_CARD_STYLE":"",
"ITEM_UNIQUE_GROUP":"0",
"_PK_":"0465GHuYRamoFBD-jQbufH",
"ITEM_LIST_ALIGN":"1",
"ITEM_INPUT_TYPE":"1",
"ITEM_LIST_LINK":"",
"ITEM_INPUT_FLAG":"2",
"ITEM_CODE":"S_MTIME",
"ITEM_MOBILE_TYPE":"3",
"ITEM_LABEL_HIDDEN":"0",
"ITEM_INPUT_DEFAULT":"@DATETIME_TS@",
"ITEM_INPUT_CONFIG":""
},
{
"SERV_ID":"OA_ZH_ASSAF_AS",
"ITEM_CARD_WIDTH":"0",
"ITEM_LOG_FLAG":"2",
"ITEM_TIP":"",
"ITEM_ORDER_CODES":"",
"ITEM_CARD_FORMAT":"",
"ITEM_LIST_STYLE":"",
"ITEM_VALIDATE":"",
"ITEM_MEMO":"处室",
"ITEM_VALIDATE_HINT":"",
"ITEM_NOTNULL":"2",
"ITEM_LIST_ORDER":"180",
"ITEM_FIELD_TYPE":"STR",
"ITEM_SEARCH_FLAG":"2",
"ITEM_INPUT_MODE":"1",
"ITEM_USER_FLAG":"0",
"_ROWNUM_":"22",
"ITEM_LIST_WIDTH":"0",
"ITEM_EXPTENDS":"",
"ITEM_NAME":"处室",
"ITEM_NOTNULL_SCRIPT":"",
"ITEM_CARD_ORDER":"0",
"ITEM_CARD_COLS":"1",
"ITEM_SUM_FLAG":"0",
"ITEM_TYPE":"1",
"S_MTIME":"2013-04-18 15:08:38:041",
"ITEM_LIST_FORMAT":"",
"ITEM_ID":"0Eb1KFl0t21F8SbsrKXWpy",
"ITEM_LIST_FLAG":"2",
"ITEM_CARD_DISABLE":"2",
"ITEM_CARD_ROWS":"1",
"ITEM_READONLY":"2",
"ITEM_HIDDEN_SCRIPT":"",
"ITEM_LIST_EDIT":"2",
"DICT_ID":"",
"ITEM_READONLY_SCRIPT":"",
"ITEM_FIELD_LENGTH":"40",
"S_FLAG":"1",
"ITEM_CARD_LINK":"",
"ITEM_HIDDEN":"1",
"ITEM_CARD_STYLE":"",
"ITEM_UNIQUE_GROUP":"0",
"_PK_":"0Eb1KFl0t21F8SbsrKXWpy",
"ITEM_LIST_ALIGN":"1",
"ITEM_INPUT_TYPE":"1",
"ITEM_LIST_LINK":"",
"ITEM_INPUT_FLAG":"2",
"ITEM_CODE":"S_DEPT",
"ITEM_MOBILE_TYPE":"3",
"ITEM_LABEL_HIDDEN":"0",
"ITEM_INPUT_DEFAULT":"@DEPT_CODE@",
"ITEM_INPUT_CONFIG":""
},
{
"SERV_ID":"OA_ZH_ASSAF_AS",
"ITEM_CARD_WIDTH":"0",
"ITEM_LOG_FLAG":"2",
"ITEM_TIP":"",
"ITEM_ORDER_CODES":"",
"ITEM_CARD_FORMAT":"",
"ITEM_LIST_STYLE":"",
"ITEM_VALIDATE":"",
"ITEM_MEMO":"有效部门",
"ITEM_VALIDATE_HINT":"",
"ITEM_NOTNULL":"2",
"ITEM_LIST_ORDER":"190",
"ITEM_FIELD_TYPE":"STR",
"ITEM_SEARCH_FLAG":"2",
"ITEM_INPUT_MODE":"3",
"ITEM_USER_FLAG":"0",
"_ROWNUM_":"23",
"ITEM_LIST_WIDTH":"0",
"ITEM_EXPTENDS":"",
"ITEM_NAME":"有效部门",
"ITEM_NOTNULL_SCRIPT":"",
"ITEM_CARD_ORDER":"0",
"ITEM_CARD_COLS":"1",
"ITEM_SUM_FLAG":"0",
"ITEM_TYPE":"1",
"S_MTIME":"2013-12-26 09:40:10:022",
"ITEM_LIST_FORMAT":"",
"ITEM_ID":"1FyFDP9gHpxbZHRGROMLL14f",
"ITEM_LIST_FLAG":"2",
"ITEM_CARD_DISABLE":"2",
"ITEM_CARD_ROWS":"1",
"ITEM_READONLY":"2",
"ITEM_HIDDEN_SCRIPT":"",
"ITEM_LIST_EDIT":"2",
"DICT_ID":"SY_ORG_DEPT_ALL",
"ITEM_READONLY_SCRIPT":"",
"ITEM_FIELD_LENGTH":"40",
"S_FLAG":"1",
"ITEM_CARD_LINK":"",
"ITEM_HIDDEN":"1",
"ITEM_CARD_STYLE":"",
"ITEM_UNIQUE_GROUP":"0",
"_PK_":"1FyFDP9gHpxbZHRGROMLL14f",
"ITEM_LIST_ALIGN":"1",
"ITEM_INPUT_TYPE":"1",
"ITEM_LIST_LINK":"",
"ITEM_INPUT_FLAG":"2",
"ITEM_CODE":"S_TDEPT",
"ITEM_MOBILE_TYPE":"3",
"ITEM_LABEL_HIDDEN":"0",
"ITEM_INPUT_DEFAULT":"@TDEPT_CODE@",
"ITEM_INPUT_CONFIG":"SY_ORG_DEPT_ALL"
},
{
"SERV_ID":"OA_ZH_ASSAF_AS",
"ITEM_CARD_WIDTH":"0",
"ITEM_LOG_FLAG":"1",
"ITEM_TIP":"",
"ITEM_ORDER_CODES":"",
"ITEM_CARD_FORMAT":"",
"ITEM_LIST_STYLE":"",
"ITEM_VALIDATE":"",
"ITEM_MEMO":"",
"ITEM_VALIDATE_HINT":"",
"ITEM_NOTNULL":"2",
"ITEM_LIST_ORDER":"220",
"ITEM_FIELD_TYPE":"STR",
"ITEM_SEARCH_FLAG":"2",
"ITEM_INPUT_MODE":"1",
"ITEM_USER_FLAG":"2",
"_ROWNUM_":"24",
"ITEM_LIST_WIDTH":"0",
"ITEM_EXPTENDS":"",
"ITEM_NAME":"正文",
"ITEM_NOTNULL_SCRIPT":"",
"ITEM_CARD_ORDER":"0",
"ITEM_CARD_COLS":"2",
"ITEM_SUM_FLAG":"2",
"ITEM_TYPE":"3",
"S_MTIME":"2013-12-26 16:31:28:524",
"ITEM_LIST_FORMAT":"",
"ITEM_ID":"0fDgbhQEp7M9hMrKAq4JJDU",
"ITEM_LIST_FLAG":"2",
"ITEM_CARD_DISABLE":"2",
"ITEM_CARD_ROWS":"1",
"ITEM_READONLY":"2",
"ITEM_HIDDEN_SCRIPT":"",
"ITEM_LIST_EDIT":"2",
"DICT_ID":"",
"ITEM_READONLY_SCRIPT":"",
"ITEM_FIELD_LENGTH":"40",
"S_FLAG":"1",
"ITEM_CARD_LINK":"",
"ITEM_HIDDEN":"2",
"ITEM_CARD_STYLE":"",
"ITEM_UNIQUE_GROUP":"0",
"_PK_":"0fDgbhQEp7M9hMrKAq4JJDU",
"ITEM_LIST_ALIGN":"0",
"ITEM_INPUT_TYPE":"14",
"ITEM_LIST_LINK":"",
"ITEM_INPUT_FLAG":"2",
"ITEM_CODE":"ZHENGWEN",
"ITEM_MOBILE_TYPE":"3",
"ITEM_LABEL_HIDDEN":"2",
"ITEM_INPUT_DEFAULT":"",
"ITEM_INPUT_CONFIG":"{'VALUE':'33','TYPES':'*.*','UPLOAD_BTN_NAME':'上传文件'}"
},
{
"SERV_ID":"OA_ZH_ASSAF_AS",
"ITEM_CARD_WIDTH":"0",
"ITEM_LOG_FLAG":"2",
"ITEM_TIP":"",
"ITEM_ORDER_CODES":"",
"ITEM_CARD_FORMAT":"",
"ITEM_LIST_STYLE":"",
"ITEM_VALIDATE":"",
"ITEM_MEMO":"模版代码",
"ITEM_VALIDATE_HINT":"",
"ITEM_NOTNULL":"2",
"ITEM_LIST_ORDER":"220",
"ITEM_FIELD_TYPE":"STR",
"ITEM_SEARCH_FLAG":"2",
"ITEM_INPUT_MODE":"1",
"ITEM_USER_FLAG":"0",
"_ROWNUM_":"25",
"ITEM_LIST_WIDTH":"0",
"ITEM_EXPTENDS":"",
"ITEM_NAME":"模版代码",
"ITEM_NOTNULL_SCRIPT":"",
"ITEM_CARD_ORDER":"0",
"ITEM_CARD_COLS":"1",
"ITEM_SUM_FLAG":"0",
"ITEM_TYPE":"1",
"S_MTIME":"2013-12-20 10:14:00:479",
"ITEM_LIST_FORMAT":"",
"ITEM_ID":"3hfMYN12ddorGwSSe3zZd1a",
"ITEM_LIST_FLAG":"2",
"ITEM_CARD_DISABLE":"2",
"ITEM_CARD_ROWS":"1",
"ITEM_READONLY":"2",
"ITEM_HIDDEN_SCRIPT":"",
"ITEM_LIST_EDIT":"2",
"DICT_ID":"",
"ITEM_READONLY_SCRIPT":"",
"ITEM_FIELD_LENGTH":"40",
"S_FLAG":"1",
"ITEM_CARD_LINK":"",
"ITEM_HIDDEN":"1",
"ITEM_CARD_STYLE":"",
"ITEM_UNIQUE_GROUP":"0",
"_PK_":"3hfMYN12ddorGwSSe3zZd1a",
"ITEM_LIST_ALIGN":"1",
"ITEM_INPUT_TYPE":"1",
"ITEM_LIST_LINK":"",
"ITEM_INPUT_FLAG":"2",
"ITEM_CODE":"TMPL_CODE",
"ITEM_MOBILE_TYPE":"3",
"ITEM_LABEL_HIDDEN":"0",
"ITEM_INPUT_DEFAULT":"OA_ZH_ASSAF_AS",
"ITEM_INPUT_CONFIG":""
},
{
"SERV_ID":"OA_ZH_ASSAF_AS",
"ITEM_CARD_WIDTH":"0",
"ITEM_LOG_FLAG":"2",
"ITEM_TIP":"",
"ITEM_ORDER_CODES":"",
"ITEM_CARD_FORMAT":"",
"ITEM_LIST_STYLE":"",
"ITEM_VALIDATE":"",
"ITEM_MEMO":"模版类型",
"ITEM_VALIDATE_HINT":"",
"ITEM_NOTNULL":"2",
"ITEM_LIST_ORDER":"230",
"ITEM_FIELD_TYPE":"STR",
"ITEM_SEARCH_FLAG":"2",
"ITEM_INPUT_MODE":"1",
"ITEM_USER_FLAG":"0",
"_ROWNUM_":"26",
"ITEM_LIST_WIDTH":"0",
"ITEM_EXPTENDS":"",
"ITEM_NAME":"模版类型",
"ITEM_NOTNULL_SCRIPT":"",
"ITEM_CARD_ORDER":"0",
"ITEM_CARD_COLS":"1",
"ITEM_SUM_FLAG":"0",
"ITEM_TYPE":"1",
"S_MTIME":"2013-09-24 17:33:01:682",
"ITEM_LIST_FORMAT":"",
"ITEM_ID":"1jj5yNDuleU8Dar3IVTMvx6r",
"ITEM_LIST_FLAG":"2",
"ITEM_CARD_DISABLE":"2",
"ITEM_CARD_ROWS":"1",
"ITEM_READONLY":"2",
"ITEM_HIDDEN_SCRIPT":"",
"ITEM_LIST_EDIT":"2",
"DICT_ID":"",
"ITEM_READONLY_SCRIPT":"",
"ITEM_FIELD_LENGTH":"40",
"S_FLAG":"1",
"ITEM_CARD_LINK":"",
"ITEM_HIDDEN":"1",
"ITEM_CARD_STYLE":"",
"ITEM_UNIQUE_GROUP":"0",
"_PK_":"1jj5yNDuleU8Dar3IVTMvx6r",
"ITEM_LIST_ALIGN":"1",
"ITEM_INPUT_TYPE":"1",
"ITEM_LIST_LINK":"",
"ITEM_INPUT_FLAG":"2",
"ITEM_CODE":"TMPL_TYPE_CODE",
"ITEM_MOBILE_TYPE":"3",
"ITEM_LABEL_HIDDEN":"0",
"ITEM_INPUT_DEFAULT":"OA_ZH_ASSAF_AS",
"ITEM_INPUT_CONFIG":""
},
{
"SERV_ID":"OA_ZH_ASSAF_AS",
"ITEM_CARD_WIDTH":"0",
"ITEM_LOG_FLAG":"1",
"ITEM_TIP":"",
"ITEM_ORDER_CODES":"",
"ITEM_CARD_FORMAT":"",
"ITEM_LIST_STYLE":"",
"ITEM_VALIDATE":"",
"ITEM_MEMO":"",
"ITEM_VALIDATE_HINT":"",
"ITEM_NOTNULL":"2",
"ITEM_LIST_ORDER":"230",
"ITEM_FIELD_TYPE":"STR",
"ITEM_SEARCH_FLAG":"2",
"ITEM_INPUT_MODE":"1",
"ITEM_USER_FLAG":"2",
"_ROWNUM_":"27",
"ITEM_LIST_WIDTH":"0",
"ITEM_EXPTENDS":"",
"ITEM_NAME":"附件",
"ITEM_NOTNULL_SCRIPT":"",
"ITEM_CARD_ORDER":"0",
"ITEM_CARD_COLS":"2",
"ITEM_SUM_FLAG":"2",
"ITEM_TYPE":"3",
"S_MTIME":"2013-12-26 16:28:34:770",
"ITEM_LIST_FORMAT":"",
"ITEM_ID":"2kcGuj1qV6trzghkSQ4VUs",
"ITEM_LIST_FLAG":"2",
"ITEM_CARD_DISABLE":"2",
"ITEM_CARD_ROWS":"1",
"ITEM_READONLY":"2",
"ITEM_HIDDEN_SCRIPT":"",
"ITEM_LIST_EDIT":"2",
"DICT_ID":"",
"ITEM_READONLY_SCRIPT":"",
"ITEM_FIELD_LENGTH":"40",
"S_FLAG":"1",
"ITEM_CARD_LINK":"",
"ITEM_HIDDEN":"2",
"ITEM_CARD_STYLE":"",
"ITEM_UNIQUE_GROUP":"0",
"_PK_":"2kcGuj1qV6trzghkSQ4VUs",
"ITEM_LIST_ALIGN":"0",
"ITEM_INPUT_TYPE":"14",
"ITEM_LIST_LINK":"",
"ITEM_INPUT_FLAG":"2",
"ITEM_CODE":"FUJIAN",
"ITEM_MOBILE_TYPE":"3",
"ITEM_LABEL_HIDDEN":"2",
"ITEM_INPUT_DEFAULT":"",
"ITEM_INPUT_CONFIG":"{\"VALUE\":\"37\",\"TYPES\":\"*.*\",\"UPLOAD_BTN_NAME\":\"上传文件\"}"
},
{
"SERV_ID":"OA_ZH_ASSAF_AS",
"ITEM_CARD_WIDTH":"0",
"ITEM_LOG_FLAG":"1",
"ITEM_TIP":"",
"ITEM_ORDER_CODES":"",
"ITEM_CARD_FORMAT":"",
"ITEM_LIST_STYLE":"",
"ITEM_VALIDATE":"",
"ITEM_MEMO":"",
"ITEM_VALIDATE_HINT":"",
"ITEM_NOTNULL":"2",
"ITEM_LIST_ORDER":"240",
"ITEM_FIELD_TYPE":"STR",
"ITEM_SEARCH_FLAG":"2",
"ITEM_INPUT_MODE":"1",
"ITEM_USER_FLAG":"2",
"_ROWNUM_":"28",
"ITEM_LIST_WIDTH":"0",
"ITEM_EXPTENDS":"",
"ITEM_NAME":"相关文件",
"ITEM_NOTNULL_SCRIPT":"",
"ITEM_CARD_ORDER":"0",
"ITEM_CARD_COLS":"2",
"ITEM_SUM_FLAG":"2",
"ITEM_TYPE":"3",
"S_MTIME":"2013-10-12 13:57:51:977",
"ITEM_LIST_FORMAT":"",
"ITEM_ID":"3B8qZERnZbB99TD8OMSr9eL",
"ITEM_LIST_FLAG":"2",
"ITEM_CARD_DISABLE":"2",
"ITEM_CARD_ROWS":"1",
"ITEM_READONLY":"2",
"ITEM_HIDDEN_SCRIPT":"",
"ITEM_LIST_EDIT":"2",
"DICT_ID":"",
"ITEM_READONLY_SCRIPT":"",
"ITEM_FIELD_LENGTH":"40",
"S_FLAG":"1",
"ITEM_CARD_LINK":"",
"ITEM_HIDDEN":"2",
"ITEM_CARD_STYLE":"",
"ITEM_UNIQUE_GROUP":"0",
"_PK_":"3B8qZERnZbB99TD8OMSr9eL",
"ITEM_LIST_ALIGN":"0",
"ITEM_INPUT_TYPE":"16",
"ITEM_LIST_LINK":"",
"ITEM_INPUT_FLAG":"2",
"ITEM_CODE":"AS_XGWJ",
"ITEM_MOBILE_TYPE":"3",
"ITEM_LABEL_HIDDEN":"2",
"ITEM_INPUT_DEFAULT":"",
"ITEM_INPUT_CONFIG":"[{'servId':'OA_SY_COMM_ENTITY_QUERY','SOURCE':'ENTITY_ID,ENTITY_CODE,TITLE,SERV_ID,S_ATIME,DATA_ID','servName':'综合查询','SHOWITEM':'TITLE','TARGET_SERV_ID_ITEM':'SERV_ID','TARGET_ID_ITEM':'DATA_ID','HIDE':'ENTITY_ID,DATA_ID,SERV_ID','DATAFLAG':'false'}]"
},
{
"SERV_ID":"OA_ZH_ASSAF_AS",
"ITEM_CARD_WIDTH":"0",
"ITEM_LOG_FLAG":"2",
"ITEM_TIP":"",
"ITEM_ORDER_CODES":"",
"ITEM_CARD_FORMAT":"",
"ITEM_LIST_STYLE":"",
"ITEM_VALIDATE":"",
"ITEM_MEMO":"",
"ITEM_VALIDATE_HINT":"",
"ITEM_NOTNULL":"2",
"ITEM_LIST_ORDER":"300",
"ITEM_FIELD_TYPE":"STR",
"ITEM_SEARCH_FLAG":"2",
"ITEM_INPUT_MODE":"1",
"ITEM_USER_FLAG":"2",
"_ROWNUM_":"29",
"ITEM_LIST_WIDTH":"0",
"ITEM_EXPTENDS":"",
"ITEM_NAME":"签批意见",
"ITEM_NOTNULL_SCRIPT":"",
"ITEM_CARD_ORDER":"0",
"ITEM_CARD_COLS":"1",
"ITEM_SUM_FLAG":"2",
"ITEM_TYPE":"3",
"S_MTIME":"2013-10-14 14:59:44:314",
"ITEM_LIST_FORMAT":"",
"ITEM_ID":"1LuczF9LFcn8pIY97ukghB",
"ITEM_LIST_FLAG":"2",
"ITEM_CARD_DISABLE":"2",
"ITEM_CARD_ROWS":"1",
"ITEM_READONLY":"2",
"ITEM_HIDDEN_SCRIPT":"",
"ITEM_LIST_EDIT":"2",
"DICT_ID":"",
"ITEM_READONLY_SCRIPT":"",
"ITEM_FIELD_LENGTH":"40",
"S_FLAG":"1",
"ITEM_CARD_LINK":"",
"ITEM_HIDDEN":"2",
"ITEM_CARD_STYLE":"",
"ITEM_UNIQUE_GROUP":"0",
"_PK_":"1LuczF9LFcn8pIY97ukghB",
"ITEM_LIST_ALIGN":"0",
"ITEM_INPUT_TYPE":"10",
"ITEM_LIST_LINK":"",
"ITEM_INPUT_FLAG":"2",
"ITEM_CODE":"MIND_FIELDSET",
"ITEM_MOBILE_TYPE":"3",
"ITEM_LABEL_HIDDEN":"2",
"ITEM_INPUT_DEFAULT":"",
"ITEM_INPUT_CONFIG":""
},
{
"SERV_ID":"OA_ZH_ASSAF_AS",
"ITEM_CARD_WIDTH":"0",
"ITEM_LOG_FLAG":"2",
"ITEM_TIP":"",
"ITEM_ORDER_CODES":"",
"ITEM_CARD_FORMAT":"",
"ITEM_LIST_STYLE":"",
"ITEM_VALIDATE":"",
"ITEM_MEMO":"",
"ITEM_VALIDATE_HINT":"",
"ITEM_NOTNULL":"2",
"ITEM_LIST_ORDER":"350",
"ITEM_FIELD_TYPE":"STR",
"ITEM_SEARCH_FLAG":"2",
"ITEM_INPUT_MODE":"1",
"ITEM_USER_FLAG":"2",
"_ROWNUM_":"30",
"ITEM_LIST_WIDTH":"0",
"ITEM_EXPTENDS":"",
"ITEM_NAME":"签批意见",
"ITEM_NOTNULL_SCRIPT":"",
"ITEM_CARD_ORDER":"0",
"ITEM_CARD_COLS":"1",
"ITEM_SUM_FLAG":"2",
"ITEM_TYPE":"3",
"S_MTIME":"2013-09-24 17:47:04:600",
"ITEM_LIST_FORMAT":"",
"ITEM_ID":"3V9oNqNSR4krrNmPLJjyXb",
"ITEM_LIST_FLAG":"2",
"ITEM_CARD_DISABLE":"2",
"ITEM_CARD_ROWS":"1",
"ITEM_READONLY":"2",
"ITEM_HIDDEN_SCRIPT":"",
"ITEM_LIST_EDIT":"2",
"DICT_ID":"",
"ITEM_READONLY_SCRIPT":"",
"ITEM_FIELD_LENGTH":"40",
"S_FLAG":"1",
"ITEM_CARD_LINK":"",
"ITEM_HIDDEN":"1",
"ITEM_CARD_STYLE":"",
"ITEM_UNIQUE_GROUP":"0",
"_PK_":"3V9oNqNSR4krrNmPLJjyXb",
"ITEM_LIST_ALIGN":"0",
"ITEM_INPUT_TYPE":"17",
"ITEM_LIST_LINK":"",
"ITEM_INPUT_FLAG":"2",
"ITEM_CODE":"MIND_ITEM",
"ITEM_MOBILE_TYPE":"3",
"ITEM_LABEL_HIDDEN":"2",
"ITEM_INPUT_DEFAULT":"",
"ITEM_INPUT_CONFIG":"{'MIND_LIST_ORDER':'TIME','MIND_LIST_EXPANDSION':'TRUE'}"
}
],
"SERV_CACHE_FLAG":"3",
"_PK_":"OA_ZH_ASSAF_AS",
"SERV_LIST_LOAD":"2",
"S_CMPY":"zhbx",
"SERV_DATA_CODE":"#GW_CODE#",
"SERV_DICT_CACHE":"AS_SERV_TYPES,AS_SERV-DNO,AS_SERV-DEV",
"SERV_CARD_TMPL_CODES":"",
"SY_SERV_WHERE":
[
{
"SERV_ID":"OA_ZH_ASSAF_AS",
"S_FLAG":"1",
"WHERE_ORDER":"1",
"_PK_":"37Fnp8UCkR2sWpo70odDUnq",
"WHERE_SERV_TYPE":"",
"S_MTIME":"2013-12-10 11:51:25:121",
"WHERE_NAME":"公司文件管理员",
"WHERE_ID":"37Fnp8UCkR2sWpo70odDUnq",
"_ROWNUM_":"0",
"WHERE_FLOW_FLAG":"4",
"WHERE_SCRIPT":"\"@ROLE_CODES@\".indexOf(\"'GWADMIN'\") >= 0",
"WHERE_CONTENT":""
},
{
"SERV_ID":"OA_ZH_ASSAF_AS",
"S_FLAG":"1",
"WHERE_ORDER":"11",
"_PK_":"0LyiN6nFM156boMv25mEbYN6k",
"WHERE_SERV_TYPE":"",
"S_MTIME":"2013-12-10 11:51:42:728",
"WHERE_NAME":"部门文件管理员",
"WHERE_ID":"0LyiN6nFM156boMv25mEbYN6k",
"_ROWNUM_":"1",
"WHERE_FLOW_FLAG":"1",
"WHERE_SCRIPT":"\"@ROLE_CODES@\".indexOf(\"'c18081953240a6d6013241b852a81038'\") >= 0",
"WHERE_CONTENT":""
},
{
"SERV_ID":"OA_ZH_ASSAF_AS",
"S_FLAG":"1",
"WHERE_ORDER":"30",
"_PK_":"2naB22e9lcEXuXE3It4SE9g",
"WHERE_SERV_TYPE":"",
"S_MTIME":"2013-12-10 11:52:07:962",
"WHERE_NAME":"其他员工查看本人",
"WHERE_ID":"2naB22e9lcEXuXE3It4SE9g",
"_ROWNUM_":"2",
"WHERE_FLOW_FLAG":"3",
"WHERE_SCRIPT":"1 == 1",
"WHERE_CONTENT":""
}
]
}