{
"SERV_TYPE":"1",
"SERV_FILE_PATH":"",
"SERV_SRC_ID":"",
"SY_SERV_WHERE":
[
],
"SERV_SQL_WHERE":"",
"S_MTIME":"2016-03-17 20:12:33:979",
"SERV_LOCK_FLAG":"2",
"SERV_CARD_TMPL_CODES":"",
"TABLE_VIEW":"SY_COMM_LINK",
"S_PUBLIC":"1",
"TABLE_ACTION":"SY_COMM_LINK",
"SERV_MOBILE_JS":"",
"SY_SERV_ITEM":
[
{
"ITEM_INPUT_MODE":"1",
"ITEM_CARD_FORMAT":"",
"S_MTIME":"2013-11-06 11:07:44:489",
"ITEM_VALIDATE_HINT":"",
"ITEM_USER_FLAG":"0",
"ITEM_NAME":"主键",
"ITEM_INPUT_TYPE":"1",
"ITEM_CARD_ROWS":"1",
"ITEM_LIST_ORDER":"0",
"ITEM_LIST_ALIGN":"1",
"ITEM_UNIQUE_GROUP":"0",
"ITEM_CARD_ORDER":"0",
"ITEM_FIELD_LENGTH":"40",
"S_FLAG":"1",
"ITEM_TIP":"",
"_PK_":"08iYyVn413ToiMlZy8QNhA",
"ITEM_ID":"08iYyVn413ToiMlZy8QNhA",
"ITEM_CODE":"LINK_ID",
"ITEM_READONLY":"2",
"ITEM_LIST_WIDTH":"0",
"ITEM_FIELD_TYPE":"STR",
"ITEM_READONLY_SCRIPT":"",
"ITEM_HIDDEN":"1",
"_ROWNUM_":"0",
"ITEM_CARD_WIDTH":"0",
"ITEM_LIST_LINK":"",
"ITEM_LIST_FLAG":"2",
"ITEM_CARD_DISABLE":"2",
"ITEM_INPUT_CONFIG":"",
"ITEM_INPUT_DEFAULT":"",
"ITEM_INPUT_FLAG":"2",
"ITEM_NOTNULL":"1",
"DICT_ID":"",
"ITEM_ORDER_CODES":"",
"ITEM_SUM_FLAG":"2",
"ITEM_LIST_EDIT":"2",
"ITEM_TYPE":"1",
"ITEM_MEMO":"主键",
"ITEM_LABEL_HIDDEN":"0",
"ITEM_LOG_FLAG":"2",
"ITEM_CARD_STYLE":"",
"ITEM_NOTNULL_SCRIPT":"",
"ITEM_SEARCH_FLAG":"2",
"SERV_ID":"SY_COMM_LINK",
"ITEM_LIST_FORMAT":"",
"ITEM_VALIDATE":"",
"ITEM_LIST_STYLE":"",
"ITEM_CARD_COLS":"1",
"ITEM_MOBILE_TYPE":"3",
"ITEM_CARD_LINK":"",
"ITEM_HIDDEN_SCRIPT":"",
"ITEM_EXPTENDS":""
},
{
"ITEM_INPUT_MODE":"1",
"ITEM_CARD_FORMAT":"",
"S_MTIME":"2013-11-06 11:07:44:489",
"ITEM_VALIDATE_HINT":"",
"ITEM_USER_FLAG":"0",
"ITEM_NAME":"链接名称",
"ITEM_INPUT_TYPE":"1",
"ITEM_CARD_ROWS":"1",
"ITEM_LIST_ORDER":"10",
"ITEM_LIST_ALIGN":"1",
"ITEM_UNIQUE_GROUP":"0",
"ITEM_CARD_ORDER":"0",
"ITEM_FIELD_LENGTH":"200",
"S_FLAG":"1",
"ITEM_TIP":"",
"_PK_":"2hnYL58XFeXVTCoyQ1Rsqm",
"ITEM_ID":"2hnYL58XFeXVTCoyQ1Rsqm",
"ITEM_CODE":"LINK_NAME",
"ITEM_READONLY":"2",
"ITEM_LIST_WIDTH":"0",
"ITEM_FIELD_TYPE":"STR",
"ITEM_READONLY_SCRIPT":"",
"ITEM_HIDDEN":"2",
"_ROWNUM_":"1",
"ITEM_CARD_WIDTH":"0",
"ITEM_LIST_LINK":"",
"ITEM_LIST_FLAG":"1",
"ITEM_CARD_DISABLE":"2",
"ITEM_INPUT_CONFIG":"",
"ITEM_INPUT_DEFAULT":"",
"ITEM_INPUT_FLAG":"2",
"ITEM_NOTNULL":"1",
"DICT_ID":"",
"ITEM_ORDER_CODES":"",
"ITEM_SUM_FLAG":"2",
"ITEM_LIST_EDIT":"2",
"ITEM_TYPE":"1",
"ITEM_MEMO":"链接名称",
"ITEM_LABEL_HIDDEN":"0",
"ITEM_LOG_FLAG":"2",
"ITEM_CARD_STYLE":"",
"ITEM_NOTNULL_SCRIPT":"",
"ITEM_SEARCH_FLAG":"1",
"SERV_ID":"SY_COMM_LINK",
"ITEM_LIST_FORMAT":"",
"ITEM_VALIDATE":"",
"ITEM_LIST_STYLE":"",
"ITEM_CARD_COLS":"2",
"ITEM_MOBILE_TYPE":"3",
"ITEM_CARD_LINK":"",
"ITEM_HIDDEN_SCRIPT":"",
"ITEM_EXPTENDS":""
},
{
"ITEM_INPUT_MODE":"1",
"ITEM_CARD_FORMAT":"",
"S_MTIME":"2016-03-15 22:03:12:540",
"ITEM_VALIDATE_HINT":"",
"ITEM_USER_FLAG":"0",
"ITEM_NAME":"链接地址",
"ITEM_INPUT_TYPE":"1",
"ITEM_CARD_ROWS":"1",
"ITEM_LIST_ORDER":"20",
"ITEM_LIST_ALIGN":"1",
"ITEM_UNIQUE_GROUP":"0",
"ITEM_CARD_ORDER":"0",
"ITEM_FIELD_LENGTH":"200",
"S_FLAG":"1",
"ITEM_TIP":"",
"_PK_":"2U9GAAOTRfjqbVD9Sy0phQ",
"ITEM_ID":"2U9GAAOTRfjqbVD9Sy0phQ",
"ITEM_CODE":"LINK_ADDRESS",
"ITEM_READONLY":"2",
"ITEM_LIST_WIDTH":"0",
"ITEM_FIELD_TYPE":"STR",
"ITEM_READONLY_SCRIPT":"",
"ITEM_HIDDEN":"2",
"_ROWNUM_":"2",
"ITEM_CARD_WIDTH":"0",
"ITEM_LIST_LINK":"window.open(\"#LINK_ADDRESS#\");",
"ITEM_LIST_FLAG":"1",
"ITEM_CARD_DISABLE":"2",
"ITEM_INPUT_CONFIG":"",
"ITEM_INPUT_DEFAULT":"",
"ITEM_INPUT_FLAG":"2",
"ITEM_NOTNULL":"1",
"DICT_ID":"",
"ITEM_ORDER_CODES":"",
"ITEM_SUM_FLAG":"2",
"ITEM_LIST_EDIT":"2",
"ITEM_TYPE":"1",
"ITEM_MEMO":"链接地址",
"ITEM_LABEL_HIDDEN":"0",
"ITEM_LOG_FLAG":"2",
"ITEM_CARD_STYLE":"",
"ITEM_NOTNULL_SCRIPT":"",
"ITEM_SEARCH_FLAG":"1",
"SERV_ID":"SY_COMM_LINK",
"ITEM_LIST_FORMAT":"",
"ITEM_VALIDATE":"",
"ITEM_LIST_STYLE":"",
"ITEM_CARD_COLS":"2",
"ITEM_MOBILE_TYPE":"3",
"ITEM_CARD_LINK":"",
"ITEM_HIDDEN_SCRIPT":"",
"ITEM_EXPTENDS":""
},
{
"ITEM_INPUT_MODE":"1",
"ITEM_CARD_FORMAT":"",
"S_MTIME":"2013-11-06 11:07:44:489",
"ITEM_VALIDATE_HINT":"",
"ITEM_USER_FLAG":"0",
"ITEM_NAME":"链接说明",
"ITEM_INPUT_TYPE":"5",
"ITEM_CARD_ROWS":"1",
"ITEM_LIST_ORDER":"30",
"ITEM_LIST_ALIGN":"1",
"ITEM_UNIQUE_GROUP":"0",
"ITEM_CARD_ORDER":"0",
"ITEM_FIELD_LENGTH":"2000",
"S_FLAG":"1",
"ITEM_TIP":"",
"_PK_":"0e_7nEMfF9FbFKTH7nbSIH",
"ITEM_ID":"0e_7nEMfF9FbFKTH7nbSIH",
"ITEM_CODE":"LINK_MEMO",
"ITEM_READONLY":"2",
"ITEM_LIST_WIDTH":"0",
"ITEM_FIELD_TYPE":"STR",
"ITEM_READONLY_SCRIPT":"",
"ITEM_HIDDEN":"2",
"_ROWNUM_":"3",
"ITEM_CARD_WIDTH":"0",
"ITEM_LIST_LINK":"",
"ITEM_LIST_FLAG":"2",
"ITEM_CARD_DISABLE":"2",
"ITEM_INPUT_CONFIG":"",
"ITEM_INPUT_DEFAULT":"",
"ITEM_INPUT_FLAG":"2",
"ITEM_NOTNULL":"2",
"DICT_ID":"",
"ITEM_ORDER_CODES":"",
"ITEM_SUM_FLAG":"2",
"ITEM_LIST_EDIT":"2",
"ITEM_TYPE":"1",
"ITEM_MEMO":"链接说明",
"ITEM_LABEL_HIDDEN":"0",
"ITEM_LOG_FLAG":"2",
"ITEM_CARD_STYLE":"",
"ITEM_NOTNULL_SCRIPT":"",
"ITEM_SEARCH_FLAG":"2",
"SERV_ID":"SY_COMM_LINK",
"ITEM_LIST_FORMAT":"",
"ITEM_VALIDATE":"",
"ITEM_LIST_STYLE":"",
"ITEM_CARD_COLS":"2",
"ITEM_MOBILE_TYPE":"3",
"ITEM_CARD_LINK":"",
"ITEM_HIDDEN_SCRIPT":"",
"ITEM_EXPTENDS":""
},
{
"ITEM_INPUT_MODE":"1",
"ITEM_CARD_FORMAT":"",
"S_MTIME":"2013-11-06 11:07:44:489",
"ITEM_VALIDATE_HINT":"",
"ITEM_USER_FLAG":"0",
"ITEM_NAME":"排序",
"ITEM_INPUT_TYPE":"1",
"ITEM_CARD_ROWS":"1",
"ITEM_LIST_ORDER":"40",
"ITEM_LIST_ALIGN":"1",
"ITEM_UNIQUE_GROUP":"0",
"ITEM_CARD_ORDER":"0",
"ITEM_FIELD_LENGTH":"4",
"S_FLAG":"1",
"ITEM_TIP":"",
"_PK_":"3siAPpxStewahlRrTv8awz",
"ITEM_ID":"3siAPpxStewahlRrTv8awz",
"ITEM_CODE":"LINK_SORT",
"ITEM_READONLY":"2",
"ITEM_LIST_WIDTH":"0",
"ITEM_FIELD_TYPE":"NUM",
"ITEM_READONLY_SCRIPT":"",
"ITEM_HIDDEN":"2",
"_ROWNUM_":"4",
"ITEM_CARD_WIDTH":"0",
"ITEM_LIST_LINK":"",
"ITEM_LIST_FLAG":"1",
"ITEM_CARD_DISABLE":"2",
"ITEM_INPUT_CONFIG":"",
"ITEM_INPUT_DEFAULT":"0",
"ITEM_INPUT_FLAG":"2",
"ITEM_NOTNULL":"2",
"DICT_ID":"",
"ITEM_ORDER_CODES":"",
"ITEM_SUM_FLAG":"2",
"ITEM_LIST_EDIT":"2",
"ITEM_TYPE":"1",
"ITEM_MEMO":"排序",
"ITEM_LABEL_HIDDEN":"0",
"ITEM_LOG_FLAG":"2",
"ITEM_CARD_STYLE":"",
"ITEM_NOTNULL_SCRIPT":"",
"ITEM_SEARCH_FLAG":"1",
"SERV_ID":"SY_COMM_LINK",
"ITEM_LIST_FORMAT":"",
"ITEM_VALIDATE":"",
"ITEM_LIST_STYLE":"",
"ITEM_CARD_COLS":"1",
"ITEM_MOBILE_TYPE":"3",
"ITEM_CARD_LINK":"",
"ITEM_HIDDEN_SCRIPT":"",
"ITEM_EXPTENDS":""
},
{
"ITEM_INPUT_MODE":"1",
"ITEM_CARD_FORMAT":"",
"S_MTIME":"2013-11-06 11:07:44:489",
"ITEM_VALIDATE_HINT":"",
"ITEM_USER_FLAG":"0",
"ITEM_NAME":"添加者",
"ITEM_INPUT_TYPE":"1",
"ITEM_CARD_ROWS":"1",
"ITEM_LIST_ORDER":"50",
"ITEM_LIST_ALIGN":"1",
"ITEM_UNIQUE_GROUP":"0",
"ITEM_CARD_ORDER":"0",
"ITEM_FIELD_LENGTH":"40",
"S_FLAG":"1",
"ITEM_TIP":"",
"_PK_":"0zZlygQZ9aAqmVFPoYX5GF",
"ITEM_ID":"0zZlygQZ9aAqmVFPoYX5GF",
"ITEM_CODE":"S_USER",
"ITEM_READONLY":"2",
"ITEM_LIST_WIDTH":"0",
"ITEM_FIELD_TYPE":"STR",
"ITEM_READONLY_SCRIPT":"",
"ITEM_HIDDEN":"1",
"_ROWNUM_":"5",
"ITEM_CARD_WIDTH":"0",
"ITEM_LIST_LINK":"",
"ITEM_LIST_FLAG":"2",
"ITEM_CARD_DISABLE":"2",
"ITEM_INPUT_CONFIG":"",
"ITEM_INPUT_DEFAULT":"@USER_CODE@",
"ITEM_INPUT_FLAG":"2",
"ITEM_NOTNULL":"2",
"DICT_ID":"",
"ITEM_ORDER_CODES":"",
"ITEM_SUM_FLAG":"2",
"ITEM_LIST_EDIT":"2",
"ITEM_TYPE":"1",
"ITEM_MEMO":"添加者",
"ITEM_LABEL_HIDDEN":"0",
"ITEM_LOG_FLAG":"2",
"ITEM_CARD_STYLE":"",
"ITEM_NOTNULL_SCRIPT":"",
"ITEM_SEARCH_FLAG":"2",
"SERV_ID":"SY_COMM_LINK",
"ITEM_LIST_FORMAT":"",
"ITEM_VALIDATE":"",
"ITEM_LIST_STYLE":"",
"ITEM_CARD_COLS":"1",
"ITEM_MOBILE_TYPE":"3",
"ITEM_CARD_LINK":"",
"ITEM_HIDDEN_SCRIPT":"",
"ITEM_EXPTENDS":""
},
{
"ITEM_INPUT_MODE":"1",
"ITEM_CARD_FORMAT":"",
"S_MTIME":"2013-11-06 11:07:44:489",
"ITEM_VALIDATE_HINT":"",
"ITEM_USER_FLAG":"0",
"ITEM_NAME":"添加时间",
"ITEM_INPUT_TYPE":"1",
"ITEM_CARD_ROWS":"1",
"ITEM_LIST_ORDER":"60",
"ITEM_LIST_ALIGN":"1",
"ITEM_UNIQUE_GROUP":"0",
"ITEM_CARD_ORDER":"0",
"ITEM_FIELD_LENGTH":"23",
"S_FLAG":"1",
"ITEM_TIP":"",
"_PK_":"1_PmpOEhp1BWH12drVDdKC",
"ITEM_ID":"1_PmpOEhp1BWH12drVDdKC",
"ITEM_CODE":"S_ATIME",
"ITEM_READONLY":"2",
"ITEM_LIST_WIDTH":"0",
"ITEM_FIELD_TYPE":"STR",
"ITEM_READONLY_SCRIPT":"",
"ITEM_HIDDEN":"1",
"_ROWNUM_":"6",
"ITEM_CARD_WIDTH":"0",
"ITEM_LIST_LINK":"",
"ITEM_LIST_FLAG":"2",
"ITEM_CARD_DISABLE":"2",
"ITEM_INPUT_CONFIG":"",
"ITEM_INPUT_DEFAULT":"@DATETIME_TS@",
"ITEM_INPUT_FLAG":"2",
"ITEM_NOTNULL":"2",
"DICT_ID":"",
"ITEM_ORDER_CODES":"",
"ITEM_SUM_FLAG":"2",
"ITEM_LIST_EDIT":"2",
"ITEM_TYPE":"1",
"ITEM_MEMO":"添加时间",
"ITEM_LABEL_HIDDEN":"0",
"ITEM_LOG_FLAG":"2",
"ITEM_CARD_STYLE":"",
"ITEM_NOTNULL_SCRIPT":"",
"ITEM_SEARCH_FLAG":"2",
"SERV_ID":"SY_COMM_LINK",
"ITEM_LIST_FORMAT":"",
"ITEM_VALIDATE":"",
"ITEM_LIST_STYLE":"",
"ITEM_CARD_COLS":"1",
"ITEM_MOBILE_TYPE":"3",
"ITEM_CARD_LINK":"",
"ITEM_HIDDEN_SCRIPT":"",
"ITEM_EXPTENDS":""
},
{
"ITEM_INPUT_MODE":"1",
"ITEM_CARD_FORMAT":"",
"S_MTIME":"2013-11-06 11:07:44:489",
"ITEM_VALIDATE_HINT":"",
"ITEM_USER_FLAG":"0",
"ITEM_NAME":"修改时间",
"ITEM_INPUT_TYPE":"1",
"ITEM_CARD_ROWS":"1",
"ITEM_LIST_ORDER":"70",
"ITEM_LIST_ALIGN":"1",
"ITEM_UNIQUE_GROUP":"0",
"ITEM_CARD_ORDER":"0",
"ITEM_FIELD_LENGTH":"23",
"S_FLAG":"1",
"ITEM_TIP":"",
"_PK_":"1nRcbfqTV5m9ADKj61r1Z7",
"ITEM_ID":"1nRcbfqTV5m9ADKj61r1Z7",
"ITEM_CODE":"S_MTIME",
"ITEM_READONLY":"2",
"ITEM_LIST_WIDTH":"0",
"ITEM_FIELD_TYPE":"STR",
"ITEM_READONLY_SCRIPT":"",
"ITEM_HIDDEN":"1",
"_ROWNUM_":"7",
"ITEM_CARD_WIDTH":"0",
"ITEM_LIST_LINK":"",
"ITEM_LIST_FLAG":"2",
"ITEM_CARD_DISABLE":"2",
"ITEM_INPUT_CONFIG":"",
"ITEM_INPUT_DEFAULT":"@DATETIME_TS@",
"ITEM_INPUT_FLAG":"2",
"ITEM_NOTNULL":"2",
"DICT_ID":"",
"ITEM_ORDER_CODES":"",
"ITEM_SUM_FLAG":"2",
"ITEM_LIST_EDIT":"2",
"ITEM_TYPE":"1",
"ITEM_MEMO":"修改时间",
"ITEM_LABEL_HIDDEN":"0",
"ITEM_LOG_FLAG":"2",
"ITEM_CARD_STYLE":"",
"ITEM_NOTNULL_SCRIPT":"",
"ITEM_SEARCH_FLAG":"2",
"SERV_ID":"SY_COMM_LINK",
"ITEM_LIST_FORMAT":"",
"ITEM_VALIDATE":"",
"ITEM_LIST_STYLE":"",
"ITEM_CARD_COLS":"1",
"ITEM_MOBILE_TYPE":"3",
"ITEM_CARD_LINK":"",
"ITEM_HIDDEN_SCRIPT":"",
"ITEM_EXPTENDS":""
},
{
"ITEM_INPUT_MODE":"1",
"ITEM_CARD_FORMAT":"",
"S_MTIME":"2013-11-06 11:07:44:489",
"ITEM_VALIDATE_HINT":"",
"ITEM_USER_FLAG":"0",
"ITEM_NAME":"处室",
"ITEM_INPUT_TYPE":"1",
"ITEM_CARD_ROWS":"1",
"ITEM_LIST_ORDER":"80",
"ITEM_LIST_ALIGN":"1",
"ITEM_UNIQUE_GROUP":"0",
"ITEM_CARD_ORDER":"0",
"ITEM_FIELD_LENGTH":"40",
"S_FLAG":"1",
"ITEM_TIP":"",
"_PK_":"0CKti8gyZbi9YSYFJfUIVZ",
"ITEM_ID":"0CKti8gyZbi9YSYFJfUIVZ",
"ITEM_CODE":"S_DEPT",
"ITEM_READONLY":"2",
"ITEM_LIST_WIDTH":"0",
"ITEM_FIELD_TYPE":"STR",
"ITEM_READONLY_SCRIPT":"",
"ITEM_HIDDEN":"1",
"_ROWNUM_":"8",
"ITEM_CARD_WIDTH":"0",
"ITEM_LIST_LINK":"",
"ITEM_LIST_FLAG":"2",
"ITEM_CARD_DISABLE":"2",
"ITEM_INPUT_CONFIG":"",
"ITEM_INPUT_DEFAULT":"@DEPT_CODE@",
"ITEM_INPUT_FLAG":"2",
"ITEM_NOTNULL":"2",
"DICT_ID":"",
"ITEM_ORDER_CODES":"",
"ITEM_SUM_FLAG":"2",
"ITEM_LIST_EDIT":"2",
"ITEM_TYPE":"1",
"ITEM_MEMO":"处室",
"ITEM_LABEL_HIDDEN":"0",
"ITEM_LOG_FLAG":"2",
"ITEM_CARD_STYLE":"",
"ITEM_NOTNULL_SCRIPT":"",
"ITEM_SEARCH_FLAG":"2",
"SERV_ID":"SY_COMM_LINK",
"ITEM_LIST_FORMAT":"",
"ITEM_VALIDATE":"",
"ITEM_LIST_STYLE":"",
"ITEM_CARD_COLS":"1",
"ITEM_MOBILE_TYPE":"3",
"ITEM_CARD_LINK":"",
"ITEM_HIDDEN_SCRIPT":"",
"ITEM_EXPTENDS":""
},
{
"ITEM_INPUT_MODE":"1",
"ITEM_CARD_FORMAT":"",
"S_MTIME":"2013-11-06 11:07:44:489",
"ITEM_VALIDATE_HINT":"",
"ITEM_USER_FLAG":"0",
"ITEM_NAME":"部门",
"ITEM_INPUT_TYPE":"1",
"ITEM_CARD_ROWS":"1",
"ITEM_LIST_ORDER":"90",
"ITEM_LIST_ALIGN":"1",
"ITEM_UNIQUE_GROUP":"0",
"ITEM_CARD_ORDER":"0",
"ITEM_FIELD_LENGTH":"40",
"S_FLAG":"1",
"ITEM_TIP":"",
"_PK_":"1iUJjiFN9eAp5c9XZh-Orl",
"ITEM_ID":"1iUJjiFN9eAp5c9XZh-Orl",
"ITEM_CODE":"S_TDEPT",
"ITEM_READONLY":"2",
"ITEM_LIST_WIDTH":"0",
"ITEM_FIELD_TYPE":"STR",
"ITEM_READONLY_SCRIPT":"",
"ITEM_HIDDEN":"1",
"_ROWNUM_":"9",
"ITEM_CARD_WIDTH":"0",
"ITEM_LIST_LINK":"",
"ITEM_LIST_FLAG":"2",
"ITEM_CARD_DISABLE":"2",
"ITEM_INPUT_CONFIG":"",
"ITEM_INPUT_DEFAULT":"@TDEPT_CODE@",
"ITEM_INPUT_FLAG":"2",
"ITEM_NOTNULL":"2",
"DICT_ID":"",
"ITEM_ORDER_CODES":"",
"ITEM_SUM_FLAG":"2",
"ITEM_LIST_EDIT":"2",
"ITEM_TYPE":"1",
"ITEM_MEMO":"部门",
"ITEM_LABEL_HIDDEN":"0",
"ITEM_LOG_FLAG":"2",
"ITEM_CARD_STYLE":"",
"ITEM_NOTNULL_SCRIPT":"",
"ITEM_SEARCH_FLAG":"2",
"SERV_ID":"SY_COMM_LINK",
"ITEM_LIST_FORMAT":"",
"ITEM_VALIDATE":"",
"ITEM_LIST_STYLE":"",
"ITEM_CARD_COLS":"1",
"ITEM_MOBILE_TYPE":"3",
"ITEM_CARD_LINK":"",
"ITEM_HIDDEN_SCRIPT":"",
"ITEM_EXPTENDS":""
},
{
"ITEM_INPUT_MODE":"1",
"ITEM_CARD_FORMAT":"",
"S_MTIME":"2013-11-06 11:07:44:489",
"ITEM_VALIDATE_HINT":"",
"ITEM_USER_FLAG":"0",
"ITEM_NAME":"机构",
"ITEM_INPUT_TYPE":"1",
"ITEM_CARD_ROWS":"1",
"ITEM_LIST_ORDER":"100",
"ITEM_LIST_ALIGN":"1",
"ITEM_UNIQUE_GROUP":"0",
"ITEM_CARD_ORDER":"0",
"ITEM_FIELD_LENGTH":"40",
"S_FLAG":"1",
"ITEM_TIP":"",
"_PK_":"2HSfJAlVJ6zo8IkvmKInra",
"ITEM_ID":"2HSfJAlVJ6zo8IkvmKInra",
"ITEM_CODE":"S_ODEPT",
"ITEM_READONLY":"2",
"ITEM_LIST_WIDTH":"0",
"ITEM_FIELD_TYPE":"STR",
"ITEM_READONLY_SCRIPT":"",
"ITEM_HIDDEN":"1",
"_ROWNUM_":"10",
"ITEM_CARD_WIDTH":"0",
"ITEM_LIST_LINK":"",
"ITEM_LIST_FLAG":"2",
"ITEM_CARD_DISABLE":"2",
"ITEM_INPUT_CONFIG":"",
"ITEM_INPUT_DEFAULT":"@ODEPT_CODE@",
"ITEM_INPUT_FLAG":"2",
"ITEM_NOTNULL":"2",
"DICT_ID":"",
"ITEM_ORDER_CODES":"",
"ITEM_SUM_FLAG":"2",
"ITEM_LIST_EDIT":"2",
"ITEM_TYPE":"1",
"ITEM_MEMO":"机构",
"ITEM_LABEL_HIDDEN":"0",
"ITEM_LOG_FLAG":"2",
"ITEM_CARD_STYLE":"",
"ITEM_NOTNULL_SCRIPT":"",
"ITEM_SEARCH_FLAG":"2",
"SERV_ID":"SY_COMM_LINK",
"ITEM_LIST_FORMAT":"",
"ITEM_VALIDATE":"",
"ITEM_LIST_STYLE":"",
"ITEM_CARD_COLS":"1",
"ITEM_MOBILE_TYPE":"3",
"ITEM_CARD_LINK":"",
"ITEM_HIDDEN_SCRIPT":"",
"ITEM_EXPTENDS":""
},
{
"ITEM_INPUT_MODE":"1",
"ITEM_CARD_FORMAT":"",
"S_MTIME":"2013-11-06 11:07:44:489",
"ITEM_VALIDATE_HINT":"",
"ITEM_USER_FLAG":"0",
"ITEM_NAME":"是否启用",
"ITEM_INPUT_TYPE":"3",
"ITEM_CARD_ROWS":"1",
"ITEM_LIST_ORDER":"110",
"ITEM_LIST_ALIGN":"1",
"ITEM_UNIQUE_GROUP":"0",
"ITEM_CARD_ORDER":"0",
"ITEM_FIELD_LENGTH":"4",
"S_FLAG":"1",
"ITEM_TIP":"",
"_PK_":"3yN7k2doF3iGDJVwWI3nP9",
"ITEM_ID":"3yN7k2doF3iGDJVwWI3nP9",
"ITEM_CODE":"S_FLAG",
"ITEM_READONLY":"2",
"ITEM_LIST_WIDTH":"0",
"ITEM_FIELD_TYPE":"NUM",
"ITEM_READONLY_SCRIPT":"",
"ITEM_HIDDEN":"2",
"_ROWNUM_":"11",
"ITEM_CARD_WIDTH":"0",
"ITEM_LIST_LINK":"",
"ITEM_LIST_FLAG":"2",
"ITEM_CARD_DISABLE":"2",
"ITEM_INPUT_CONFIG":"SY_YESNO",
"ITEM_INPUT_DEFAULT":"1",
"ITEM_INPUT_FLAG":"2",
"ITEM_NOTNULL":"2",
"DICT_ID":"SY_YESNO",
"ITEM_ORDER_CODES":"",
"ITEM_SUM_FLAG":"2",
"ITEM_LIST_EDIT":"2",
"ITEM_TYPE":"1",
"ITEM_MEMO":"是否启用",
"ITEM_LABEL_HIDDEN":"0",
"ITEM_LOG_FLAG":"2",
"ITEM_CARD_STYLE":"",
"ITEM_NOTNULL_SCRIPT":"",
"ITEM_SEARCH_FLAG":"2",
"SERV_ID":"SY_COMM_LINK",
"ITEM_LIST_FORMAT":"",
"ITEM_VALIDATE":"",
"ITEM_LIST_STYLE":"",
"ITEM_CARD_COLS":"1",
"ITEM_MOBILE_TYPE":"3",
"ITEM_CARD_LINK":"",
"ITEM_HIDDEN_SCRIPT":"",
"ITEM_EXPTENDS":""
},
{
"ITEM_INPUT_MODE":"1",
"ITEM_CARD_FORMAT":"",
"S_MTIME":"2016-02-23 10:38:18:344",
"ITEM_VALIDATE_HINT":"",
"ITEM_USER_FLAG":"0",
"ITEM_NAME":"链接类型",
"ITEM_INPUT_TYPE":"3",
"ITEM_CARD_ROWS":"1",
"ITEM_LIST_ORDER":"120",
"ITEM_LIST_ALIGN":"1",
"ITEM_UNIQUE_GROUP":"0",
"ITEM_CARD_ORDER":"0",
"ITEM_FIELD_LENGTH":"4",
"S_FLAG":"1",
"ITEM_TIP":"",
"_PK_":"2z3IbGb51aAVOy8gcSbFxG",
"ITEM_ID":"2z3IbGb51aAVOy8gcSbFxG",
"ITEM_CODE":"LINK_TYPE",
"ITEM_READONLY":"2",
"ITEM_LIST_WIDTH":"0",
"ITEM_FIELD_TYPE":"NUM",
"ITEM_READONLY_SCRIPT":"",
"ITEM_HIDDEN":"2",
"_ROWNUM_":"12",
"ITEM_CARD_WIDTH":"0",
"ITEM_LIST_LINK":"",
"ITEM_LIST_FLAG":"3",
"ITEM_CARD_DISABLE":"2",
"ITEM_INPUT_CONFIG":"BN_LINK_TYPE",
"ITEM_INPUT_DEFAULT":"2",
"ITEM_INPUT_FLAG":"2",
"ITEM_NOTNULL":"2",
"DICT_ID":"BN_LINK_TYPE",
"ITEM_ORDER_CODES":"",
"ITEM_SUM_FLAG":"0",
"ITEM_LIST_EDIT":"2",
"ITEM_TYPE":"1",
"ITEM_MEMO":"链接类型：1下载；2链接",
"ITEM_LABEL_HIDDEN":"0",
"ITEM_LOG_FLAG":"2",
"ITEM_CARD_STYLE":"",
"ITEM_NOTNULL_SCRIPT":"",
"ITEM_SEARCH_FLAG":"1",
"SERV_ID":"SY_COMM_LINK",
"ITEM_LIST_FORMAT":"",
"ITEM_VALIDATE":"",
"ITEM_LIST_STYLE":"",
"ITEM_CARD_COLS":"1",
"ITEM_MOBILE_TYPE":"3",
"ITEM_CARD_LINK":"",
"ITEM_HIDDEN_SCRIPT":"",
"ITEM_EXPTENDS":""
}
],
"SERV_JS":"",
"SERV_NAV_ITEMS":"",
"SERV_CACHE_FLAG":"3",
"S_CMPY":"ruaho",
"SERV_DATA_SOURCE":"",
"S_FLAG":"1",
"SERV_DATA_CODE":"",
"SERV_PID":"",
"SERV_AUTH_FLAG":"1",
"_PK_":"SY_COMM_LINK",
"SERV_DATA_TITLE":"",
"SERV_SEARCH_FLAG":"2",
"SERV_QUERY_MODE":"1",
"SERV_NO_COUNT":"2",
"S_USER":"chensheng",
"SERV_RED_HEAD":"",
"SAFE_FLAG":"0",
"SY_SERV_QUERY":
[
],
"_ROWNUM_":"0",
"SERV_DICT_CACHE":"",
"SERV_PAGE_COUNT":"50",
"SERV_CARD_LOAD":"2",
"SERV_KEYS":"LINK_ID",
"SERV_CLASS":"com.rh.core.comm.news.link.LinkServ",
"SERV_CMPY":"",
"SERV_DELETE_FLAG":"2",
"SERV_CARD_STYLE":"2",
"SERV_NAME":"常用链接",
"SERV_LIST_STYLE":"",
"SERV_MOBILE_LIST":"",
"SERV_RELATE_CONFIG":"",
"SERV_LIST_LOAD":"1",
"SERV_ID":"SY_COMM_LINK",
"SERV_SQL_ORDER":"LINK_SORT asc",
"SERV_CARD_TMPL":"2",
"SERV_WF_FLAG":"2",
"SERV_RELATE_FLAG":"0",
"SY_SERV_LINK":
[
],
"SY_SERV_ACT":
[
{
"ACT_TYPE":"3",
"LIST_DIS_GROUP":"",
"ACT_EXPRESSION_FLAG":"0",
"ACT_CSS":"byid",
"ACT_MEMO":"",
"ACT_CODE":"byid",
"S_FLAG":"1",
"ACT_WS_FLAG":"2",
"_PK_":"2R2-aUN4B9RFUiZ9E3UDHx",
"ACT_LOG_FLAG":"2",
"ACT_HOT_KEY":"",
"ACT_ID":"2R2-aUN4B9RFUiZ9E3UDHx",
"SERV_ID":"SY_COMM_LINK",
"S_MTIME":"2016-03-24 17:54:08:160",
"ACT_EXPRESSION":"",
"ACT_WS_RESULT":"",
"ACT_MOBILE_FLAG":"1",
"ACT_ORDER":"10",
"ACT_GROUP":"2",
"SY_SERV_ACT_PARAM":
[
],
"_ROWNUM_":"0",
"ACT_TIP":"",
"ACT_NAME":" 查 看 "
},
{
"ACT_TYPE":"1",
"LIST_DIS_GROUP":"",
"ACT_EXPRESSION_FLAG":"0",
"ACT_CSS":"add",
"ACT_MEMO":"",
"ACT_CODE":"add",
"S_FLAG":"1",
"ACT_WS_FLAG":"2",
"_PK_":"3dBj8Kt_5f8UYUBFDCleu8",
"ACT_LOG_FLAG":"2",
"ACT_HOT_KEY":"",
"ACT_ID":"3dBj8Kt_5f8UYUBFDCleu8",
"SERV_ID":"SY_COMM_LINK",
"S_MTIME":"2013-11-06 11:07:44:494",
"ACT_EXPRESSION":"",
"ACT_WS_RESULT":"",
"ACT_MOBILE_FLAG":"1",
"ACT_ORDER":"20",
"ACT_GROUP":"1",
"SY_SERV_ACT_PARAM":
[
],
"_ROWNUM_":"1",
"ACT_TIP":"",
"ACT_NAME":" 新 建"
},
{
"ACT_TYPE":"1",
"LIST_DIS_GROUP":"",
"ACT_EXPRESSION_FLAG":"0",
"ACT_CSS":"batchSave",
"ACT_MEMO":"",
"ACT_CODE":"batchSave",
"S_FLAG":"2",
"ACT_WS_FLAG":"2",
"_PK_":"3_xxrU6y52G8I0FkG-xG2H",
"ACT_LOG_FLAG":"2",
"ACT_HOT_KEY":"",
"ACT_ID":"3_xxrU6y52G8I0FkG-xG2H",
"SERV_ID":"SY_COMM_LINK",
"S_MTIME":"2013-11-06 11:07:44:494",
"ACT_EXPRESSION":"",
"ACT_WS_RESULT":"",
"ACT_MOBILE_FLAG":"1",
"ACT_ORDER":"30",
"ACT_GROUP":"1",
"SY_SERV_ACT_PARAM":
[
],
"_ROWNUM_":"2",
"ACT_TIP":"",
"ACT_NAME":" 保 存 "
},
{
"ACT_TYPE":"2",
"LIST_DIS_GROUP":"",
"ACT_EXPRESSION_FLAG":"0",
"ACT_CSS":"save",
"ACT_MEMO":"",
"ACT_CODE":"save",
"S_FLAG":"1",
"ACT_WS_FLAG":"2",
"_PK_":"37F8kbgcpaKWC6C2DlkFXB",
"ACT_LOG_FLAG":"2",
"ACT_HOT_KEY":"",
"ACT_ID":"37F8kbgcpaKWC6C2DlkFXB",
"SERV_ID":"SY_COMM_LINK",
"S_MTIME":"2016-03-23 09:13:14:326",
"ACT_EXPRESSION":"",
"ACT_WS_RESULT":"",
"ACT_MOBILE_FLAG":"1",
"ACT_ORDER":"50",
"ACT_GROUP":"1",
"SY_SERV_ACT_PARAM":
[
],
"_ROWNUM_":"3",
"ACT_TIP":"",
"ACT_NAME":" 保 存 "
},
{
"ACT_TYPE":"2",
"LIST_DIS_GROUP":"",
"ACT_EXPRESSION_FLAG":"0",
"ACT_CSS":"copy",
"ACT_MEMO":"",
"ACT_CODE":"copyNew",
"S_FLAG":"2",
"ACT_WS_FLAG":"2",
"_PK_":"3aVNDD0llbr9WTCSirRqUR",
"ACT_LOG_FLAG":"2",
"ACT_HOT_KEY":"",
"ACT_ID":"3aVNDD0llbr9WTCSirRqUR",
"SERV_ID":"SY_COMM_LINK",
"S_MTIME":"2013-11-06 11:07:44:494",
"ACT_EXPRESSION":"'#_ADD_#'==''",
"ACT_WS_RESULT":"",
"ACT_MOBILE_FLAG":"1",
"ACT_ORDER":"60",
"ACT_GROUP":"1",
"SY_SERV_ACT_PARAM":
[
],
"_ROWNUM_":"4",
"ACT_TIP":"",
"ACT_NAME":"复制并新建"
},
{
"ACT_TYPE":"2",
"LIST_DIS_GROUP":"",
"ACT_EXPRESSION_FLAG":"0",
"ACT_CSS":"search",
"ACT_MEMO":"",
"ACT_CODE":"logItem",
"S_FLAG":"2",
"ACT_WS_FLAG":"2",
"_PK_":"3UCdXEKk96XqagAcjmrE_v",
"ACT_LOG_FLAG":"2",
"ACT_HOT_KEY":"",
"ACT_ID":"3UCdXEKk96XqagAcjmrE_v",
"SERV_ID":"SY_COMM_LINK",
"S_MTIME":"2013-11-06 11:07:44:494",
"ACT_EXPRESSION":"'#_ADD_#'==''",
"ACT_WS_RESULT":"",
"ACT_MOBILE_FLAG":"1",
"ACT_ORDER":"70",
"ACT_GROUP":"2",
"SY_SERV_ACT_PARAM":
[
],
"_ROWNUM_":"5",
"ACT_TIP":"",
"ACT_NAME":"变更历史"
},
{
"ACT_TYPE":"1",
"LIST_DIS_GROUP":"",
"ACT_EXPRESSION_FLAG":"0",
"ACT_CSS":"delete",
"ACT_MEMO":"",
"ACT_CODE":"delete",
"S_FLAG":"1",
"ACT_WS_FLAG":"2",
"_PK_":"3H0r4lXzdctWIL1o6pLEHK",
"ACT_LOG_FLAG":"1",
"ACT_HOT_KEY":"",
"ACT_ID":"3H0r4lXzdctWIL1o6pLEHK",
"SERV_ID":"SY_COMM_LINK",
"S_MTIME":"2013-11-06 11:07:44:494",
"ACT_EXPRESSION":"",
"ACT_WS_RESULT":"",
"ACT_MOBILE_FLAG":"1",
"ACT_ORDER":"100",
"ACT_GROUP":"1",
"SY_SERV_ACT_PARAM":
[
],
"_ROWNUM_":"6",
"ACT_TIP":"",
"ACT_NAME":" 删 除 "
},
{
"ACT_TYPE":"1",
"LIST_DIS_GROUP":"",
"ACT_EXPRESSION_FLAG":"0",
"ACT_CSS":"imp",
"ACT_MEMO":"",
"ACT_CODE":"imp",
"S_FLAG":"2",
"ACT_WS_FLAG":"2",
"_PK_":"262YCc6AZcFbzeJ8CM8Oas",
"ACT_LOG_FLAG":"2",
"ACT_HOT_KEY":"",
"ACT_ID":"262YCc6AZcFbzeJ8CM8Oas",
"SERV_ID":"SY_COMM_LINK",
"S_MTIME":"2013-11-06 11:07:44:494",
"ACT_EXPRESSION":"",
"ACT_WS_RESULT":"",
"ACT_MOBILE_FLAG":"1",
"ACT_ORDER":"110",
"ACT_GROUP":"1",
"SY_SERV_ACT_PARAM":
[
],
"_ROWNUM_":"7",
"ACT_TIP":"",
"ACT_NAME":" 导 入 "
},
{
"ACT_TYPE":"1",
"LIST_DIS_GROUP":"",
"ACT_EXPRESSION_FLAG":"0",
"ACT_CSS":"exp",
"ACT_MEMO":"",
"ACT_CODE":"exp",
"S_FLAG":"2",
"ACT_WS_FLAG":"2",
"_PK_":"0WGDYPGGNfyUcUUy-xDaGy",
"ACT_LOG_FLAG":"2",
"ACT_HOT_KEY":"",
"ACT_ID":"0WGDYPGGNfyUcUUy-xDaGy",
"SERV_ID":"SY_COMM_LINK",
"S_MTIME":"2013-11-06 11:07:44:494",
"ACT_EXPRESSION":"",
"ACT_WS_RESULT":"",
"ACT_MOBILE_FLAG":"1",
"ACT_ORDER":"120",
"ACT_GROUP":"2",
"SY_SERV_ACT_PARAM":
[
],
"_ROWNUM_":"8",
"ACT_TIP":"",
"ACT_NAME":" 导 出 "
},
{
"ACT_TYPE":"2",
"LIST_DIS_GROUP":"",
"ACT_EXPRESSION_FLAG":"0",
"ACT_CSS":"exp",
"ACT_MEMO":"this.transmit();",
"ACT_CODE":"transmit",
"S_FLAG":"2",
"ACT_WS_FLAG":"2",
"_PK_":"0sPbUD60JbvXUE-mXy9fl_",
"ACT_LOG_FLAG":"2",
"ACT_HOT_KEY":"",
"ACT_ID":"0sPbUD60JbvXUE-mXy9fl_",
"SERV_ID":"SY_COMM_LINK",
"S_MTIME":"2013-11-06 11:07:44:494",
"ACT_EXPRESSION":"",
"ACT_WS_RESULT":"",
"ACT_MOBILE_FLAG":"1",
"ACT_ORDER":"120",
"ACT_GROUP":"2",
"SY_SERV_ACT_PARAM":
[
],
"_ROWNUM_":"9",
"ACT_TIP":"",
"ACT_NAME":" 转 发 "
},
{
"ACT_TYPE":"2",
"LIST_DIS_GROUP":"",
"ACT_EXPRESSION_FLAG":"0",
"ACT_CSS":"imp",
"ACT_MEMO":"this.receive();",
"ACT_CODE":"receive",
"S_FLAG":"2",
"ACT_WS_FLAG":"2",
"_PK_":"0ugr6-_VN5GUzxqcsZdxli",
"ACT_LOG_FLAG":"2",
"ACT_HOT_KEY":"",
"ACT_ID":"0ugr6-_VN5GUzxqcsZdxli",
"SERV_ID":"SY_COMM_LINK",
"S_MTIME":"2013-11-06 11:07:44:494",
"ACT_EXPRESSION":"",
"ACT_WS_RESULT":"",
"ACT_MOBILE_FLAG":"1",
"ACT_ORDER":"130",
"ACT_GROUP":"2",
"SY_SERV_ACT_PARAM":
[
],
"_ROWNUM_":"10",
"ACT_TIP":"",
"ACT_NAME":" 接 收 "
}
],
"SERV_MEMO":""
}